Workbook
Name Fore: #REF!
Name Fore: #REF!
Name Fore: #REF!
Name Fore: #REF!
Name Fore: #REF!
Name Fore: #REF!
Name Fore: #REF!
Name Fore: #REF!
Name Fore: #REF!
Name Fore: #REF!
Name Fore: #REF!
Name Fore: #REF!
Name Fore: #REF!
Name Fore: #REF!
Name Fore: #REF!
Name OLE_LINK11: Readme_Part_2!$B$61
Name OLE_LINK6: Readme_Intro!$B$44
Name Parmtype: #REF!
Name Parmtype: #REF!
Name Parmtype: #REF!
Name Parmtype: policy_parameters_uniformity!#REF!
Name Parmtype: policy_parameters_comprehensive!#REF!
Name Sheet: #REF!
Name Sheet: #REF!
Name Sheet: #REF!
Name Sheet: policy_parameters_uniformity!#REF!
Name Sheet: policy_parameters_comprehensive!#REF!

Sheet Readme_Intro
A1: Contents
B2: Part 1: Parameters defining tax rates and other general policy choices
C3: A. Introduction
C4: B. Sheets provided (links included in Readme_Part_1)
D5: Sheets formatted for user input
E6: policy_parameters.Current_law_C
E7: policy_parameters.Current_law_U
E8: csv_selection
D9: Sheets formatted to create a csv file for the model to use
E10: policy_parameters_comprehensive
E11: policy_parameters_uniformity
C12: C. How to estimate parameter values that are consistent with the uniformity perspective
C13: D. How to create alternative csv files for Part 1 parameters
B14: Part 2: Parameters defining depreciation rules, investment tax credit rules, production tax credit rules, and marginal tax rate adjustments
C15: A. Introduction
C16: B. Sheets provided (links included in Readme_Part_2.x.y)
D17: Part_2.1.1: Multi-year depreciation parameters
E18: recovery_periods_ | H18: one sheet
E19: acceleration_rates_ | H19: one sheet
E20: straight_line_flags_ | H20: one sheet
E21: inflation_adjustments_ | H21: one sheet
E22: IRS asset class mapping | H22: documentation only: not for csv
D23: Part_2.1.2: Expensing parameters
E24: sec_179_expens_shares_ | H24: three sheets
E25: other_expens_shares_ | H25: two sheets
D26: Part_2.2: Investment tax credit parameters
E27: itc_rates_ | H27: two sheets
E28: itc_nondeprcbl_bases_ | H28: one sheet
D29: Part_2.3: Production tax credit parameters
E30: ptc_rates_ | H30: nine sheets
D31: Part_2.4: Marginal_tax rate adjustment parameters
E32: sec_199A_adjustments_ | H32: one sheet
E33: industry_adjustments_ | H33: one sheet
E34: asset_adjustments_ | H34: one sheet
E35: Interaction check | H35: utility only: not for csv
C36: C. Part 2 worksheet naming conventions
C37: D. Guide to color-coding in Part 2 worksheets
C38: E. How to estimate parameter values that are consistent with the uniformity perspective
C39: F. How to create alternative csv files for Part 2 parameters

Sheet Readme_Part_1
A1: Part 1: Parameters defining tax rates and other general policy choices
B3: A. Introduction
C4: Parameters in Part 1 vary by year. The sheets provided contain current law values from 2026 through 2036.
C5: ▪ | D5: To see the list of sheets provided, click here.
C6: Most of the parameters are numerical values, such as tax rates, but one set of parameters (rows 49-67) contains character values that tell the model which parameter files to use from Part 2. The Readme files for Part 2 will explain how to select values for those parameters. The model expects two .csv files--one containing parameter values consistent with the comprehensive perspective, and one containing parameter values consistent with the uniformity perspective.
C7: ▪ | D7: For guidance on how to make parameter values consistent with the uniformity perspective, click here.
C8: ▪ | D8: For guidance on how to create the two .csv files, click here.
B10: B. Sheets provided (consistent with CBO's Winter 2026 baseline)
B12: · Sheets formatted for user input
C13: policy_parameters.Current_law_C
D14: This sheet contains policy parameter values that are consistent with current law under the comprehensive analytical perspective.
C15: policy_parameters.Current_law_U
D16: This sheet contains the same policy parameters as the comprehensive sheet, but the values are consistent with the tax uniformity analytical perspective. Values that differ from the comprehensive sheet are rendered in dark red.
C17: csv_selection
D18: Use this sheet to select which of the available policy_parameter sheets to write as .csv files for the model to use.
B20: · Sheets formatted to generate a .csv file for the model to use
C21: policy_parameters_comprehensive
C22: policy_parameters_uniformity
D23: Do not make changes to the cells in these sheets. Doing so will break the links with sheets formatted for user input. If you want to make changes directly to a .csv file, read that .csv file into Excel, make the changes, and save it.
B25: C. How to estimate parameter values that are consistent with the uniformity perspective
B27: The uniformity perspective is intended to illuminate differences in tax treatment among different industries, asset types, legal forms of organization, and sources of financing. Under the comprehensive perspective, however, some parameter values differ for other reasons. Among Part 1 parameters, those fall into three categories:
B28: 1. | C28: Marginal individual income tax rates. Under the comprehensive perspective, individual income tax rates that apply to different sources of income or deductions reflect the circumstances (specifically, the taxable income from all sources) of the recipients of that income or claimants of those deductions. Because each source of income is distributed differently across the income scale, each source will face a different average marginal tax rate. Under the uniformity perspective, however, individual income tax rates should be independent of the circumstances of the recipients and claimants. Any differences should reflect only differences in the tax law. Under current law, CBO recognizes only four distinct categories of individual income tax rates that are defined solely by the tax law. The following table lists the four categories, the income sources and deductions that belong to each, and 2025 values under each perspective as an illustration:
D30: Income source | F30: 2026 value under the comprehensive perspective | H30: 2026 value under the uniformity perspective
C31: a. | D31: Capital gains held until death | F31: 0 | H31: 0
C32: b. | D32: Income from nontaxable retirement accounts | F32: 0 | H32: 0
C33: c. | D33: Income subject to a 20% maximum rate
D34: Dividends | F34: 0.1997 | H34: 0.2092
D35: Long-term capital gains | F35: 0.2116 | H35: 0.2092
C36: d. | D36: Income and deductions subject to the ordinary rate schedule
D37: Profits from pass-through businesses | F37: 0.3042 | H37: 0.2776
D38: Interest | F38: 0.3036 | H38: 0.2776
D39: Short-term capital gains | F39: 0.3495 | H39: 0.2776
D40: Income from temporarily tax-deferred accounts | F40: 0.231 | H40: 0.2776
D41: Home mortgage interest deductions | F41: 0.1949 | H41: 0.2776
D42: Homeowner property tax deductions | F42: 0.1776 | H42: 0.2776
C43: For category c, CBO calculated an average rate using (1 -c_corp_equity_retained_earnings_share)*(1-c_corp_equity_repurchases_share) as the weight on dividends and 1 minus that share as the weight on long-term capital gains. For category d, CBO calculated an average rate from interest (weighted by the share of marginal investment financed by debt) and short-term capital gains (weighted by the share of marginal investment financed by equity).
C44: You are not bound by the groupings in the above table. You can group sources however you like as long as the groupings are driven by explicit policy choices, not by correlations.
B46: 2. | C46: Business interest deduction limitations: The limitations on the deductibility of business interest expenses apply only above certain gross receipts thresholds. Because of their size, many more C corporations are subject to those limitations than are pass-through entities. Therefore, under the comprehensive perspective, the deductible share of C corporation interest is lower than that for pass-through entities. That difference, however, is driven by the average business size, not the tax law. Thus, under the uniformity perspective, CBO used an average deductible share for both organizational forms using each form’s share of interest paid as the weights.
D47: Legal form of organization | F47: 2026 value under the comprehensive perspective | H47: 2026 value under the uniformity perspective
D48: C Corporations | F48: 0.9884 | H48: 0.9888
D49: Pass-through businesses | F49: 0.9933 | H49: 0.9888
C50: If you want to simulate a policy that imposes different deductibility rules on each form of organization, then you should use the same values for the uniformity perspective as for the comprehensive perspective.
B52: 3. | C52: Account category: Savers may place any combination of debt instruments and C corporation equities into nontaxable retirement accounts subject to statutory limits on annual contributions. In practice, however, they are much more likely to place the debt and equity of C corporations into such accounts than debt issued by pass-through entities or owner-occupied housing. The comprehensive perspective takes those differences into account. Because those differences are not driven by the current tax law, however, the share placed in nontaxable (or temporarily-deferred) accounts should not vary by instrument type under the uniformity perspective. CBO calculate weighted average shares allocated to nontaxable and temporarily-deferred accounts using debt and equity shares of account balances derived from the Financial Accounts of the United States as weights. The equity of pass-through entities and owner-occupied housing cannot be placed in such accounts without incurring unrelated business income tax. Thus, the uniformity perspective should recognize that effective prohibition and assign all such equity to taxable accounts, just as under the comprehensive perspective. The following table illustrates the different treatment of shares in nontaxable accounts.
D54: Legal form of organization/source of financing | F54: 2026 value under the comprehensive perspective | H54: 2026 value under the uniformity perspective
D55: C Corporation equity | F55: 0.3424 | H55: 0.3488
D56: C Corporation debt | F56: 0.4205 | H56: 0.3488
D57: Pass-through equity | F57: 0 | H57: 0
D58: Pass-through debt | F58: 0.1829 | H58: 0.3488
D59: Owner-occupied housing equity | F59: 0 | H59: 0
D60: Owner-occupied housing debt | F60: 0.1295 | H60: 0.3488
C61: If your policy regarding retirement saving explicitly distinguishes between the equity and debt of C corporations or between the debt of different organizational forms, then the parameter values under the uniformity perspective should reflect those distinctions.
B63: D. How to create alternative .csv files for Part 1 parameters
B65: 1. | C65: Copy an existing sheet that contains parameters consistent with the comprehensive perspective and replace the descriptive suffix after the period with one that is appropriate for the simulation you are creating. Note that Excel will trunctate suffixes at 13 characters.
B66: 2. | C66: Repeat Step 1 for parameters consistent with the uniformity perspective.
B67: 3. | C67: Enter new parameter values into yellow-shaded cells of both of the new sheets. If you simulation involves any changes to lines 49-67, you will have to complete all steps in Part 2 before making those changes. You can enter values into unshaded cells, but you will wipe out formulas in the process. If you add new lines or change the order of existing lines, the links to the sheets from which .csv files are generated will not work properly.
B68: 4. | C68: Go to the csv_selection sheet and enter the suffixes of the sheets for which you want to run a simulation into cells C1 (for the comprehensive perspective) and C2 (for the uniformity perspective). For example, to run current law, you would enter Current_law_C into cell C1 and Current_law_U into cell C2.
B69: 5. | C69: Save the entire workbook as an Excel file.
B70: 6. | C70: Go to the policy_parameters_comprehensive sheet and save it as a .csv file using the following steps:
C71: a. | D71: Click on 'Save As', then navigate to the \captax\captax\data\inputs\policy_parameters folder.
C72: b. | D72: In the 'Save as type' box, select 'CSV (comma delimited)'.
C73: c. | D73: From the list of files in the folder, select the file named policy_parameters_Current-Law_comprehensive, but do not click 'Save'.
C74: d. | D74: Replace Current-Law in the 'File name' box with a new descriptive suffix, retaining the underscores on either side. It does not have to be the same suffix as the one entered on the csv_selection sheet--it can be more descriptive if you like. You will provide this file name to the model when you run it.
C75: e. | D75: Click 'Save'.
B76: 7. | C76: Repeat Step 6 for the policy_parameters_uniformity sheet.
B77: 8. | C77: Close the workbook without saving the changes in Steps 6 and 7.
B78: 9. | C78: If you want to verify the contents of the .csv files, reopen the workbook and go to the policy_parameters_comprehensive sheet. Then open the .csv file you created in Step 6 and compare the two. For the uniformity perspective, go to the policy_parameters_uniformity sheet and compare it to the .csv file you created in Step 7.

Sheet policy_parameters.Current_law_C
A1: Variable names from working paper | C1: Variable names in csv file | D1: Template for policy parameter values under the comprehensive perspective
C2: year | D2: 2026 | E2: 2027 | F2: 2028 | G2: 2029 | H2: 2030 | I2: 2031 | J2: 2032 | K2: 2033 | L2: 2034 | M2: 2035 | N2: 2036
A3: Tax Rate Parameters
B4: Taxes on profits/imputed rent
A5: t[cc] | C5: c_corp_tax_rate | D5: 0.21 | E5: 0.21 | F5: 0.21 | G5: 0.21 | H5: 0.21 | I5: 0.21 | J5: 0.21 | K5: 0.21 | L5: 0.21 | M5: 0.21 | N5: 0.21
A6: t[pt] | C6: pass_thru_tax_rate | D6: 0.3042 | E6: 0.3056 | F6: 0.3051 | G6: 0.3103 | H6: 0.3121 | I6: 0.312 | J6: 0.3121 | K6: 0.3123 | L6: 0.3139 | M6: 0.3139 | N6: 0.3164
A7: t[se] | C7: seca_tax_rate | D7: 0.0352 | E7: 0.0352 | F7: 0.0352 | G7: 0.0352 | H7: 0.0352 | I7: 0.0352 | J7: 0.0352 | K7: 0.0352 | L7: 0.0352 | M7: 0.0353 | N7: 0.0353
A8: t[rep] | C8: repurchases_tax_rate | D8: 0.01 | E8: 0.01 | F8: 0.01 | G8: 0.01 | H8: 0.01 | I8: 0.01 | J8: 0.01 | K8: 0.01 | L8: 0.01 | M8: 0.01 | N8: 0.01
A9: t[oh] | C9: ooh_tax_rate | D9: 0 | E9: 0 | F9: 0 | G9: 0 | H9: 0 | I9: 0 | J9: 0 | K9: 0 | L9: 0 | M9: 0 | N9: 0
B10: Individual income taxes on investment income
A11: t[div] | C11: dividend_inc_tax_rate | D11: 0.1997 | E11: 0.1999 | F11: 0.2006 | G11: 0.1968 | H11: 0.1991 | I11: 0.2 | J11: 0.2018 | K11: 0.2003 | L11: 0.2022 | M11: 0.2019 | N11: 0.2063
A12: t[scg] | C12: cap_gains_short_term_tax_rate | D12: 0.3495 | E12: 0.3445 | F12: 0.3409 | G12: 0.3347 | H12: 0.3331 | I12: 0.3322 | J12: 0.33 | K12: 0.3308 | L12: 0.332 | M12: 0.3317 | N12: 0.3339
A13: t[lcg] | C13: cap_gains_long_term_tax_rate | D13: 0.2116 | E13: 0.2095 | F13: 0.2072 | G13: 0.2051 | H13: 0.2041 | I13: 0.2038 | J13: 0.2042 | K13: 0.2046 | L13: 0.2049 | M13: 0.2042 | N13: 0.2052
A14: t[xcg] | C14: cap_gains_at_death_tax_rate | D14: 0 | E14: 0 | F14: 0 | G14: 0 | H14: 0 | I14: 0 | J14: 0 | K14: 0 | L14: 0 | M14: 0 | N14: 0
A15: t[int,cc] | C15: interest_inc_from_biz_tax_rate | D15: 0.3036 | E15: 0.3044 | F15: 0.3045 | G15: 0.3041 | H15: 0.3064 | I15: 0.3056 | J15: 0.3041 | K15: 0.3064 | L15: 0.3056 | M15: 0.3061 | N15: 0.3089
A16: t[int,oh] | C16: interest_inc_from_ooh_tax_rate | D16: 0.3036 | E16: 0.3044 | F16: 0.3045 | G16: 0.3041 | H16: 0.3064 | I16: 0.3056 | J16: 0.3041 | K16: 0.3064 | L16: 0.3056 | M16: 0.3061 | N16: 0.3089
A17: t[td] | C17: ret_plan_deferred_tax_rate | D17: 0.231 | E17: 0.2308 | F17: 0.2339 | G17: 0.2311 | H17: 0.2331 | I17: 0.2341 | J17: 0.2359 | K17: 0.2381 | L17: 0.2364 | M17: 0.2379 | N17: 0.238
A18: t[nt] | C18: ret_plan_nontaxable_tax_rate | D18: 0 | E18: 0 | F18: 0 | G18: 0 | H18: 0 | I18: 0 | J18: 0 | K18: 0 | L18: 0 | M18: 0 | N18: 0
B19: Individual income taxes that apply to itemized deductions
A20: t[hmi] | C20: mortg_interest_deduction_tax_rate | D20: 0.1949 | E20: 0.1947 | F20: 0.1943 | G20: 0.1976 | H20: 0.1978 | I20: 0.1978 | J20: 0.1983 | K20: 0.1988 | L20: 0.1996 | M20: 0.2006 | N20: 0.2015
A21: t[ptx] | C21: prop_tax_deduction_tax_rate | D21: 0.1776 | E21: 0.1778 | F21: 0.1774 | G21: 0.1817 | H21: 0.1816 | I21: 0.1814 | J21: 0.1816 | K21: 0.1818 | L21: 0.1823 | M21: 0.1828 | N21: 0.1836
A22: Deduction Parameters
A23: ξ | C23: pass_thru_inc_share_below_thresholds | D23: 0.3225 | E23: 0.318 | F23: 0.3209 | G23: 0.3133 | H23: 0.305 | I23: 0.3035 | J23: 0.3006 | K23: 0.2979 | L23: 0.2948 | M23: 0.2919 | N23: 0.2896
A24: q^ | C24: pass_thru_eligibility_below_thresholds | D24: 0.7734 | E24: 0.7741 | F24: 0.7749 | G24: 0.775 | H24: 0.7743 | I24: 0.7744 | J24: 0.774 | K24: 0.7738 | L24: 0.7739 | M24: 0.7732 | N24: 0.773
A25: θ[cc] | C25: c_corp_interest_deductible_share | D25: 0.9884 | E25: 0.9815 | F25: 0.9768 | G25: 0.9739 | H25: 0.9724 | I25: 0.9723 | J25: 0.9727 | K25: 0.9733 | L25: 0.9736 | M25: 0.9738 | N25: 0.9743
A26: θ[pt] | C26: pass_thru_interest_deductible_share | D26: 0.9933 | E26: 0.9894 | F26: 0.9867 | G26: 0.985 | H26: 0.9841 | I26: 0.9841 | J26: 0.9842 | K26: 0.9846 | L26: 0.9848 | M26: 0.9849 | N26: 0.9852
A27: θ[oh] | C27: mortg_interest_deductible_share | D27: 0.5552 | E27: 0.5876 | F27: 0.6222 | G27: 0.6473 | H27: 0.5526 | I27: 0.5723 | J27: 0.589 | K27: 0.6036 | L27: 0.6137 | M27: 0.6211 | N27: 0.6253
A28: λ | C28: prop_tax_deductible_share | D28: 0.3457 | E28: 0.356 | F28: 0.3709 | G28: 0.3781 | H28: 0.0435 | I28: 0.0436 | J28: 0.0424 | K28: 0.0413 | L28: 0.04 | M28: 0.0383 | N28: 0.0365
A29: Timing Adjustment Parameters Reflecting Fluctuating Rates of Return
B30: Ratio of PV of item to nominal item
A31: ν[cc,inc] | C31: c_corp_net_inc_timing_adjustment | D31: 1 | E31: 1 | F31: 1 | G31: 1 | H31: 1 | I31: 1 | J31: 1 | K31: 1 | L31: 1 | M31: 1 | N31: 1
A32: ν[pt,inc] | C32: pass_thru_net_inc_timing_adjustment | D32: 1 | E32: 1 | F32: 1 | G32: 1 | H32: 1 | I32: 1 | J32: 1 | K32: 1 | L32: 1 | M32: 1 | N32: 1
A33: ν[se,inc] | C33: seca_net_inc_timing_adjustment | D33: 1 | E33: 1 | F33: 1 | G33: 1 | H33: 1 | I33: 1 | J33: 1 | K33: 1 | L33: 1 | M33: 1 | N33: 1
A34: ν[cc,ded] | C34: c_corp_deductions_timing_adjustment | D34: 1 | E34: 1 | F34: 1 | G34: 1 | H34: 1 | I34: 1 | J34: 1 | K34: 1 | L34: 1 | M34: 1 | N34: 1
A35: ν[pt,ded] | C35: pass_thru_deductions_timing_adjustment | D35: 1 | E35: 1 | F35: 1 | G35: 1 | H35: 1 | I35: 1 | J35: 1 | K35: 1 | L35: 1 | M35: 1 | N35: 1
A36: ν[se,ded] | C36: seca_deductions_timing_adjustment | D36: 1 | E36: 1 | F36: 1 | G36: 1 | H36: 1 | I36: 1 | J36: 1 | K36: 1 | L36: 1 | M36: 1 | N36: 1
A37: ν[cc,crd] | C37: c_corp_credits_timing_adjustment | D37: 1 | E37: 1 | F37: 1 | G37: 1 | H37: 1 | I37: 1 | J37: 1 | K37: 1 | L37: 1 | M37: 1 | N37: 1
A38: ν[pt,crd] | C38: pass_thru_credits_timing_adjustment | D38: 1 | E38: 1 | F38: 1 | G38: 1 | H38: 1 | I38: 1 | J38: 1 | K38: 1 | L38: 1 | M38: 1 | N38: 1
A39: Additive Annual Changes to Holding Period Parameters
A40: ω[stg] Δ | C40: change_cap_gains_short_term_share | D40: 0 | E40: 0 | F40: 0 | G40: 0 | H40: 0 | I40: 0 | J40: 0 | K40: 0 | L40: 0 | M40: 0 | N40: 0
A41: ω[xtg] Δ | C41: change_cap_gains_at_death_share | D41: 0 | E41: 0 | F41: 0 | G41: 0 | H41: 0 | I41: 0 | J41: 0 | K41: 0 | L41: 0 | M41: 0 | N41: 0
A42: Y[stg] Δ | C42: change_cap_gains_short_term_holding_period | D42: 0 | E42: 0 | F42: 0 | G42: 0 | H42: 0 | I42: 0 | J42: 0 | K42: 0 | L42: 0 | M42: 0 | N42: 0
A43: Y[ltg] Δ | C43: change_cap_gains_long_term_holding_period | D43: 0 | E43: 0 | F43: 0 | G43: 0 | H43: 0 | I43: 0 | J43: 0 | K43: 0 | L43: 0 | M43: 0 | N43: 0
A44: Y[xtg] Δ | C44: change_cap_gains_at_death_holding_period | D44: 0 | E44: 0 | F44: 0 | G44: 0 | H44: 0 | I44: 0 | J44: 0 | K44: 0 | L44: 0 | M44: 0 | N44: 0
A45: Y[td] Δ | C45: change_ret_plan_deferred_holding_period | D45: 0 | E45: 0 | F45: 0 | G45: 0 | H45: 0 | I45: 0 | J45: 0 | K45: 0 | L45: 0 | M45: 0 | N45: 0
A46: Y[nt] Δ | C46: change_ret_plan_nontaxable_holding_period | D46: 0 | E46: 0 | F46: 0 | G46: 0 | H46: 0 | I46: 0 | J46: 0 | K46: 0 | L46: 0 | M46: 0 | N46: 0
A47: Y[inv] Δ | C47: change_inventories_holding_period | D47: 0 | E47: 0 | F47: 0 | G47: 0 | H47: 0 | I47: 0 | J47: 0 | K47: 0 | L47: 0 | M47: 0 | N47: 0
A48: File Extensions Pointing to Depreciation, ITC & Rate Adjustment Parameters
B49: Cost recovery deduction parameters
A50: L[j,a] suffix | C50: recovery_periods | D50: CLaw_perm | E50: CLaw_perm | F50: CLaw_perm | G50: CLaw_perm | H50: CLaw_perm | I50: CLaw_perm | J50: CLaw_perm | K50: CLaw_perm | L50: CLaw_perm | M50: CLaw_perm | N50: CLaw_perm
A51: b[j,a] suffix | C51: acceleration_rates | D51: CLaw_perm | E51: CLaw_perm | F51: CLaw_perm | G51: CLaw_perm | H51: CLaw_perm | I51: CLaw_perm | J51: CLaw_perm | K51: CLaw_perm | L51: CLaw_perm | M51: CLaw_perm | N51: CLaw_perm
A52: p[j,a] suffix | C52: straight_line_flags | D52: CLaw_perm | E52: CLaw_perm | F52: CLaw_perm | G52: CLaw_perm | H52: CLaw_perm | I52: CLaw_perm | J52: CLaw_perm | K52: CLaw_perm | L52: CLaw_perm | M52: CLaw_perm | N52: CLaw_perm
A53: ι[j,a] suffix | C53: inflation_adjustments | D53: CLaw_perm | E53: CLaw_perm | F53: CLaw_perm | G53: CLaw_perm | H53: CLaw_perm | I53: CLaw_perm | J53: CLaw_perm | K53: CLaw_perm | L53: CLaw_perm | M53: CLaw_perm | N53: CLaw_perm
A54: x[179,j,a] suffix | C54: c_corp_sec_179_expens_shares | D54: CLCC_perm | E54: CLCC_perm | F54: CLCC_perm | G54: CLCC_perm | H54: CLCC_perm | I54: CLCC_perm | J54: CLCC_perm | K54: CLCC_perm | L54: CLCC_perm | M54: CLCC_perm | N54: CLCC_perm
C55: pass_thru_sec_179_expens_shares | D55: CLPT_perm | E55: CLPT_perm | F55: CLPT_perm | G55: CLPT_perm | H55: CLPT_perm | I55: CLPT_perm | J55: CLPT_perm | K55: CLPT_perm | L55: CLPT_perm | M55: CLPT_perm | N55: CLPT_perm
A56: x[oth,j,a] suffix | C56: other_expens_shares | D56: CLaw_temp | E56: CLaw_temp | F56: CLaw_temp | G56: CLaw_perm | H56: CLaw_perm | I56: CLaw_perm | J56: CLaw_perm | K56: CLaw_perm | L56: CLaw_perm | M56: CLaw_perm | N56: CLaw_perm
B57: Investment tax credit parameters
A58: k[j,a] suffix | C58: itc_rates | D58: CLaw_2026 | E58: Claw_perm | F58: Claw_perm | G58: Claw_perm | H58: Claw_perm | I58: Claw_perm | J58: Claw_perm | K58: Claw_perm | L58: Claw_perm | M58: Claw_perm | N58: Claw_perm
A59: ψ[j,a] suffix | C59: itc_nondeprcbl_bases | D59: CLaw_rduc | E59: CLaw_rduc | F59: CLaw_rduc | G59: CLaw_rduc | H59: CLaw_rduc | I59: CLaw_rduc | J59: CLaw_rduc | K59: CLaw_rduc | L59: CLaw_rduc | M59: CLaw_rduc | N59: CLaw_rduc
B60: Production tax credit parameters
A61: η[j,a] suffix | C61: ptc_rates | D61: CLaw_2026 | E61: CLaw_2027 | F61: CLaw_2028 | G61: CLaw_2029 | H61: CLaw_2030 | I61: CLaw_2031 | J61: CLaw_2032 | K61: CLaw_2033 | L61: CLaw_perm | M61: CLaw_perm | N61: CLaw_perm
B62: Tax rate adjustment parameters
A63: q̂1[j] & ε̂1[j] suffix | C63: sec_199A_adjustments | D63: CLaw_perm | E63: CLaw_perm | F63: CLaw_perm | G63: CLaw_perm | H63: CLaw_perm | I63: CLaw_perm | J63: CLaw_perm | K63: CLaw_perm | L63: CLaw_perm | M63: CLaw_perm | N63: CLaw_perm
A64: q̂2[j] & ε̂2[j] suffix | C64: c_corp_industry_adjustments | D64: CLaw_perm | E64: CLaw_perm | F64: CLaw_perm | G64: CLaw_perm | H64: CLaw_perm | I64: CLaw_perm | J64: CLaw_perm | K64: CLaw_perm | L64: CLaw_perm | M64: CLaw_perm | N64: CLaw_perm
C65: pass_thru_industry_adjustments | D65: CLaw_perm | E65: CLaw_perm | F65: CLaw_perm | G65: CLaw_perm | H65: CLaw_perm | I65: CLaw_perm | J65: CLaw_perm | K65: CLaw_perm | L65: CLaw_perm | M65: CLaw_perm | N65: CLaw_perm
A66: q̃[a] & ε̃[a] suffix | C66: c_corp_asset_adjustments | D66: CLaw_perm | E66: CLaw_perm | F66: CLaw_perm | G66: CLaw_perm | H66: CLaw_perm | I66: CLaw_perm | J66: CLaw_perm | K66: CLaw_perm | L66: CLaw_perm | M66: CLaw_perm | N66: CLaw_perm
C67: pass_thru_asset_adjustments | D67: CLaw_perm | E67: CLaw_perm | F67: CLaw_perm | G67: CLaw_perm | H67: CLaw_perm | I67: CLaw_perm | J67: CLaw_perm | K67: CLaw_perm | L67: CLaw_perm | M67: CLaw_perm | N67: CLaw_perm
A68: Account Category Parameters
A69: α[cc,eqt,ft] | C69: c_corp_equity_account_category_share_taxable | D69: 0.6241 | E69: 0.63 | F69: 0.627 | G69: 0.6321 | H69: 0.6327 | I69: 0.6359 | J69: 0.6363 | K69: 0.638 | L69: 0.6394 | M69: 0.64 | N69: 0.6406
A70: α[cc,eqt.td] | C70: c_corp_equity_account_category_share_deferred | D70: 0.0335 | E70: 0.0335 | F70: 0.0335 | G70: 0.0335 | H70: 0.0335 | I70: 0.0335 | J70: 0.0335 | K70: 0.0335 | L70: 0.0335 | M70: 0.0335 | N70: 0.0335
A71: α[cc,eqt,nt] | C71: c_corp_equity_account_category_share_nontaxable | D71: 0.3424 | E71: 0.3365 | F71: 0.3395 | G71: 0.3344 | H71: 0.3338 | I71: 0.3306 | J71: 0.3302 | K71: 0.3285 | L71: 0.3271 | M71: 0.3265 | N71: 0.3259
A72: α[cc,dbt,ft] | C72: c_corp_debt_account_category_share_taxable | D72: 0.387 | E72: 0.3917 | F72: 0.3889 | G72: 0.3934 | H72: 0.3941 | I72: 0.3965 | J72: 0.3975 | K72: 0.3981 | L72: 0.3991 | M72: 0.3996 | N72: 0.4
A73: α[cc,dbt.td] | C73: c_corp_debt_account_category_share_deferred | D73: 0.1925 | E73: 0.1925 | F73: 0.1925 | G73: 0.1925 | H73: 0.1925 | I73: 0.1925 | J73: 0.1925 | K73: 0.1925 | L73: 0.1925 | M73: 0.1925 | N73: 0.1925
A74: α[cc,dbt,nt] | C74: c_corp_debt_account_category_share_nontaxable | D74: 0.4205 | E74: 0.4158 | F74: 0.4186 | G74: 0.4141 | H74: 0.4134 | I74: 0.411 | J74: 0.41 | K74: 0.4094 | L74: 0.4084 | M74: 0.4079 | N74: 0.4075
A75: α[pt,eqt,ft] | C75: pass_thru_equity_account_category_share_taxable | D75: 1 | E75: 1 | F75: 1 | G75: 1 | H75: 1 | I75: 1 | J75: 1 | K75: 1 | L75: 1 | M75: 1 | N75: 1
A76: α[pt,eqt.td] | C76: pass_thru_equity_account_category_share_deferred | D76: 0 | E76: 0 | F76: 0 | G76: 0 | H76: 0 | I76: 0 | J76: 0 | K76: 0 | L76: 0 | M76: 0 | N76: 0
A77: α[pt,eqt,nt] | C77: pass_thru_equity_account_category_share_nontaxable | D77: 0 | E77: 0 | F77: 0 | G77: 0 | H77: 0 | I77: 0 | J77: 0 | K77: 0 | L77: 0 | M77: 0 | N77: 0
A78: α[pt,dbt,ft] | C78: pass_thru_debt_account_category_share_taxable | D78: 0.6887 | E78: 0.6907 | F78: 0.6896 | G78: 0.6915 | H78: 0.6917 | I78: 0.6928 | J78: 0.693 | K78: 0.6935 | L78: 0.694 | M78: 0.6942 | N78: 0.6944
A79: α[pt,dbt.td] | C79: pass_thru_debt_account_category_share_deferred | D79: 0.1284 | E79: 0.1284 | F79: 0.1284 | G79: 0.1284 | H79: 0.1284 | I79: 0.1284 | J79: 0.1284 | K79: 0.1284 | L79: 0.1284 | M79: 0.1284 | N79: 0.1284
A80: α[pt,dbt,nt] | C80: pass_thru_debt_account_category_share_nontaxable | D80: 0.1829 | E80: 0.1809 | F80: 0.182 | G80: 0.1801 | H80: 0.1799 | I80: 0.1788 | J80: 0.1786 | K80: 0.1781 | L80: 0.1776 | M80: 0.1774 | N80: 0.1772
... A86: α[oh,dbt,nt] | C86: ooh_debt_account_category_share_nontaxable | D86: 0.1295 | E86: 0.1284 | F86: 0.1289 | G86: 0.1279 | H86: 0.1279 | I86: 0.1272 | J86: 0.1273 | K86: 0.1268 | L86: 0.1265 | M86: 0.1264 | N86: 0.1263

Sheet policy_parameters.Current_law_U
A1: Variable names from working paper | C1: Variable names in csv file | D1: Template for policy parameter values under the uniformity perspective
C2: year | D2: 2026 | E2: 2027 | F2: 2028 | G2: 2029 | H2: 2030 | I2: 2031 | J2: 2032 | K2: 2033 | L2: 2034 | M2: 2035 | N2: 2036
A3: Tax Rate Parameters
B4: Taxes on profits/imputed rent
A5: t[cc] | C5: c_corp_tax_rate | D5: 0.21 | E5: 0.21 | F5: 0.21 | G5: 0.21 | H5: 0.21 | I5: 0.21 | J5: 0.21 | K5: 0.21 | L5: 0.21 | M5: 0.21 | N5: 0.21
A6: t[pt] | C6: pass_thru_tax_rate | D6: 0.2776 | E6: 0.2769 | F6: 0.2759 | G6: 0.276 | H6: 0.2766 | I6: 0.276 | J6: 0.275 | K6: 0.2761 | L6: 0.2764 | M6: 0.2767 | N6: 0.2787
A7: t[se] | C7: seca_tax_rate | D7: 0.0352 | E7: 0.0352 | F7: 0.0352 | G7: 0.0352 | H7: 0.0352 | I7: 0.0352 | J7: 0.0352 | K7: 0.0352 | L7: 0.0352 | M7: 0.0353 | N7: 0.0353
A8: t[rep] | C8: repurchases_tax_rate | D8: 0.01 | E8: 0.01 | F8: 0.01 | G8: 0.01 | H8: 0.01 | I8: 0.01 | J8: 0.01 | K8: 0.01 | L8: 0.01 | M8: 0.01 | N8: 0.01
A9: t[oh] | C9: ooh_tax_rate | D9: 0 | E9: 0 | F9: 0 | G9: 0 | H9: 0 | I9: 0 | J9: 0 | K9: 0 | L9: 0 | M9: 0 | N9: 0
B10: Individual income taxes on investment income
A11: t[div] | C11: dividend_inc_tax_rate | D11: 0.2092 | E11: 0.2076 | F11: 0.2059 | G11: 0.2034 | H11: 0.2031 | I11: 0.203 | J11: 0.2037 | K11: 0.2037 | L11: 0.2044 | M11: 0.2037 | N11: 0.2054
A12: t[scg] | C12: cap_gains_short_term_tax_rate | D12: 0.2776 | E12: 0.2769 | F12: 0.2759 | G12: 0.276 | H12: 0.2766 | I12: 0.276 | J12: 0.275 | K12: 0.2761 | L12: 0.2764 | M12: 0.2767 | N12: 0.2787
A13: t[lcg] | C13: cap_gains_long_term_tax_rate | D13: 0.2092 | E13: 0.2076 | F13: 0.2059 | G13: 0.2034 | H13: 0.2031 | I13: 0.203 | J13: 0.2037 | K13: 0.2037 | L13: 0.2044 | M13: 0.2037 | N13: 0.2054
A14: t[xcg] | C14: cap_gains_at_death_tax_rate | D14: 0 | E14: 0 | F14: 0 | G14: 0 | H14: 0 | I14: 0 | J14: 0 | K14: 0 | L14: 0 | M14: 0 | N14: 0
A15: t[int,cc] | C15: interest_inc_from_biz_tax_rate | D15: 0.2776 | E15: 0.2769 | F15: 0.2759 | G15: 0.276 | H15: 0.2766 | I15: 0.276 | J15: 0.275 | K15: 0.2761 | L15: 0.2764 | M15: 0.2767 | N15: 0.2787
A16: t[int,oh] | C16: interest_inc_from_ooh_tax_rate | D16: 0.2776 | E16: 0.2769 | F16: 0.2759 | G16: 0.276 | H16: 0.2766 | I16: 0.276 | J16: 0.275 | K16: 0.2761 | L16: 0.2764 | M16: 0.2767 | N16: 0.2787
A17: t[td] | C17: ret_plan_deferred_tax_rate | D17: 0.2776 | E17: 0.2769 | F17: 0.2759 | G17: 0.276 | H17: 0.2766 | I17: 0.276 | J17: 0.275 | K17: 0.2761 | L17: 0.2764 | M17: 0.2767 | N17: 0.2787
A18: t[nt] | C18: ret_plan_nontaxable_tax_rate | D18: 0 | E18: 0 | F18: 0 | G18: 0 | H18: 0 | I18: 0 | J18: 0 | K18: 0 | L18: 0 | M18: 0 | N18: 0
B19: Individual income taxes that apply to itemized deductions
A20: t[hmi] | C20: mortg_interest_deduction_tax_rate | D20: 0.2776 | E20: 0.2769 | F20: 0.2759 | G20: 0.276 | H20: 0.2766 | I20: 0.276 | J20: 0.275 | K20: 0.2761 | L20: 0.2764 | M20: 0.2767 | N20: 0.2787
A21: t[ptx] | C21: prop_tax_deduction_tax_rate | D21: 0.2776 | E21: 0.2769 | F21: 0.2759 | G21: 0.276 | H21: 0.2766 | I21: 0.276 | J21: 0.275 | K21: 0.2761 | L21: 0.2764 | M21: 0.2767 | N21: 0.2787
A22: Deduction Parameters
A23: ξ | C23: pass_thru_inc_share_below_thresholds | D23: 0.3225 | E23: 0.318 | F23: 0.3209 | G23: 0.3133 | H23: 0.305 | I23: 0.3035 | J23: 0.3006 | K23: 0.2979 | L23: 0.2948 | M23: 0.2919 | N23: 0.2896
A24: q^ | C24: pass_thru_eligibility_below_thresholds | D24: 0.7734 | E24: 0.7741 | F24: 0.7749 | G24: 0.775 | H24: 0.7743 | I24: 0.7744 | J24: 0.774 | K24: 0.7738 | L24: 0.7739 | M24: 0.7732 | N24: 0.773
A25: θ[cc] | C25: c_corp_interest_deductible_share | D25: 0.9888 | E25: 0.9822 | F25: 0.9777 | G25: 0.9749 | H25: 0.9734 | I25: 0.9734 | J25: 0.9737 | K25: 0.9743 | L25: 0.9746 | M25: 0.9748 | N25: 0.9753
A26: θ[pt] | C26: pass_thru_interest_deductible_share | D26: 0.9888 | E26: 0.9822 | F26: 0.9777 | G26: 0.9749 | H26: 0.9734 | I26: 0.9734 | J26: 0.9737 | K26: 0.9743 | L26: 0.9746 | M26: 0.9748 | N26: 0.9753
A27: θ[oh] | C27: mortg_interest_deductible_share | D27: 0.5552 | E27: 0.5876 | F27: 0.6222 | G27: 0.6473 | H27: 0.5526 | I27: 0.5723 | J27: 0.589 | K27: 0.6036 | L27: 0.6137 | M27: 0.6211 | N27: 0.6253
A28: λ | C28: prop_tax_deductible_share | D28: 0.3457 | E28: 0.356 | F28: 0.3709 | G28: 0.3781 | H28: 0.0435 | I28: 0.0436 | J28: 0.0424 | K28: 0.0413 | L28: 0.04 | M28: 0.0383 | N28: 0.0365
A29: Timing Adjustment Parameters Reflecting Fluctuating Rates of Return
B30: Ratio of PV of item to nominal item
A31: ν[cc,inc] | C31: c_corp_net_inc_timing_adjustment | D31: 1 | E31: 1 | F31: 1 | G31: 1 | H31: 1 | I31: 1 | J31: 1 | K31: 1 | L31: 1 | M31: 1 | N31: 1
A32: ν[pt,inc] | C32: pass_thru_net_inc_timing_adjustment | D32: 1 | E32: 1 | F32: 1 | G32: 1 | H32: 1 | I32: 1 | J32: 1 | K32: 1 | L32: 1 | M32: 1 | N32: 1
A33: ν[se,inc] | C33: seca_net_inc_timing_adjustment | D33: 1 | E33: 1 | F33: 1 | G33: 1 | H33: 1 | I33: 1 | J33: 1 | K33: 1 | L33: 1 | M33: 1 | N33: 1
A34: ν[cc,ded] | C34: c_corp_deductions_timing_adjustment | D34: 1 | E34: 1 | F34: 1 | G34: 1 | H34: 1 | I34: 1 | J34: 1 | K34: 1 | L34: 1 | M34: 1 | N34: 1
A35: ν[pt,ded] | C35: pass_thru_deductions_timing_adjustment | D35: 1 | E35: 1 | F35: 1 | G35: 1 | H35: 1 | I35: 1 | J35: 1 | K35: 1 | L35: 1 | M35: 1 | N35: 1
A36: ν[se,ded] | C36: seca_deductions_timing_adjustment | D36: 1 | E36: 1 | F36: 1 | G36: 1 | H36: 1 | I36: 1 | J36: 1 | K36: 1 | L36: 1 | M36: 1 | N36: 1
A37: ν[cc,crd] | C37: c_corp_credits_timing_adjustment | D37: 1 | E37: 1 | F37: 1 | G37: 1 | H37: 1 | I37: 1 | J37: 1 | K37: 1 | L37: 1 | M37: 1 | N37: 1
A38: ν[pt,crd] | C38: pass_thru_credits_timing_adjustment | D38: 1 | E38: 1 | F38: 1 | G38: 1 | H38: 1 | I38: 1 | J38: 1 | K38: 1 | L38: 1 | M38: 1 | N38: 1
A39: Additive Annual Changes to Holding Period Parameters
A40: ω[stg] Δ | C40: change_cap_gains_short_term_share | D40: 0 | E40: 0 | F40: 0 | G40: 0 | H40: 0 | I40: 0 | J40: 0 | K40: 0 | L40: 0 | M40: 0 | N40: 0
A41: ω[xtg] Δ | C41: change_cap_gains_at_death_share | D41: 0 | E41: 0 | F41: 0 | G41: 0 | H41: 0 | I41: 0 | J41: 0 | K41: 0 | L41: 0 | M41: 0 | N41: 0
A42: Y[stg] Δ | C42: change_cap_gains_short_term_holding_period | D42: 0 | E42: 0 | F42: 0 | G42: 0 | H42: 0 | I42: 0 | J42: 0 | K42: 0 | L42: 0 | M42: 0 | N42: 0
A43: Y[ltg] Δ | C43: change_cap_gains_long_term_holding_period | D43: 0 | E43: 0 | F43: 0 | G43: 0 | H43: 0 | I43: 0 | J43: 0 | K43: 0 | L43: 0 | M43: 0 | N43: 0
A44: Y[xtg] Δ | C44: change_cap_gains_at_death_holding_period | D44: 0 | E44: 0 | F44: 0 | G44: 0 | H44: 0 | I44: 0 | J44: 0 | K44: 0 | L44: 0 | M44: 0 | N44: 0
A45: Y[td] Δ | C45: change_ret_plan_deferred_holding_period | D45: 0 | E45: 0 | F45: 0 | G45: 0 | H45: 0 | I45: 0 | J45: 0 | K45: 0 | L45: 0 | M45: 0 | N45: 0
A46: Y[nt] Δ | C46: change_ret_plan_nontaxable_holding_period | D46: 0 | E46: 0 | F46: 0 | G46: 0 | H46: 0 | I46: 0 | J46: 0 | K46: 0 | L46: 0 | M46: 0 | N46: 0
A47: Y[inv] Δ | C47: change_inventories_holding_period | D47: 0 | E47: 0 | F47: 0 | G47: 0 | H47: 0 | I47: 0 | J47: 0 | K47: 0 | L47: 0 | M47: 0 | N47: 0
A48: File Suffixes Pointing to Depreciation, ITC & Rate Adjustment Parameters
B49: Cost recovery deduction parameters
A50: L[j,a] suffix | C50: recovery_periods | D50: CLaw_perm | E50: CLaw_perm | F50: CLaw_perm | G50: CLaw_perm | H50: CLaw_perm | I50: CLaw_perm | J50: CLaw_perm | K50: CLaw_perm | L50: CLaw_perm | M50: CLaw_perm | N50: CLaw_perm
A51: b[j,a] suffix | C51: acceleration_rates | D51: CLaw_perm | E51: CLaw_perm | F51: CLaw_perm | G51: CLaw_perm | H51: CLaw_perm | I51: CLaw_perm | J51: CLaw_perm | K51: CLaw_perm | L51: CLaw_perm | M51: CLaw_perm | N51: CLaw_perm
A52: p[j,a] suffix | C52: straight_line_flags | D52: CLaw_perm | E52: CLaw_perm | F52: CLaw_perm | G52: CLaw_perm | H52: CLaw_perm | I52: CLaw_perm | J52: CLaw_perm | K52: CLaw_perm | L52: CLaw_perm | M52: CLaw_perm | N52: CLaw_perm
A53: ι[j,a] suffix | C53: inflation_adjustments | D53: CLaw_perm | E53: CLaw_perm | F53: CLaw_perm | G53: CLaw_perm | H53: CLaw_perm | I53: CLaw_perm | J53: CLaw_perm | K53: CLaw_perm | L53: CLaw_perm | M53: CLaw_perm | N53: CLaw_perm
A54: x[179,j,a] suffix | C54: c_corp_sec_179_expens_shares | D54: CLaw_perm | E54: CLaw_perm | F54: CLaw_perm | G54: CLaw_perm | H54: CLaw_perm | I54: CLaw_perm | J54: CLaw_perm | K54: CLaw_perm | L54: CLaw_perm | M54: CLaw_perm | N54: CLaw_perm
C55: pass_thru_sec_179_expens_shares | D55: CLaw_perm | E55: CLaw_perm | F55: CLaw_perm | G55: CLaw_perm | H55: CLaw_perm | I55: CLaw_perm | J55: CLaw_perm | K55: CLaw_perm | L55: CLaw_perm | M55: CLaw_perm | N55: CLaw_perm
A56: x[oth,j,a] suffix | C56: other_expens_shares | D56: CLaw_temp | E56: CLaw_temp | F56: CLaw_temp | G56: CLaw_perm | H56: CLaw_perm | I56: CLaw_perm | J56: CLaw_perm | K56: CLaw_perm | L56: CLaw_perm | M56: CLaw_perm | N56: CLaw_perm
B57: Investment tax credit parameters
A58: k[j,a] suffix | C58: itc_rates | D58: CLaw_2026 | E58: Claw_perm | F58: Claw_perm | G58: Claw_perm | H58: Claw_perm | I58: Claw_perm | J58: Claw_perm | K58: Claw_perm | L58: Claw_perm | M58: Claw_perm | N58: Claw_perm
A59: ψ[j,a] suffix | C59: itc_nondeprcbl_bases | D59: CLaw_rduc | E59: CLaw_rduc | F59: CLaw_rduc | G59: CLaw_rduc | H59: CLaw_rduc | I59: CLaw_rduc | J59: CLaw_rduc | K59: CLaw_rduc | L59: CLaw_rduc | M59: CLaw_rduc | N59: CLaw_rduc
B60: Production tax credit parameters
A61: η[j,a] suffix | C61: ptc_rates | D61: CLaw_2026 | E61: CLaw_2027 | F61: CLaw_2028 | G61: CLaw_2029 | H61: CLaw_2030 | I61: CLaw_2031 | J61: CLaw_2032 | K61: CLaw_2033 | L61: CLaw_perm | M61: CLaw_perm | N61: CLaw_perm
B62: Tax rate adjustment parameters
A63: q̂1[j] & ε̂1[j] suffix | C63: sec_199A_adjustments | D63: CLaw_perm | E63: CLaw_perm | F63: CLaw_perm | G63: CLaw_perm | H63: CLaw_perm | I63: CLaw_perm | J63: CLaw_perm | K63: CLaw_perm | L63: CLaw_perm | M63: CLaw_perm | N63: CLaw_perm
A64: q̂2[j] & ε̂2[j] suffix | C64: c_corp_industry_adjustments | D64: CLaw_perm | E64: CLaw_perm | F64: CLaw_perm | G64: CLaw_perm | H64: CLaw_perm | I64: CLaw_perm | J64: CLaw_perm | K64: CLaw_perm | L64: CLaw_perm | M64: CLaw_perm | N64: CLaw_perm
C65: pass_thru_industry_adjustments | D65: CLaw_perm | E65: CLaw_perm | F65: CLaw_perm | G65: CLaw_perm | H65: CLaw_perm | I65: CLaw_perm | J65: CLaw_perm | K65: CLaw_perm | L65: CLaw_perm | M65: CLaw_perm | N65: CLaw_perm
A66: q̃[a] & ε̃[a] suffix | C66: c_corp_asset_adjustments | D66: CLaw_perm | E66: CLaw_perm | F66: CLaw_perm | G66: CLaw_perm | H66: CLaw_perm | I66: CLaw_perm | J66: CLaw_perm | K66: CLaw_perm | L66: CLaw_perm | M66: CLaw_perm | N66: CLaw_perm
C67: pass_thru_asset_adjustments | D67: CLaw_perm | E67: CLaw_perm | F67: CLaw_perm | G67: CLaw_perm | H67: CLaw_perm | I67: CLaw_perm | J67: CLaw_perm | K67: CLaw_perm | L67: CLaw_perm | M67: CLaw_perm | N67: CLaw_perm
A68: Account Category Parameters
A69: α[cc,eqt,ft] | C69: c_corp_equity_account_category_share_taxable | D69: 0.5934 | E69: 0.5984 | F69: 0.5958 | G69: 0.6003 | H69: 0.6008 | I69: 0.6036 | J69: 0.604 | K69: 0.6054 | L69: 0.6065 | M69: 0.6071 | N69: 0.6076
A70: α[cc,eqt.td] | C70: c_corp_equity_account_category_share_deferred | D70: 0.0578 | E70: 0.0578 | F70: 0.0578 | G70: 0.0578 | H70: 0.0578 | I70: 0.0578 | J70: 0.0578 | K70: 0.0578 | L70: 0.0578 | M70: 0.0578 | N70: 0.0578
A71: α[cc,eqt,nt] | C71: c_corp_equity_account_category_share_nontaxable | D71: 0.3488 | E71: 0.3438 | F71: 0.3464 | G71: 0.3419 | H71: 0.3414 | I71: 0.3386 | J71: 0.3382 | K71: 0.3368 | L71: 0.3357 | M71: 0.3351 | N71: 0.3346
A72: α[cc,dbt,ft] | C72: c_corp_debt_account_category_share_taxable | D72: 0.5934 | E72: 0.5984 | F72: 0.5958 | G72: 0.6003 | H72: 0.6008 | I72: 0.6036 | J72: 0.604 | K72: 0.6054 | L72: 0.6065 | M72: 0.6071 | N72: 0.6076
A73: α[cc,dbt.td] | C73: c_corp_debt_account_category_share_deferred | D73: 0.0578 | E73: 0.0578 | F73: 0.0578 | G73: 0.0578 | H73: 0.0578 | I73: 0.0578 | J73: 0.0578 | K73: 0.0578 | L73: 0.0578 | M73: 0.0578 | N73: 0.0578
A74: α[cc,dbt,nt] | C74: c_corp_debt_account_category_share_nontaxable | D74: 0.3488 | E74: 0.3438 | F74: 0.3464 | G74: 0.3419 | H74: 0.3414 | I74: 0.3386 | J74: 0.3382 | K74: 0.3368 | L74: 0.3357 | M74: 0.3351 | N74: 0.3346
A75: α[pt,eqt,ft] | C75: pass_thru_equity_account_category_share_taxable | D75: 1 | E75: 1 | F75: 1 | G75: 1 | H75: 1 | I75: 1 | J75: 1 | K75: 1 | L75: 1 | M75: 1 | N75: 1
A76: α[pt,eqt.td] | C76: pass_thru_equity_account_category_share_deferred | D76: 0 | E76: 0 | F76: 0 | G76: 0 | H76: 0 | I76: 0 | J76: 0 | K76: 0 | L76: 0 | M76: 0 | N76: 0
A77: α[pt,eqt,nt] | C77: pass_thru_equity_account_category_share_nontaxable | D77: 0 | E77: 0 | F77: 0 | G77: 0 | H77: 0 | I77: 0 | J77: 0 | K77: 0 | L77: 0 | M77: 0 | N77: 0
A78: α[pt,dbt,ft] | C78: pass_thru_debt_account_category_share_taxable | D78: 0.5934 | E78: 0.5984 | F78: 0.5958 | G78: 0.6003 | H78: 0.6008 | I78: 0.6036 | J78: 0.604 | K78: 0.6054 | L78: 0.6065 | M78: 0.6071 | N78: 0.6076
A79: α[pt,dbt.td] | C79: pass_thru_debt_account_category_share_deferred | D79: 0.0578 | E79: 0.0578 | F79: 0.0578 | G79: 0.0578 | H79: 0.0578 | I79: 0.0578 | J79: 0.0578 | K79: 0.0578 | L79: 0.0578 | M79: 0.0578 | N79: 0.0578
A80: α[pt,dbt,nt] | C80: pass_thru_debt_account_category_share_nontaxable | D80: 0.3488 | E80: 0.3438 | F80: 0.3464 | G80: 0.3419 | H80: 0.3414 | I80: 0.3386 | J80: 0.3382 | K80: 0.3368 | L80: 0.3357 | M80: 0.3351 | N80: 0.3346
... A86: α[oh,dbt,nt] | C86: ooh_debt_account_category_share_nontaxable | D86: 0.3488 | E86: 0.3438 | F86: 0.3464 | G86: 0.3419 | H86: 0.3414 | I86: 0.3386 | J86: 0.3382 | K86: 0.3368 | L86: 0.3357 | M86: 0.3351 | N86: 0.3346

Sheet csv_selection
A1: Comprehensive perspective | B1: policy_parameters. | C1: Current_law_C
A2: Uniformity perspective | B2: policy_parameters. | C2: Current_law_U
C4: Enter suffixes of policy_parameters files in cells C1 and C2

Sheet policy_parameters_comprehensive
A1: =INDIRECT(csv_selection!$B$1 & csv_selection!$C$1 & "!C2") -> year | B1: =INDIRECT(csv_selection!$B$1 & csv_selection!$C$1 & "!C5") -> c_corp_tax_rate | C1: =INDIRECT(csv_selection!$B$1 & csv_selection!$C$1 & "!C6") -> pass_thru_tax_rate | D1: =INDIRECT(csv_selection!$B$1 & csv_selection!$C$1 & "!C7") -> seca_tax_rate | E1: =INDIRECT(csv_selection!$B$1 & csv_selection!$C$1 & "!C8") -> repurchases_tax_rate | F1: =INDIRECT(csv_selection!$B$1 & csv_selection!$C$1 & "!C9") -> ooh_tax_rate | G1: =INDIRECT(csv_selection!$B$1 & csv_selection!$C$1 & "!C11") -> dividend_inc_tax_rate | H1: =INDIRECT(csv_selection!$B$1 & csv_selection!$C$1 & "!C12") -> cap_gains_short_term_tax_rate | I1: =INDIRECT(csv_selection!$B$1 & csv_selection!$C$1 & "!C13") -> cap_gains_long_term_tax_rate | J1: =INDIRECT(csv_selection!$B$1 & csv_selection!$C$1 & "!C14") -> cap_gains_at_death_tax_rate | K1: =INDIRECT(csv_selection!$B$1 & csv_selection!$C$1 & "!C15") -> interest_inc_from_biz_tax_rate | L1: =INDIRECT(csv_selection!$B$1 & csv_selection!$C$1 & "!C16") -> interest_inc_from_ooh_tax_rate | M1: =INDIRECT(csv_selection!$B$1 & csv_selection!$C$1 & "!C17") -> ret_plan_deferred_tax_rate | N1: =INDIRECT(csv_selection!$B$1 & csv_selection!$C$1 & "!C18") -> ret_plan_nontaxable_tax_rate | O1: =INDIRECT(csv_selection!$B$1 & csv_selection!$C$1 & "!C20") -> mortg_interest_deduction_tax_rate | P1: =INDIRECT(csv_selection!$B$1 & csv_selection!$C$1 & "!C21") -> prop_tax_deduction_tax_rate | Q1: =INDIRECT(csv_selection!$B$1 & csv_selection!$C$1 & "!C23") -> pass_thru_inc_share_below_thresholds | R1: =INDIRECT(csv_selection!$B$1 & csv_selection!$C$1 & "!C24") -> pass_thru_eligibility_below_thresholds | S1: =INDIRECT(csv_selection!$B$1 & csv_selection!$C$1 & "!C25") -> c_corp_interest_deductible_share | T1: =INDIRECT(csv_selection!$B$1 & csv_selection!$C$1 & "!C26") -> pass_thru_interest_deductible_share | U1: =INDIRECT(csv_selection!$B$1 & csv_selection!$C$1 & "!C27") -> mortg_interest_deductible_share | V1: =INDIRECT(csv_selection!$B$1 & csv_selection!$C$1 & "!C28") -> prop_tax_deductible_share | W1: =INDIRECT(csv_selection!$B$1 & csv_selection!$C$1 & "!C31") -> c_corp_net_inc_timing_adjustment | X1: =INDIRECT(csv_selection!$B$1 & csv_selection!$C$1 & "!C32") -> pass_thru_net_inc_timing_adjustment | Y1: =INDIRECT(csv_selection!$B$1 & csv_selection!$C$1 & "!C33") -> seca_net_inc_timing_adjustment | Z1: =INDIRECT(csv_selection!$B$1 & csv_selection!$C$1 & "!C34") -> c_corp_deductions_timing_adjustment | AA1: =INDIRECT(csv_selection!$B$1 & csv_selection!$C$1 & "!C35") -> pass_thru_deductions_timing_adjustment | AB1: =INDIRECT(csv_selection!$B$1 & csv_selection!$C$1 & "!C36") -> seca_deductions_timing_adjustment | AC1: =INDIRECT(csv_selection!$B$1 & csv_selection!$C$1 & "!C37") -> c_corp_credits_timing_adjustment | AD1: =INDIRECT(csv_selection!$B$1 & csv_selection!$C$1 & "!C38") -> pass_thru_credits_timing_adjustment | AE1: =INDIRECT(csv_selection!$B$1 & csv_selection!$C$1 & "!C40") -> change_cap_gains_short_term_share | AF1: =INDIRECT(csv_selection!$B$1 & csv_selection!$C$1 & "!C41") -> change_cap_gains_at_death_share | AG1: =INDIRECT(csv_selection!$B$1 & csv_selection!$C$1 & "!C42") -> change_cap_gains_short_term_holding_period | AH1: =INDIRECT(csv_selection!$B$1 & csv_selection!$C$1 & "!C43") -> change_cap_gains_long_term_holding_period | AI1: =INDIRECT(csv_selection!$B$1 & csv_selection!$C$1 & "!C44") -> change_cap_gains_at_death_holding_period | AJ1: =INDIRECT(csv_selection!$B$1 & csv_selection!$C$1 & "!C45") -> change_ret_plan_deferred_holding_period | AK1: =INDIRECT(csv_selection!$B$1 & csv_selection!$C$1 & "!C46") -> change_ret_plan_nontaxable_holding_period | AL1: =INDIRECT(csv_selection!$B$1 & csv_selection!$C$1 & "!C47") -> change_inventories_holding_period | AM1: =INDIRECT(csv_selection!$B$1 & csv_selection!$C$1 & "!C50") -> recovery_periods | AN1: =INDIRECT(csv_selection!$B$1 & csv_selection!$C$1 & "!C51") -> acceleration_rates | AO1: =INDIRECT(csv_selection!$B$1 & csv_selection!$C$1 & "!C52") -> straight_line_flags | AP1: =INDIRECT(csv_selection!$B$1 & csv_selection!$C$1 & "!C53") -> inflation_adjustments | AQ1: =INDIRECT(csv_selection!$B$1 & csv_selection!$C$1 & "!C54") -> c_corp_sec_179_expens_shares | AR1: =INDIRECT(csv_selection!$B$1 & csv_selection!$C$1 & "!C55") -> pass_thru_sec_179_expens_shares | AS1: =INDIRECT(csv_selection!$B$1 & csv_selection!$C$1 & "!C56") -> other_expens_shares | AT1: =INDIRECT(csv_selection!$B$1 & csv_selection!$C$1 & "!C58") -> itc_rates | AU1: =INDIRECT(csv_selection!$B$1 & csv_selection!$C$1 & "!C59") -> itc_nondeprcbl_bases | AV1: =INDIRECT(csv_selection!$B$1 & csv_selection!$C$1 & "!C61") -> ptc_rates | AW1: =INDIRECT(csv_selection!$B$1 & csv_selection!$C$1 & "!C63") -> sec_199A_adjustments | AX1: =INDIRECT(csv_selection!$B$1 & csv_selection!$C$1 & "!C64") -> c_corp_industry_adjustments | AY1: =INDIRECT(csv_selection!$B$1 & csv_selection!$C$1 & "!C65") -> pass_thru_industry_adjustments | AZ1: =INDIRECT(csv_selection!$B$1 & csv_selection!$C$1 & "!C66") -> c_corp_asset_adjustments | BA1: =INDIRECT(csv_selection!$B$1 & csv_selection!$C$1 & "!C67") -> pass_thru_asset_adjustments | BB1: =INDIRECT(csv_selection!$B$1 & csv_selection!$C$1 & "!C69") -> c_corp_equity_account_category_share_taxable | BC1: =INDIRECT(csv_selection!$B$1 & csv_selection!$C$1 & "!C70") -> c_corp_equity_account_category_share_deferred | BD1: =INDIRECT(csv_selection!$B$1 & csv_selection!$C$1 & "!C71") -> c_corp_equity_account_category_share_nontaxable | BE1: =INDIRECT(csv_selection!$B$1 & csv_selection!$C$1 & "!C72") -> c_corp_debt_account_category_share_taxable | BF1: =INDIRECT(csv_selection!$B$1 & csv_selection!$C$1 & "!C73") -> c_corp_debt_account_category_share_deferred | BG1: =INDIRECT(csv_selection!$B$1 & csv_selection!$C$1 & "!C74") -> c_corp_debt_account_category_share_nontaxable | BH1: =INDIRECT(csv_selection!$B$1 & csv_selection!$C$1 & "!C75") -> pass_thru_equity_account_category_share_taxable | BI1: =INDIRECT(csv_selection!$B$1 & csv_selection!$C$1 & "!C76") -> pass_thru_equity_account_category_share_deferred | BJ1: =INDIRECT(csv_selection!$B$1 & csv_selection!$C$1 & "!C77") -> pass_thru_equity_account_category_share_nontaxable | BK1: =INDIRECT(csv_selection!$B$1 & csv_selection!$C$1 & "!C78") -> pass_thru_debt_account_category_share_taxable | BL1: =INDIRECT(csv_selection!$B$1 & csv_selection!$C$1 & "!C79") -> pass_thru_debt_account_category_share_deferred | BM1: =INDIRECT(csv_selection!$B$1 & csv_selection!$C$1 & "!C80") -> pass_thru_debt_account_category_share_nontaxable | BN1: =INDIRECT(csv_selection!$B$1 & csv_selection!$C$1 & "!C81") -> ooh_equity_account_category_share_taxable | BO1: =INDIRECT(csv_selection!$B$1 & csv_selection!$C$1 & "!C82") -> ooh_equity_account_category_share_deferred | BP1: =INDIRECT(csv_selection!$B$1 & csv_selection!$C$1 & "!C83") -> ooh_equity_account_category_share_nontaxable | BQ1: =INDIRECT(csv_selection!$B$1 & csv_selection!$C$1 & "!C84") -> ooh_debt_account_category_share_taxable | BR1: =INDIRECT(csv_selection!$B$1 & csv_selection!$C$1 & "!C85") -> ooh_debt_account_category_share_deferred | BS1: =INDIRECT(csv_selection!$B$1 & csv_selection!$C$1 & "!C86") -> ooh_debt_account_category_share_nontaxable
A2: =INDIRECT(csv_selection!$B$1 & csv_selection!$C$1 & "!D2") -> 2026 | B2: =INDIRECT(csv_selection!$B$1 & csv_selection!$C$1 & "!D5") -> 0.21 | C2: =INDIRECT(csv_selection!$B$1 & csv_selection!$C$1 & "!D6") -> 0.3042 | D2: =INDIRECT(csv_selection!$B$1 & csv_selection!$C$1 & "!D7") -> 0.0352 | E2: =INDIRECT(csv_selection!$B$1 & csv_selection!$C$1 & "!D8") -> 0.01 | F2: =INDIRECT(csv_selection!$B$1 & csv_selection!$C$1 & "!D9") -> 0 | G2: =INDIRECT(csv_selection!$B$1 & csv_selection!$C$1 & "!D11") -> 0.1997 | H2: =INDIRECT(csv_selection!$B$1 & csv_selection!$C$1 & "!D12") -> 0.3495 | I2: =INDIRECT(csv_selection!$B$1 & csv_selection!$C$1 & "!D13") -> 0.2116 | J2: =INDIRECT(csv_selection!$B$1 & csv_selection!$C$1 & "!D14") -> 0 | K2: =INDIRECT(csv_selection!$B$1 & csv_selection!$C$1 & "!D15") -> 0.3036 | L2: =INDIRECT(csv_selection!$B$1 & csv_selection!$C$1 & "!D16") -> 0.3036 | M2: =INDIRECT(csv_selection!$B$1 & csv_selection!$C$1 & "!D17") -> 0.231 | N2: =INDIRECT(csv_selection!$B$1 & csv_selection!$C$1 & "!D18") -> 0 | O2: =INDIRECT(csv_selection!$B$1 & csv_selection!$C$1 & "!D20") -> 0.1949 | P2: =INDIRECT(csv_selection!$B$1 & csv_selection!$C$1 & "!D21") -> 0.1776 | Q2: =INDIRECT(csv_selection!$B$1 & csv_selection!$C$1 & "!D23") -> 0.3225 | R2: =INDIRECT(csv_selection!$B$1 & csv_selection!$C$1 & "!D24") -> 0.7734 | S2: =INDIRECT(csv_selection!$B$1 & csv_selection!$C$1 & "!D25") -> 0.9884 | T2: =INDIRECT(csv_selection!$B$1 & csv_selection!$C$1 & "!D26") -> 0.9933 | U2: =INDIRECT(csv_selection!$B$1 & csv_selection!$C$1 & "!D27") -> 0.5552 | V2: =INDIRECT(csv_selection!$B$1 & csv_selection!$C$1 & "!D28") -> 0.3457 | W2: =INDIRECT(csv_selection!$B$1 & csv_selection!$C$1 & "!D31") -> 1 | X2: =INDIRECT(csv_selection!$B$1 & csv_selection!$C$1 & "!D32") -> 1 | Y2: =INDIRECT(csv_selection!$B$1 & csv_selection!$C$1 & "!D33") -> 1 | Z2: =INDIRECT(csv_selection!$B$1 & csv_selection!$C$1 & "!D34") -> 1 | AA2: =INDIRECT(csv_selection!$B$1 & csv_selection!$C$1 & "!D35") -> 1 | AB2: =INDIRECT(csv_selection!$B$1 & csv_selection!$C$1 & "!D36") -> 1 | AC2: =INDIRECT(csv_selection!$B$1 & csv_selection!$C$1 & "!D37") -> 1 | AD2: =INDIRECT(csv_selection!$B$1 & csv_selection!$C$1 & "!D38") -> 1 | AE2: =INDIRECT(csv_selection!$B$1 & csv_selection!$C$1 & "!D40") -> 0 | AF2: =INDIRECT(csv_selection!$B$1 & csv_selection!$C$1 & "!D41") -> 0 | AG2: =INDIRECT(csv_selection!$B$1 & csv_selection!$C$1 & "!D42") -> 0 | AH2: =INDIRECT(csv_selection!$B$1 & csv_selection!$C$1 & "!D43") -> 0 | AI2: =INDIRECT(csv_selection!$B$1 & csv_selection!$C$1 & "!D44") -> 0 | AJ2: =INDIRECT(csv_selection!$B$1 & csv_selection!$C$1 & "!D45") -> 0 | AK2: =INDIRECT(csv_selection!$B$1 & csv_selection!$C$1 & "!D46") -> 0 | AL2: =INDIRECT(csv_selection!$B$1 & csv_selection!$C$1 & "!D47") -> 0 | AM2: =INDIRECT(csv_selection!$B$1 & csv_selection!$C$1 & "!D50") -> CLaw_perm | AN2: =INDIRECT(csv_selection!$B$1 & csv_selection!$C$1 & "!D51") -> CLaw_perm | AO2: =INDIRECT(csv_selection!$B$1 & csv_selection!$C$1 & "!D52") -> CLaw_perm | AP2: =INDIRECT(csv_selection!$B$1 & csv_selection!$C$1 & "!D53") -> CLaw_perm | AQ2: =INDIRECT(csv_selection!$B$1 & csv_selection!$C$1 & "!D54") -> CLCC_perm | AR2: =INDIRECT(csv_selection!$B$1 & csv_selection!$C$1 & "!D55") -> CLPT_perm | AS2: =INDIRECT(csv_selection!$B$1 & csv_selection!$C$1 & "!D56") -> CLaw_temp | AT2: =INDIRECT(csv_selection!$B$1 & csv_selection!$C$1 & "!D58") -> CLaw_2026 | AU2: =INDIRECT(csv_selection!$B$1 & csv_selection!$C$1 & "!D59") -> CLaw_rduc | AV2: =INDIRECT(csv_selection!$B$1 & csv_selection!$C$1 & "!D61") -> CLaw_2026 | AW2: =INDIRECT(csv_selection!$B$1 & csv_selection!$C$1 & "!D63") -> CLaw_perm | AX2: =INDIRECT(csv_selection!$B$1 & csv_selection!$C$1 & "!D64") -> CLaw_perm | AY2: =INDIRECT(csv_selection!$B$1 & csv_selection!$C$1 & "!D65") -> CLaw_perm | AZ2: =INDIRECT(csv_selection!$B$1 & csv_selection!$C$1 & "!D66") -> CLaw_perm | BA2: =INDIRECT(csv_selection!$B$1 & csv_selection!$C$1 & "!D67") -> CLaw_perm | BB2: =INDIRECT(csv_selection!$B$1 & csv_selection!$C$1 & "!D69") -> 0.6241 | BC2: =INDIRECT(csv_selection!$B$1 & csv_selection!$C$1 & "!D70") -> 0.0335 | BD2: =INDIRECT(csv_selection!$B$1 & csv_selection!$C$1 & "!D71") -> 0.3424 | BE2: =INDIRECT(csv_selection!$B$1 & csv_selection!$C$1 & "!D72") -> 0.387 | BF2: =INDIRECT(csv_selection!$B$1 & csv_selection!$C$1 & "!D73") -> 0.1925 | BG2: =INDIRECT(csv_selection!$B$1 & csv_selection!$C$1 & "!D74") -> 0.4205 | BH2: =INDIRECT(csv_selection!$B$1 & csv_selection!$C$1 & "!D75") -> 1 | BI2: =INDIRECT(csv_selection!$B$1 & csv_selection!$C$1 & "!D76") -> 0 | BJ2: =INDIRECT(csv_selection!$B$1 & csv_selection!$C$1 & "!D77") -> 0 | BK2: =INDIRECT(csv_selection!$B$1 & csv_selection!$C$1 & "!D78") -> 0.6887 | BL2: =INDIRECT(csv_selection!$B$1 & csv_selection!$C$1 & "!D79") -> 0.1284 | BM2: =INDIRECT(csv_selection!$B$1 & csv_selection!$C$1 & "!D80") -> 0.1829 | BN2: =INDIRECT(csv_selection!$B$1 & csv_selection!$C$1 & "!D81") -> 1 | BO2: =INDIRECT(csv_selection!$B$1 & csv_selection!$C$1 & "!D82") -> 0 | BP2: =INDIRECT(csv_selection!$B$1 & csv_selection!$C$1 & "!D83") -> 0 | BQ2: =INDIRECT(csv_selection!$B$1 & csv_selection!$C$1 & "!D84") -> 0.8127 | BR2: =INDIRECT(csv_selection!$B$1 & csv_selection!$C$1 & "!D85") -> 0.0578 | BS2: =INDIRECT(csv_selection!$B$1 & csv_selection!$C$1 & "!D86") -> 0.1295
A3: =INDIRECT(csv_selection!$B$1 & csv_selection!$C$1 & "!E2") -> 2027 | B3: =INDIRECT(csv_selection!$B$1 & csv_selection!$C$1 & "!E5") -> 0.21 | C3: =INDIRECT(csv_selection!$B$1 & csv_selection!$C$1 & "!E6") -> 0.3056 | D3: =INDIRECT(csv_selection!$B$1 & csv_selection!$C$1 & "!E7") -> 0.0352 | E3: =INDIRECT(csv_selection!$B$1 & csv_selection!$C$1 & "!E8") -> 0.01 | F3: =INDIRECT(csv_selection!$B$1 & csv_selection!$C$1 & "!E9") -> 0 | G3: =INDIRECT(csv_selection!$B$1 & csv_selection!$C$1 & "!E11") -> 0.1999 | H3: =INDIRECT(csv_selection!$B$1 & csv_selection!$C$1 & "!E12") -> 0.3445 | I3: =INDIRECT(csv_selection!$B$1 & csv_selection!$C$1 & "!E13") -> 0.2095 | J3: =INDIRECT(csv_selection!$B$1 & csv_selection!$C$1 & "!E14") -> 0 | K3: =INDIRECT(csv_selection!$B$1 & csv_selection!$C$1 & "!E15") -> 0.3044 | L3: =INDIRECT(csv_selection!$B$1 & csv_selection!$C$1 & "!E16") -> 0.3044 | M3: =INDIRECT(csv_selection!$B$1 & csv_selection!$C$1 & "!E17") -> 0.2308 | N3: =INDIRECT(csv_selection!$B$1 & csv_selection!$C$1 & "!E18") -> 0 | O3: =INDIRECT(csv_selection!$B$1 & csv_selection!$C$1 & "!E20") -> 0.1947 | P3: =INDIRECT(csv_selection!$B$1 & csv_selection!$C$1 & "!E21") -> 0.1778 | Q3: =INDIRECT(csv_selection!$B$1 & csv_selection!$C$1 & "!E23") -> 0.318 | R3: =INDIRECT(csv_selection!$B$1 & csv_selection!$C$1 & "!E24") -> 0.7741 | S3: =INDIRECT(csv_selection!$B$1 & csv_selection!$C$1 & "!E25") -> 0.9815 | T3: =INDIRECT(csv_selection!$B$1 & csv_selection!$C$1 & "!E26") -> 0.9894 | U3: =INDIRECT(csv_selection!$B$1 & csv_selection!$C$1 & "!E27") -> 0.5876 | V3: =INDIRECT(csv_selection!$B$1 & csv_selection!$C$1 & "!E28") -> 0.356 | W3: =INDIRECT(csv_selection!$B$1 & csv_selection!$C$1 & "!E31") -> 1 | X3: =INDIRECT(csv_selection!$B$1 & csv_selection!$C$1 & "!E32") -> 1 | Y3: =INDIRECT(csv_selection!$B$1 & csv_selection!$C$1 & "!E33") -> 1 | Z3: =INDIRECT(csv_selection!$B$1 & csv_selection!$C$1 & "!E34") -> 1 | AA3: =INDIRECT(csv_selection!$B$1 & csv_selection!$C$1 & "!E35") -> 1 | AB3: =INDIRECT(csv_selection!$B$1 & csv_selection!$C$1 & "!E36") -> 1 | AC3: =INDIRECT(csv_selection!$B$1 & csv_selection!$C$1 & "!E37") -> 1 | AD3: =INDIRECT(csv_selection!$B$1 & csv_selection!$C$1 & "!E38") -> 1 | AE3: =INDIRECT(csv_selection!$B$1 & csv_selection!$C$1 & "!E40") -> 0 | AF3: =INDIRECT(csv_selection!$B$1 & csv_selection!$C$1 & "!E41") -> 0 | AG3: =INDIRECT(csv_selection!$B$1 & csv_selection!$C$1 & "!E42") -> 0 | AH3: =INDIRECT(csv_selection!$B$1 & csv_selection!$C$1 & "!E43") -> 0 | AI3: =INDIRECT(csv_selection!$B$1 & csv_selection!$C$1 & "!E44") -> 0 | AJ3: =INDIRECT(csv_selection!$B$1 & csv_selection!$C$1 & "!E45") -> 0 | AK3: =INDIRECT(csv_selection!$B$1 & csv_selection!$C$1 & "!E46") -> 0 | AL3: =INDIRECT(csv_selection!$B$1 & csv_selection!$C$1 & "!E47") -> 0 | AM3: =INDIRECT(csv_selection!$B$1 & csv_selection!$C$1 & "!E50") -> CLaw_perm | AN3: =INDIRECT(csv_selection!$B$1 & csv_selection!$C$1 & "!E51") -> CLaw_perm | AO3: =INDIRECT(csv_selection!$B$1 & csv_selection!$C$1 & "!E52") -> CLaw_perm | AP3: =INDIRECT(csv_selection!$B$1 & csv_selection!$C$1 & "!E53") -> CLaw_perm | AQ3: =INDIRECT(csv_selection!$B$1 & csv_selection!$C$1 & "!E54") -> CLCC_perm | AR3: =INDIRECT(csv_selection!$B$1 & csv_selection!$C$1 & "!E55") -> CLPT_perm | AS3: =INDIRECT(csv_selection!$B$1 & csv_selection!$C$1 & "!E56") -> CLaw_temp | AT3: =INDIRECT(csv_selection!$B$1 & csv_selection!$C$1 & "!E58") -> Claw_perm | AU3: =INDIRECT(csv_selection!$B$1 & csv_selection!$C$1 & "!E59") -> CLaw_rduc | AV3: =INDIRECT(csv_selection!$B$1 & csv_selection!$C$1 & "!E61") -> CLaw_2027 | AW3: =INDIRECT(csv_selection!$B$1 & csv_selection!$C$1 & "!E63") -> CLaw_perm | AX3: =INDIRECT(csv_selection!$B$1 & csv_selection!$C$1 & "!E64") -> CLaw_perm | AY3: =INDIRECT(csv_selection!$B$1 & csv_selection!$C$1 & "!E65") -> CLaw_perm | AZ3: =INDIRECT(csv_selection!$B$1 & csv_selection!$C$1 & "!E66") -> CLaw_perm | BA3: =INDIRECT(csv_selection!$B$1 & csv_selection!$C$1 & "!E67") -> CLaw_perm | BB3: =INDIRECT(csv_selection!$B$1 & csv_selection!$C$1 & "!E69") -> 0.63 | BC3: =INDIRECT(csv_selection!$B$1 & csv_selection!$C$1 & "!E70") -> 0.0335 | BD3: =INDIRECT(csv_selection!$B$1 & csv_selection!$C$1 & "!E71") -> 0.3365 | BE3: =INDIRECT(csv_selection!$B$1 & csv_selection!$C$1 & "!E72") -> 0.3917 | BF3: =INDIRECT(csv_selection!$B$1 & csv_selection!$C$1 & "!E73") -> 0.1925 | BG3: =INDIRECT(csv_selection!$B$1 & csv_selection!$C$1 & "!E74") -> 0.4158 | BH3: =INDIRECT(csv_selection!$B$1 & csv_selection!$C$1 & "!E75") -> 1 | BI3: =INDIRECT(csv_selection!$B$1 & csv_selection!$C$1 & "!E76") -> 0 | BJ3: =INDIRECT(csv_selection!$B$1 & csv_selection!$C$1 & "!E77") -> 0 | BK3: =INDIRECT(csv_selection!$B$1 & csv_selection!$C$1 & "!E78") -> 0.6907 | BL3: =INDIRECT(csv_selection!$B$1 & csv_selection!$C$1 & "!E79") -> 0.1284 | BM3: =INDIRECT(csv_selection!$B$1 & csv_selection!$C$1 & "!E80") -> 0.1809 | BN3: =INDIRECT(csv_selection!$B$1 & csv_selection!$C$1 & "!E81") -> 1 | BO3: =INDIRECT(csv_selection!$B$1 & csv_selection!$C$1 & "!E82") -> 0 | BP3: =INDIRECT(csv_selection!$B$1 & csv_selection!$C$1 & "!E83") -> 0 | BQ3: =INDIRECT(csv_selection!$B$1 & csv_selection!$C$1 & "!E84") -> 0.8138 | BR3: =INDIRECT(csv_selection!$B$1 & csv_selection!$C$1 & "!E85") -> 0.0578 | BS3: =INDIRECT(csv_selection!$B$1 & csv_selection!$C$1 & "!E86") -> 0.1284
A4: =INDIRECT(csv_selection!$B$1 & csv_selection!$C$1 & "!F2") -> 2028 | B4: =INDIRECT(csv_selection!$B$1 & csv_selection!$C$1 & "!F5") -> 0.21 | C4: =INDIRECT(csv_selection!$B$1 & csv_selection!$C$1 & "!F6") -> 0.3051 | D4: =INDIRECT(csv_selection!$B$1 & csv_selection!$C$1 & "!F7") -> 0.0352 | E4: =INDIRECT(csv_selection!$B$1 & csv_selection!$C$1 & "!F8") -> 0.01 | F4: =INDIRECT(csv_selection!$B$1 & csv_selection!$C$1 & "!F9") -> 0 | G4: =INDIRECT(csv_selection!$B$1 & csv_selection!$C$1 & "!F11") -> 0.2006 | H4: =INDIRECT(csv_selection!$B$1 & csv_selection!$C$1 & "!F12") -> 0.3409 | I4: =INDIRECT(csv_selection!$B$1 & csv_selection!$C$1 & "!F13") -> 0.2072 | J4: =INDIRECT(csv_selection!$B$1 & csv_selection!$C$1 & "!F14") -> 0 | K4: =INDIRECT(csv_selection!$B$1 & csv_selection!$C$1 & "!F15") -> 0.3045 | L4: =INDIRECT(csv_selection!$B$1 & csv_selection!$C$1 & "!F16") -> 0.3045 | M4: =INDIRECT(csv_selection!$B$1 & csv_selection!$C$1 & "!F17") -> 0.2339 | N4: =INDIRECT(csv_selection!$B$1 & csv_selection!$C$1 & "!F18") -> 0 | O4: =INDIRECT(csv_selection!$B$1 & csv_selection!$C$1 & "!F20") -> 0.1943 | P4: =INDIRECT(csv_selection!$B$1 & csv_selection!$C$1 & "!F21") -> 0.1774 | Q4: =INDIRECT(csv_selection!$B$1 & csv_selection!$C$1 & "!F23") -> 0.3209 | R4: =INDIRECT(csv_selection!$B$1 & csv_selection!$C$1 & "!F24") -> 0.7749 | S4: =INDIRECT(csv_selection!$B$1 & csv_selection!$C$1 & "!F25") -> 0.9768 | T4: =INDIRECT(csv_selection!$B$1 & csv_selection!$C$1 & "!F26") -> 0.9867 | U4: =INDIRECT(csv_selection!$B$1 & csv_selection!$C$1 & "!F27") -> 0.6222 | V4: =INDIRECT(csv_selection!$B$1 & csv_selection!$C$1 & "!F28") -> 0.3709 | W4: =INDIRECT(csv_selection!$B$1 & csv_selection!$C$1 & "!F31") -> 1 | X4: =INDIRECT(csv_selection!$B$1 & csv_selection!$C$1 & "!F32") -> 1 | Y4: =INDIRECT(csv_selection!$B$1 & csv_selection!$C$1 & "!F33") -> 1 | Z4: =INDIRECT(csv_selection!$B$1 & csv_selection!$C$1 & "!F34") -> 1 | AA4: =INDIRECT(csv_selection!$B$1 & csv_selection!$C$1 & "!F35") -> 1 | AB4: =INDIRECT(csv_selection!$B$1 & csv_selection!$C$1 & "!F36") -> 1 | AC4: =INDIRECT(csv_selection!$B$1 & csv_selection!$C$1 & "!F37") -> 1 | AD4: =INDIRECT(csv_selection!$B$1 & csv_selection!$C$1 & "!F38") -> 1 | AE4: =INDIRECT(csv_selection!$B$1 & csv_selection!$C$1 & "!F40") -> 0 | AF4: =INDIRECT(csv_selection!$B$1 & csv_selection!$C$1 & "!F41") -> 0 | AG4: =INDIRECT(csv_selection!$B$1 & csv_selection!$C$1 & "!F42") -> 0 | AH4: =INDIRECT(csv_selection!$B$1 & csv_selection!$C$1 & "!F43") -> 0 | AI4: =INDIRECT(csv_selection!$B$1 & csv_selection!$C$1 & "!F44") -> 0 | AJ4: =INDIRECT(csv_selection!$B$1 & csv_selection!$C$1 & "!F45") -> 0 | AK4: =INDIRECT(csv_selection!$B$1 & csv_selection!$C$1 & "!F46") -> 0 | AL4: =INDIRECT(csv_selection!$B$1 & csv_selection!$C$1 & "!F47") -> 0 | AM4: =INDIRECT(csv_selection!$B$1 & csv_selection!$C$1 & "!F50") -> CLaw_perm | AN4: =INDIRECT(csv_selection!$B$1 & csv_selection!$C$1 & "!F51") -> CLaw_perm | AO4: =INDIRECT(csv_selection!$B$1 & csv_selection!$C$1 & "!F52") -> CLaw_perm | AP4: =INDIRECT(csv_selection!$B$1 & csv_selection!$C$1 & "!F53") -> CLaw_perm | AQ4: =INDIRECT(csv_selection!$B$1 & csv_selection!$C$1 & "!F54") -> CLCC_perm | AR4: =INDIRECT(csv_selection!$B$1 & csv_selection!$C$1 & "!F55") -> CLPT_perm | AS4: =INDIRECT(csv_selection!$B$1 & csv_selection!$C$1 & "!F56") -> CLaw_temp | AT4: =INDIRECT(csv_selection!$B$1 & csv_selection!$C$1 & "!F58") -> Claw_perm | AU4: =INDIRECT(csv_selection!$B$1 & csv_selection!$C$1 & "!F59") -> CLaw_rduc | AV4: =INDIRECT(csv_selection!$B$1 & csv_selection!$C$1 & "!F61") -> CLaw_2028 | AW4: =INDIRECT(csv_selection!$B$1 & csv_selection!$C$1 & "!F63") -> CLaw_perm | AX4: =INDIRECT(csv_selection!$B$1 & csv_selection!$C$1 & "!F64") -> CLaw_perm | AY4: =INDIRECT(csv_selection!$B$1 & csv_selection!$C$1 & "!F65") -> CLaw_perm | AZ4: =INDIRECT(csv_selection!$B$1 & csv_selection!$C$1 & "!F66") -> CLaw_perm | BA4: =INDIRECT(csv_selection!$B$1 & csv_selection!$C$1 & "!F67") -> CLaw_perm | BB4: =INDIRECT(csv_selection!$B$1 & csv_selection!$C$1 & "!F69") -> 0.627 | BC4: =INDIRECT(csv_selection!$B$1 & csv_selection!$C$1 & "!F70") -> 0.0335 | BD4: =INDIRECT(csv_selection!$B$1 & csv_selection!$C$1 & "!F71") -> 0.3395 | BE4: =INDIRECT(csv_selection!$B$1 & csv_selection!$C$1 & "!F72") -> 0.3889 | BF4: =INDIRECT(csv_selection!$B$1 & csv_selection!$C$1 & "!F73") -> 0.1925 | BG4: =INDIRECT(csv_selection!$B$1 & csv_selection!$C$1 & "!F74") -> 0.4186 | BH4: =INDIRECT(csv_selection!$B$1 & csv_selection!$C$1 & "!F75") -> 1 | BI4: =INDIRECT(csv_selection!$B$1 & csv_selection!$C$1 & "!F76") -> 0 | BJ4: =INDIRECT(csv_selection!$B$1 & csv_selection!$C$1 & "!F77") -> 0 | BK4: =INDIRECT(csv_selection!$B$1 & csv_selection!$C$1 & "!F78") -> 0.6896 | BL4: =INDIRECT(csv_selection!$B$1 & csv_selection!$C$1 & "!F79") -> 0.1284 | BM4: =INDIRECT(csv_selection!$B$1 & csv_selection!$C$1 & "!F80") -> 0.182 | BN4: =INDIRECT(csv_selection!$B$1 & csv_selection!$C$1 & "!F81") -> 1 | BO4: =INDIRECT(csv_selection!$B$1 & csv_selection!$C$1 & "!F82") -> 0 | BP4: =INDIRECT(csv_selection!$B$1 & csv_selection!$C$1 & "!F83") -> 0 | BQ4: =INDIRECT(csv_selection!$B$1 & csv_selection!$C$1 & "!F84") -> 0.8133 | BR4: =INDIRECT(csv_selection!$B$1 & csv_selection!$C$1 & "!F85") -> 0.0578 | BS4: =INDIRECT(csv_selection!$B$1 & csv_selection!$C$1 & "!F86") -> 0.1289
A5: =INDIRECT(csv_selection!$B$1 & csv_selection!$C$1 & "!G2") -> 2029 | B5: =INDIRECT(csv_selection!$B$1 & csv_selection!$C$1 & "!G5") -> 0.21 | C5: =INDIRECT(csv_selection!$B$1 & csv_selection!$C$1 & "!G6") -> 0.3103 | D5: =INDIRECT(csv_selection!$B$1 & csv_selection!$C$1 & "!G7") -> 0.0352 | E5: =INDIRECT(csv_selection!$B$1 & csv_selection!$C$1 & "!G8") -> 0.01 | F5: =INDIRECT(csv_selection!$B$1 & csv_selection!$C$1 & "!G9") -> 0 | G5: =INDIRECT(csv_selection!$B$1 & csv_selection!$C$1 & "!G11") -> 0.1968 | H5: =INDIRECT(csv_selection!$B$1 & csv_selection!$C$1 & "!G12") -> 0.3347 | I5: =INDIRECT(csv_selection!$B$1 & csv_selection!$C$1 & "!G13") -> 0.2051 | J5: =INDIRECT(csv_selection!$B$1 & csv_selection!$C$1 & "!G14") -> 0 | K5: =INDIRECT(csv_selection!$B$1 & csv_selection!$C$1 & "!G15") -> 0.3041 | L5: =INDIRECT(csv_selection!$B$1 & csv_selection!$C$1 & "!G16") -> 0.3041 | M5: =INDIRECT(csv_selection!$B$1 & csv_selection!$C$1 & "!G17") -> 0.2311 | N5: =INDIRECT(csv_selection!$B$1 & csv_selection!$C$1 & "!G18") -> 0 | O5: =INDIRECT(csv_selection!$B$1 & csv_selection!$C$1 & "!G20") -> 0.1976 | P5: =INDIRECT(csv_selection!$B$1 & csv_selection!$C$1 & "!G21") -> 0.1817 | Q5: =INDIRECT(csv_selection!$B$1 & csv_selection!$C$1 & "!G23") -> 0.3133 | R5: =INDIRECT(csv_selection!$B$1 & csv_selection!$C$1 & "!G24") -> 0.775 | S5: =INDIRECT(csv_selection!$B$1 & csv_selection!$C$1 & "!G25") -> 0.9739 | T5: =INDIRECT(csv_selection!$B$1 & csv_selection!$C$1 & "!G26") -> 0.985 | U5: =INDIRECT(csv_selection!$B$1 & csv_selection!$C$1 & "!G27") -> 0.6473 | V5: =INDIRECT(csv_selection!$B$1 & csv_selection!$C$1 & "!G28") -> 0.3781 | W5: =INDIRECT(csv_selection!$B$1 & csv_selection!$C$1 & "!G31") -> 1 | X5: =INDIRECT(csv_selection!$B$1 & csv_selection!$C$1 & "!G32") -> 1 | Y5: =INDIRECT(csv_selection!$B$1 & csv_selection!$C$1 & "!G33") -> 1 | Z5: =INDIRECT(csv_selection!$B$1 & csv_selection!$C$1 & "!G34") -> 1 | AA5: =INDIRECT(csv_selection!$B$1 & csv_selection!$C$1 & "!G35") -> 1 | AB5: =INDIRECT(csv_selection!$B$1 & csv_selection!$C$1 & "!G36") -> 1 | AC5: =INDIRECT(csv_selection!$B$1 & csv_selection!$C$1 & "!G37") -> 1 | AD5: =INDIRECT(csv_selection!$B$1 & csv_selection!$C$1 & "!G38") -> 1 | AE5: =INDIRECT(csv_selection!$B$1 & csv_selection!$C$1 & "!G40") -> 0 | AF5: =INDIRECT(csv_selection!$B$1 & csv_selection!$C$1 & "!G41") -> 0 | AG5: =INDIRECT(csv_selection!$B$1 & csv_selection!$C$1 & "!G42") -> 0 | AH5: =INDIRECT(csv_selection!$B$1 & csv_selection!$C$1 & "!G43") -> 0 | AI5: =INDIRECT(csv_selection!$B$1 & csv_selection!$C$1 & "!G44") -> 0 | AJ5: =INDIRECT(csv_selection!$B$1 & csv_selection!$C$1 & "!G45") -> 0 | AK5: =INDIRECT(csv_selection!$B$1 & csv_selection!$C$1 & "!G46") -> 0 | AL5: =INDIRECT(csv_selection!$B$1 & csv_selection!$C$1 & "!G47") -> 0 | AM5: =INDIRECT(csv_selection!$B$1 & csv_selection!$C$1 & "!G50") -> CLaw_perm | AN5: =INDIRECT(csv_selection!$B$1 & csv_selection!$C$1 & "!G51") -> CLaw_perm | AO5: =INDIRECT(csv_selection!$B$1 & csv_selection!$C$1 & "!G52") -> CLaw_perm | AP5: =INDIRECT(csv_selection!$B$1 & csv_selection!$C$1 & "!G53") -> CLaw_perm | AQ5: =INDIRECT(csv_selection!$B$1 & csv_selection!$C$1 & "!G54") -> CLCC_perm | AR5: =INDIRECT(csv_selection!$B$1 & csv_selection!$C$1 & "!G55") -> CLPT_perm | AS5: =INDIRECT(csv_selection!$B$1 & csv_selection!$C$1 & "!G56") -> CLaw_perm | AT5: =INDIRECT(csv_selection!$B$1 & csv_selection!$C$1 & "!G58") -> Claw_perm | AU5: =INDIRECT(csv_selection!$B$1 & csv_selection!$C$1 & "!G59") -> CLaw_rduc | AV5: =INDIRECT(csv_selection!$B$1 & csv_selection!$C$1 & "!G61") -> CLaw_2029 | AW5: =INDIRECT(csv_selection!$B$1 & csv_selection!$C$1 & "!G63") -> CLaw_perm | AX5: =INDIRECT(csv_selection!$B$1 & csv_selection!$C$1 & "!G64") -> CLaw_perm | AY5: =INDIRECT(csv_selection!$B$1 & csv_selection!$C$1 & "!G65") -> CLaw_perm | AZ5: =INDIRECT(csv_selection!$B$1 & csv_selection!$C$1 & "!G66") -> CLaw_perm | BA5: =INDIRECT(csv_selection!$B$1 & csv_selection!$C$1 & "!G67") -> CLaw_perm | BB5: =INDIRECT(csv_selection!$B$1 & csv_selection!$C$1 & "!G69") -> 0.6321 | BC5: =INDIRECT(csv_selection!$B$1 & csv_selection!$C$1 & "!G70") -> 0.0335 | BD5: =INDIRECT(csv_selection!$B$1 & csv_selection!$C$1 & "!G71") -> 0.3344 | BE5: =INDIRECT(csv_selection!$B$1 & csv_selection!$C$1 & "!G72") -> 0.3934 | BF5: =INDIRECT(csv_selection!$B$1 & csv_selection!$C$1 & "!G73") -> 0.1925 | BG5: =INDIRECT(csv_selection!$B$1 & csv_selection!$C$1 & "!G74") -> 0.4141 | BH5: =INDIRECT(csv_selection!$B$1 & csv_selection!$C$1 & "!G75") -> 1 | BI5: =INDIRECT(csv_selection!$B$1 & csv_selection!$C$1 & "!G76") -> 0 | BJ5: =INDIRECT(csv_selection!$B$1 & csv_selection!$C$1 & "!G77") -> 0 | BK5: =INDIRECT(csv_selection!$B$1 & csv_selection!$C$1 & "!G78") -> 0.6915 | BL5: =INDIRECT(csv_selection!$B$1 & csv_selection!$C$1 & "!G79") -> 0.1284 | BM5: =INDIRECT(csv_selection!$B$1 & csv_selection!$C$1 & "!G80") -> 0.1801 | BN5: =INDIRECT(csv_selection!$B$1 & csv_selection!$C$1 & "!G81") -> 1 | BO5: =INDIRECT(csv_selection!$B$1 & csv_selection!$C$1 & "!G82") -> 0 | BP5: =INDIRECT(csv_selection!$B$1 & csv_selection!$C$1 & "!G83") -> 0 | BQ5: =INDIRECT(csv_selection!$B$1 & csv_selection!$C$1 & "!G84") -> 0.8143 | BR5: =INDIRECT(csv_selection!$B$1 & csv_selection!$C$1 & "!G85") -> 0.0578 | BS5: =INDIRECT(csv_selection!$B$1 & csv_selection!$C$1 & "!G86") -> 0.1279
A6: =INDIRECT(csv_selection!$B$1 & csv_selection!$C$1 & "!H2") -> 2030 | B6: =INDIRECT(csv_selection!$B$1 & csv_selection!$C$1 & "!H5") -> 0.21 | C6: =INDIRECT(csv_selection!$B$1 & csv_selection!$C$1 & "!H6") -> 0.3121 | D6: =INDIRECT(csv_selection!$B$1 & csv_selection!$C$1 & "!H7") -> 0.0352 | E6: =INDIRECT(csv_selection!$B$1 & csv_selection!$C$1 & "!H8") -> 0.01 | F6: =INDIRECT(csv_selection!$B$1 & csv_selection!$C$1 & "!H9") -> 0 | G6: =INDIRECT(csv_selection!$B$1 & csv_selection!$C$1 & "!H11") -> 0.1991 | H6: =INDIRECT(csv_selection!$B$1 & csv_selection!$C$1 & "!H12") -> 0.3331 | I6: =INDIRECT(csv_selection!$B$1 & csv_selection!$C$1 & "!H13") -> 0.2041 | J6: =INDIRECT(csv_selection!$B$1 & csv_selection!$C$1 & "!H14") -> 0 | K6: =INDIRECT(csv_selection!$B$1 & csv_selection!$C$1 & "!H15") -> 0.3064 | L6: =INDIRECT(csv_selection!$B$1 & csv_selection!$C$1 & "!H16") -> 0.3064 | M6: =INDIRECT(csv_selection!$B$1 & csv_selection!$C$1 & "!H17") -> 0.2331 | N6: =INDIRECT(csv_selection!$B$1 & csv_selection!$C$1 & "!H18") -> 0 | O6: =INDIRECT(csv_selection!$B$1 & csv_selection!$C$1 & "!H20") -> 0.1978 | P6: =INDIRECT(csv_selection!$B$1 & csv_selection!$C$1 & "!H21") -> 0.1816 | Q6: =INDIRECT(csv_selection!$B$1 & csv_selection!$C$1 & "!H23") -> 0.305 | R6: =INDIRECT(csv_selection!$B$1 & csv_selection!$C$1 & "!H24") -> 0.7743 | S6: =INDIRECT(csv_selection!$B$1 & csv_selection!$C$1 & "!H25") -> 0.9724 | T6: =INDIRECT(csv_selection!$B$1 & csv_selection!$C$1 & "!H26") -> 0.9841 | U6: =INDIRECT(csv_selection!$B$1 & csv_selection!$C$1 & "!H27") -> 0.5526 | V6: =INDIRECT(csv_selection!$B$1 & csv_selection!$C$1 & "!H28") -> 0.0435 | W6: =INDIRECT(csv_selection!$B$1 & csv_selection!$C$1 & "!H31") -> 1 | X6: =INDIRECT(csv_selection!$B$1 & csv_selection!$C$1 & "!H32") -> 1 | Y6: =INDIRECT(csv_selection!$B$1 & csv_selection!$C$1 & "!H33") -> 1 | Z6: =INDIRECT(csv_selection!$B$1 & csv_selection!$C$1 & "!H34") -> 1 | AA6: =INDIRECT(csv_selection!$B$1 & csv_selection!$C$1 & "!H35") -> 1 | AB6: =INDIRECT(csv_selection!$B$1 & csv_selection!$C$1 & "!H36") -> 1 | AC6: =INDIRECT(csv_selection!$B$1 & csv_selection!$C$1 & "!H37") -> 1 | AD6: =INDIRECT(csv_selection!$B$1 & csv_selection!$C$1 & "!H38") -> 1 | AE6: =INDIRECT(csv_selection!$B$1 & csv_selection!$C$1 & "!H40") -> 0 | AF6: =INDIRECT(csv_selection!$B$1 & csv_selection!$C$1 & "!H41") -> 0 | AG6: =INDIRECT(csv_selection!$B$1 & csv_selection!$C$1 & "!H42") -> 0 | AH6: =INDIRECT(csv_selection!$B$1 & csv_selection!$C$1 & "!H43") -> 0 | AI6: =INDIRECT(csv_selection!$B$1 & csv_selection!$C$1 & "!H44") -> 0 | AJ6: =INDIRECT(csv_selection!$B$1 & csv_selection!$C$1 & "!H45") -> 0 | AK6: =INDIRECT(csv_selection!$B$1 & csv_selection!$C$1 & "!H46") -> 0 | AL6: =INDIRECT(csv_selection!$B$1 & csv_selection!$C$1 & "!H47") -> 0 | AM6: =INDIRECT(csv_selection!$B$1 & csv_selection!$C$1 & "!H50") -> CLaw_perm | AN6: =INDIRECT(csv_selection!$B$1 & csv_selection!$C$1 & "!H51") -> CLaw_perm | AO6: =INDIRECT(csv_selection!$B$1 & csv_selection!$C$1 & "!H52") -> CLaw_perm | AP6: =INDIRECT(csv_selection!$B$1 & csv_selection!$C$1 & "!H53") -> CLaw_perm | AQ6: =INDIRECT(csv_selection!$B$1 & csv_selection!$C$1 & "!H54") -> CLCC_perm | AR6: =INDIRECT(csv_selection!$B$1 & csv_selection!$C$1 & "!H55") -> CLPT_perm | AS6: =INDIRECT(csv_selection!$B$1 & csv_selection!$C$1 & "!H56") -> CLaw_perm | AT6: =INDIRECT(csv_selection!$B$1 & csv_selection!$C$1 & "!H58") -> Claw_perm | AU6: =INDIRECT(csv_selection!$B$1 & csv_selection!$C$1 & "!H59") -> CLaw_rduc | AV6: =INDIRECT(csv_selection!$B$1 & csv_selection!$C$1 & "!H61") -> CLaw_2030 | AW6: =INDIRECT(csv_selection!$B$1 & csv_selection!$C$1 & "!H63") -> CLaw_perm | AX6: =INDIRECT(csv_selection!$B$1 & csv_selection!$C$1 & "!H64") -> CLaw_perm | AY6: =INDIRECT(csv_selection!$B$1 & csv_selection!$C$1 & "!H65") -> CLaw_perm | AZ6: =INDIRECT(csv_selection!$B$1 & csv_selection!$C$1 & "!H66") -> CLaw_perm | BA6: =INDIRECT(csv_selection!$B$1 & csv_selection!$C$1 & "!H67") -> CLaw_perm | BB6: =INDIRECT(csv_selection!$B$1 & csv_selection!$C$1 & "!H69") -> 0.6327 | BC6: =INDIRECT(csv_selection!$B$1 & csv_selection!$C$1 & "!H70") -> 0.0335 | BD6: =INDIRECT(csv_selection!$B$1 & csv_selection!$C$1 & "!H71") -> 0.3338 | BE6: =INDIRECT(csv_selection!$B$1 & csv_selection!$C$1 & "!H72") -> 0.3941 | BF6: =INDIRECT(csv_selection!$B$1 & csv_selection!$C$1 & "!H73") -> 0.1925 | BG6: =INDIRECT(csv_selection!$B$1 & csv_selection!$C$1 & "!H74") -> 0.4134 | BH6: =INDIRECT(csv_selection!$B$1 & csv_selection!$C$1 & "!H75") -> 1 | BI6: =INDIRECT(csv_selection!$B$1 & csv_selection!$C$1 & "!H76") -> 0 | BJ6: =INDIRECT(csv_selection!$B$1 & csv_selection!$C$1 & "!H77") -> 0 | BK6: =INDIRECT(csv_selection!$B$1 & csv_selection!$C$1 & "!H78") -> 0.6917 | BL6: =INDIRECT(csv_selection!$B$1 & csv_selection!$C$1 & "!H79") -> 0.1284 | BM6: =INDIRECT(csv_selection!$B$1 & csv_selection!$C$1 & "!H80") -> 0.1799 | BN6: =INDIRECT(csv_selection!$B$1 & csv_selection!$C$1 & "!H81") -> 1 | BO6: =INDIRECT(csv_selection!$B$1 & csv_selection!$C$1 & "!H82") -> 0 | BP6: =INDIRECT(csv_selection!$B$1 & csv_selection!$C$1 & "!H83") -> 0 | BQ6: =INDIRECT(csv_selection!$B$1 & csv_selection!$C$1 & "!H84") -> 0.8143 | BR6: =INDIRECT(csv_selection!$B$1 & csv_selection!$C$1 & "!H85") -> 0.0578 | BS6: =INDIRECT(csv_selection!$B$1 & csv_selection!$C$1 & "!H86") -> 0.1279
A7: =INDIRECT(csv_selection!$B$1 & csv_selection!$C$1 & "!I2") -> 2031 | B7: =INDIRECT(csv_selection!$B$1 & csv_selection!$C$1 & "!I5") -> 0.21 | C7: =INDIRECT(csv_selection!$B$1 & csv_selection!$C$1 & "!I6") -> 0.312 | D7: =INDIRECT(csv_selection!$B$1 & csv_selection!$C$1 & "!I7") -> 0.0352 | E7: =INDIRECT(csv_selection!$B$1 & csv_selection!$C$1 & "!I8") -> 0.01 | F7: =INDIRECT(csv_selection!$B$1 & csv_selection!$C$1 & "!I9") -> 0 | G7: =INDIRECT(csv_selection!$B$1 & csv_selection!$C$1 & "!I11") -> 0.2 | H7: =INDIRECT(csv_selection!$B$1 & csv_selection!$C$1 & "!I12") -> 0.3322 | I7: =INDIRECT(csv_selection!$B$1 & csv_selection!$C$1 & "!I13") -> 0.2038 | J7: =INDIRECT(csv_selection!$B$1 & csv_selection!$C$1 & "!I14") -> 0 | K7: =INDIRECT(csv_selection!$B$1 & csv_selection!$C$1 & "!I15") -> 0.3056 | L7: =INDIRECT(csv_selection!$B$1 & csv_selection!$C$1 & "!I16") -> 0.3056 | M7: =INDIRECT(csv_selection!$B$1 & csv_selection!$C$1 & "!I17") -> 0.2341 | N7: =INDIRECT(csv_selection!$B$1 & csv_selection!$C$1 & "!I18") -> 0 | O7: =INDIRECT(csv_selection!$B$1 & csv_selection!$C$1 & "!I20") -> 0.1978 | P7: =INDIRECT(csv_selection!$B$1 & csv_selection!$C$1 & "!I21") -> 0.1814 | Q7: =INDIRECT(csv_selection!$B$1 & csv_selection!$C$1 & "!I23") -> 0.3035 | R7: =INDIRECT(csv_selection!$B$1 & csv_selection!$C$1 & "!I24") -> 0.7744 | S7: =INDIRECT(csv_selection!$B$1 & csv_selection!$C$1 & "!I25") -> 0.9723 | T7: =INDIRECT(csv_selection!$B$1 & csv_selection!$C$1 & "!I26") -> 0.9841 | U7: =INDIRECT(csv_selection!$B$1 & csv_selection!$C$1 & "!I27") -> 0.5723 | V7: =INDIRECT(csv_selection!$B$1 & csv_selection!$C$1 & "!I28") -> 0.0436 | W7: =INDIRECT(csv_selection!$B$1 & csv_selection!$C$1 & "!I31") -> 1 | X7: =INDIRECT(csv_selection!$B$1 & csv_selection!$C$1 & "!I32") -> 1 | Y7: =INDIRECT(csv_selection!$B$1 & csv_selection!$C$1 & "!I33") -> 1 | Z7: =INDIRECT(csv_selection!$B$1 & csv_selection!$C$1 & "!I34") -> 1 | AA7: =INDIRECT(csv_selection!$B$1 & csv_selection!$C$1 & "!I35") -> 1 | AB7: =INDIRECT(csv_selection!$B$1 & csv_selection!$C$1 & "!I36") -> 1 | AC7: =INDIRECT(csv_selection!$B$1 & csv_selection!$C$1 & "!I37") -> 1 | AD7: =INDIRECT(csv_selection!$B$1 & csv_selection!$C$1 & "!I38") -> 1 | AE7: =INDIRECT(csv_selection!$B$1 & csv_selection!$C$1 & "!I40") -> 0 | AF7: =INDIRECT(csv_selection!$B$1 & csv_selection!$C$1 & "!I41") -> 0 | AG7: =INDIRECT(csv_selection!$B$1 & csv_selection!$C$1 & "!I42") -> 0 | AH7: =INDIRECT(csv_selection!$B$1 & csv_selection!$C$1 & "!I43") -> 0 | AI7: =INDIRECT(csv_selection!$B$1 & csv_selection!$C$1 & "!I44") -> 0 | AJ7: =INDIRECT(csv_selection!$B$1 & csv_selection!$C$1 & "!I45") -> 0 | AK7: =INDIRECT(csv_selection!$B$1 & csv_selection!$C$1 & "!I46") -> 0 | AL7: =INDIRECT(csv_selection!$B$1 & csv_selection!$C$1 & "!I47") -> 0 | AM7: =INDIRECT(csv_selection!$B$1 & csv_selection!$C$1 & "!I50") -> CLaw_perm | AN7: =INDIRECT(csv_selection!$B$1 & csv_selection!$C$1 & "!I51") -> CLaw_perm | AO7: =INDIRECT(csv_selection!$B$1 & csv_selection!$C$1 & "!I52") -> CLaw_perm | AP7: =INDIRECT(csv_selection!$B$1 & csv_selection!$C$1 & "!I53") -> CLaw_perm | AQ7: =INDIRECT(csv_selection!$B$1 & csv_selection!$C$1 & "!I54") -> CLCC_perm | AR7: =INDIRECT(csv_selection!$B$1 & csv_selection!$C$1 & "!I55") -> CLPT_perm | AS7: =INDIRECT(csv_selection!$B$1 & csv_selection!$C$1 & "!I56") -> CLaw_perm | AT7: =INDIRECT(csv_selection!$B$1 & csv_selection!$C$1 & "!I58") -> Claw_perm | AU7: =INDIRECT(csv_selection!$B$1 & csv_selection!$C$1 & "!I59") -> CLaw_rduc | AV7: =INDIRECT(csv_selection!$B$1 & csv_selection!$C$1 & "!I61") -> CLaw_2031 | AW7: =INDIRECT(csv_selection!$B$1 & csv_selection!$C$1 & "!I63") -> CLaw_perm | AX7: =INDIRECT(csv_selection!$B$1 & csv_selection!$C$1 & "!I64") -> CLaw_perm | AY7: =INDIRECT(csv_selection!$B$1 & csv_selection!$C$1 & "!I65") -> CLaw_perm | AZ7: =INDIRECT(csv_selection!$B$1 & csv_selection!$C$1 & "!I66") -> CLaw_perm | BA7: =INDIRECT(csv_selection!$B$1 & csv_selection!$C$1 & "!I67") -> CLaw_perm | BB7: =INDIRECT(csv_selection!$B$1 & csv_selection!$C$1 & "!I69") -> 0.6359 | BC7: =INDIRECT(csv_selection!$B$1 & csv_selection!$C$1 & "!I70") -> 0.0335 | BD7: =INDIRECT(csv_selection!$B$1 & csv_selection!$C$1 & "!I71") -> 0.3306 | BE7: =INDIRECT(csv_selection!$B$1 & csv_selection!$C$1 & "!I72") -> 0.3965 | BF7: =INDIRECT(csv_selection!$B$1 & csv_selection!$C$1 & "!I73") -> 0.1925 | BG7: =INDIRECT(csv_selection!$B$1 & csv_selection!$C$1 & "!I74") -> 0.411 | BH7: =INDIRECT(csv_selection!$B$1 & csv_selection!$C$1 & "!I75") -> 1 | BI7: =INDIRECT(csv_selection!$B$1 & csv_selection!$C$1 & "!I76") -> 0 | BJ7: =INDIRECT(csv_selection!$B$1 & csv_selection!$C$1 & "!I77") -> 0 | BK7: =INDIRECT(csv_selection!$B$1 & csv_selection!$C$1 & "!I78") -> 0.6928 | BL7: =INDIRECT(csv_selection!$B$1 & csv_selection!$C$1 & "!I79") -> 0.1284 | BM7: =INDIRECT(csv_selection!$B$1 & csv_selection!$C$1 & "!I80") -> 0.1788 | BN7: =INDIRECT(csv_selection!$B$1 & csv_selection!$C$1 & "!I81") -> 1 | BO7: =INDIRECT(csv_selection!$B$1 & csv_selection!$C$1 & "!I82") -> 0 | BP7: =INDIRECT(csv_selection!$B$1 & csv_selection!$C$1 & "!I83") -> 0 | BQ7: =INDIRECT(csv_selection!$B$1 & csv_selection!$C$1 & "!I84") -> 0.815 | BR7: =INDIRECT(csv_selection!$B$1 & csv_selection!$C$1 & "!I85") -> 0.0578 | BS7: =INDIRECT(csv_selection!$B$1 & csv_selection!$C$1 & "!I86") -> 0.1272
A8: =INDIRECT(csv_selection!$B$1 & csv_selection!$C$1 & "!J2") -> 2032 | B8: =INDIRECT(csv_selection!$B$1 & csv_selection!$C$1 & "!J5") -> 0.21 | C8: =INDIRECT(csv_selection!$B$1 & csv_selection!$C$1 & "!J6") -> 0.3121 | D8: =INDIRECT(csv_selection!$B$1 & csv_selection!$C$1 & "!J7") -> 0.0352 | E8: =INDIRECT(csv_selection!$B$1 & csv_selection!$C$1 & "!J8") -> 0.01 | F8: =INDIRECT(csv_selection!$B$1 & csv_selection!$C$1 & "!J9") -> 0 | G8: =INDIRECT(csv_selection!$B$1 & csv_selection!$C$1 & "!J11") -> 0.2018 | H8: =INDIRECT(csv_selection!$B$1 & csv_selection!$C$1 & "!J12") -> 0.33 | I8: =INDIRECT(csv_selection!$B$1 & csv_selection!$C$1 & "!J13") -> 0.2042 | J8: =INDIRECT(csv_selection!$B$1 & csv_selection!$C$1 & "!J14") -> 0 | K8: =INDIRECT(csv_selection!$B$1 & csv_selection!$C$1 & "!J15") -> 0.3041 | L8: =INDIRECT(csv_selection!$B$1 & csv_selection!$C$1 & "!J16") -> 0.3041 | M8: =INDIRECT(csv_selection!$B$1 & csv_selection!$C$1 & "!J17") -> 0.2359 | N8: =INDIRECT(csv_selection!$B$1 & csv_selection!$C$1 & "!J18") -> 0 | O8: =INDIRECT(csv_selection!$B$1 & csv_selection!$C$1 & "!J20") -> 0.1983 | P8: =INDIRECT(csv_selection!$B$1 & csv_selection!$C$1 & "!J21") -> 0.1816 | Q8: =INDIRECT(csv_selection!$B$1 & csv_selection!$C$1 & "!J23") -> 0.3006 | R8: =INDIRECT(csv_selection!$B$1 & csv_selection!$C$1 & "!J24") -> 0.774 | S8: =INDIRECT(csv_selection!$B$1 & csv_selection!$C$1 & "!J25") -> 0.9727 | T8: =INDIRECT(csv_selection!$B$1 & csv_selection!$C$1 & "!J26") -> 0.9842 | U8: =INDIRECT(csv_selection!$B$1 & csv_selection!$C$1 & "!J27") -> 0.589 | V8: =INDIRECT(csv_selection!$B$1 & csv_selection!$C$1 & "!J28") -> 0.0424 | W8: =INDIRECT(csv_selection!$B$1 & csv_selection!$C$1 & "!J31") -> 1 | X8: =INDIRECT(csv_selection!$B$1 & csv_selection!$C$1 & "!J32") -> 1 | Y8: =INDIRECT(csv_selection!$B$1 & csv_selection!$C$1 & "!J33") -> 1 | Z8: =INDIRECT(csv_selection!$B$1 & csv_selection!$C$1 & "!J34") -> 1 | AA8: =INDIRECT(csv_selection!$B$1 & csv_selection!$C$1 & "!J35") -> 1 | AB8: =INDIRECT(csv_selection!$B$1 & csv_selection!$C$1 & "!J36") -> 1 | AC8: =INDIRECT(csv_selection!$B$1 & csv_selection!$C$1 & "!J37") -> 1 | AD8: =INDIRECT(csv_selection!$B$1 & csv_selection!$C$1 & "!J38") -> 1 | AE8: =INDIRECT(csv_selection!$B$1 & csv_selection!$C$1 & "!J40") -> 0 | AF8: =INDIRECT(csv_selection!$B$1 & csv_selection!$C$1 & "!J41") -> 0 | AG8: =INDIRECT(csv_selection!$B$1 & csv_selection!$C$1 & "!J42") -> 0 | AH8: =INDIRECT(csv_selection!$B$1 & csv_selection!$C$1 & "!J43") -> 0 | AI8: =INDIRECT(csv_selection!$B$1 & csv_selection!$C$1 & "!J44") -> 0 | AJ8: =INDIRECT(csv_selection!$B$1 & csv_selection!$C$1 & "!J45") -> 0 | AK8: =INDIRECT(csv_selection!$B$1 & csv_selection!$C$1 & "!J46") -> 0 | AL8: =INDIRECT(csv_selection!$B$1 & csv_selection!$C$1 & "!J47") -> 0 | AM8: =INDIRECT(csv_selection!$B$1 & csv_selection!$C$1 & "!J50") -> CLaw_perm | AN8: =INDIRECT(csv_selection!$B$1 & csv_selection!$C$1 & "!J51") -> CLaw_perm | AO8: =INDIRECT(csv_selection!$B$1 & csv_selection!$C$1 & "!J52") -> CLaw_perm | AP8: =INDIRECT(csv_selection!$B$1 & csv_selection!$C$1 & "!J53") -> CLaw_perm | AQ8: =INDIRECT(csv_selection!$B$1 & csv_selection!$C$1 & "!J54") -> CLCC_perm | AR8: =INDIRECT(csv_selection!$B$1 & csv_selection!$C$1 & "!J55") -> CLPT_perm | AS8: =INDIRECT(csv_selection!$B$1 & csv_selection!$C$1 & "!J56") -> CLaw_perm | AT8: =INDIRECT(csv_selection!$B$1 & csv_selection!$C$1 & "!J58") -> Claw_perm | AU8: =INDIRECT(csv_selection!$B$1 & csv_selection!$C$1 & "!J59") -> CLaw_rduc | AV8: =INDIRECT(csv_selection!$B$1 & csv_selection!$C$1 & "!J61") -> CLaw_2032 | AW8: =INDIRECT(csv_selection!$B$1 & csv_selection!$C$1 & "!J63") -> CLaw_perm | AX8: =INDIRECT(csv_selection!$B$1 & csv_selection!$C$1 & "!J64") -> CLaw_perm | AY8: =INDIRECT(csv_selection!$B$1 & csv_selection!$C$1 & "!J65") -> CLaw_perm | AZ8: =INDIRECT(csv_selection!$B$1 & csv_selection!$C$1 & "!J66") -> CLaw_perm | BA8: =INDIRECT(csv_selection!$B$1 & csv_selection!$C$1 & "!J67") -> CLaw_perm | BB8: =INDIRECT(csv_selection!$B$1 & csv_selection!$C$1 & "!J69") -> 0.6363 | BC8: =INDIRECT(csv_selection!$B$1 & csv_selection!$C$1 & "!J70") -> 0.0335 | BD8: =INDIRECT(csv_selection!$B$1 & csv_selection!$C$1 & "!J71") -> 0.3302 | BE8: =INDIRECT(csv_selection!$B$1 & csv_selection!$C$1 & "!J72") -> 0.3975 | BF8: =INDIRECT(csv_selection!$B$1 & csv_selection!$C$1 & "!J73") -> 0.1925 | BG8: =INDIRECT(csv_selection!$B$1 & csv_selection!$C$1 & "!J74") -> 0.41 | BH8: =INDIRECT(csv_selection!$B$1 & csv_selection!$C$1 & "!J75") -> 1 | BI8: =INDIRECT(csv_selection!$B$1 & csv_selection!$C$1 & "!J76") -> 0 | BJ8: =INDIRECT(csv_selection!$B$1 & csv_selection!$C$1 & "!J77") -> 0 | BK8: =INDIRECT(csv_selection!$B$1 & csv_selection!$C$1 & "!J78") -> 0.693 | BL8: =INDIRECT(csv_selection!$B$1 & csv_selection!$C$1 & "!J79") -> 0.1284 | BM8: =INDIRECT(csv_selection!$B$1 & csv_selection!$C$1 & "!J80") -> 0.1786 | BN8: =INDIRECT(csv_selection!$B$1 & csv_selection!$C$1 & "!J81") -> 1 | BO8: =INDIRECT(csv_selection!$B$1 & csv_selection!$C$1 & "!J82") -> 0 | BP8: =INDIRECT(csv_selection!$B$1 & csv_selection!$C$1 & "!J83") -> 0 | BQ8: =INDIRECT(csv_selection!$B$1 & csv_selection!$C$1 & "!J84") -> 0.8149 | BR8: =INDIRECT(csv_selection!$B$1 & csv_selection!$C$1 & "!J85") -> 0.0578 | BS8: =INDIRECT(csv_selection!$B$1 & csv_selection!$C$1 & "!J86") -> 0.1273
A9: =INDIRECT(csv_selection!$B$1 & csv_selection!$C$1 & "!K2") -> 2033 | B9: =INDIRECT(csv_selection!$B$1 & csv_selection!$C$1 & "!K5") -> 0.21 | C9: =INDIRECT(csv_selection!$B$1 & csv_selection!$C$1 & "!K6") -> 0.3123 | D9: =INDIRECT(csv_selection!$B$1 & csv_selection!$C$1 & "!K7") -> 0.0352 | E9: =INDIRECT(csv_selection!$B$1 & csv_selection!$C$1 & "!K8") -> 0.01 | F9: =INDIRECT(csv_selection!$B$1 & csv_selection!$C$1 & "!K9") -> 0 | G9: =INDIRECT(csv_selection!$B$1 & csv_selection!$C$1 & "!K11") -> 0.2003 | H9: =INDIRECT(csv_selection!$B$1 & csv_selection!$C$1 & "!K12") -> 0.3308 | I9: =INDIRECT(csv_selection!$B$1 & csv_selection!$C$1 & "!K13") -> 0.2046 | J9: =INDIRECT(csv_selection!$B$1 & csv_selection!$C$1 & "!K14") -> 0 | K9: =INDIRECT(csv_selection!$B$1 & csv_selection!$C$1 & "!K15") -> 0.3064 | L9: =INDIRECT(csv_selection!$B$1 & csv_selection!$C$1 & "!K16") -> 0.3064 | M9: =INDIRECT(csv_selection!$B$1 & csv_selection!$C$1 & "!K17") -> 0.2381 | N9: =INDIRECT(csv_selection!$B$1 & csv_selection!$C$1 & "!K18") -> 0 | O9: =INDIRECT(csv_selection!$B$1 & csv_selection!$C$1 & "!K20") -> 0.1988 | P9: =INDIRECT(csv_selection!$B$1 & csv_selection!$C$1 & "!K21") -> 0.1818 | Q9: =INDIRECT(csv_selection!$B$1 & csv_selection!$C$1 & "!K23") -> 0.2979 | R9: =INDIRECT(csv_selection!$B$1 & csv_selection!$C$1 & "!K24") -> 0.7738 | S9: =INDIRECT(csv_selection!$B$1 & csv_selection!$C$1 & "!K25") -> 0.9733 | T9: =INDIRECT(csv_selection!$B$1 & csv_selection!$C$1 & "!K26") -> 0.9846 | U9: =INDIRECT(csv_selection!$B$1 & csv_selection!$C$1 & "!K27") -> 0.6036 | V9: =INDIRECT(csv_selection!$B$1 & csv_selection!$C$1 & "!K28") -> 0.0413 | W9: =INDIRECT(csv_selection!$B$1 & csv_selection!$C$1 & "!K31") -> 1 | X9: =INDIRECT(csv_selection!$B$1 & csv_selection!$C$1 & "!K32") -> 1 | Y9: =INDIRECT(csv_selection!$B$1 & csv_selection!$C$1 & "!K33") -> 1 | Z9: =INDIRECT(csv_selection!$B$1 & csv_selection!$C$1 & "!K34") -> 1 | AA9: =INDIRECT(csv_selection!$B$1 & csv_selection!$C$1 & "!K35") -> 1 | AB9: =INDIRECT(csv_selection!$B$1 & csv_selection!$C$1 & "!K36") -> 1 | AC9: =INDIRECT(csv_selection!$B$1 & csv_selection!$C$1 & "!K37") -> 1 | AD9: =INDIRECT(csv_selection!$B$1 & csv_selection!$C$1 & "!K38") -> 1 | AE9: =INDIRECT(csv_selection!$B$1 & csv_selection!$C$1 & "!K40") -> 0 | AF9: =INDIRECT(csv_selection!$B$1 & csv_selection!$C$1 & "!K41") -> 0 | AG9: =INDIRECT(csv_selection!$B$1 & csv_selection!$C$1 & "!K42") -> 0 | AH9: =INDIRECT(csv_selection!$B$1 & csv_selection!$C$1 & "!K43") -> 0 | AI9: =INDIRECT(csv_selection!$B$1 & csv_selection!$C$1 & "!K44") -> 0 | AJ9: =INDIRECT(csv_selection!$B$1 & csv_selection!$C$1 & "!K45") -> 0 | AK9: =INDIRECT(csv_selection!$B$1 & csv_selection!$C$1 & "!K46") -> 0 | AL9: =INDIRECT(csv_selection!$B$1 & csv_selection!$C$1 & "!K47") -> 0 | AM9: =INDIRECT(csv_selection!$B$1 & csv_selection!$C$1 & "!K50") -> CLaw_perm | AN9: =INDIRECT(csv_selection!$B$1 & csv_selection!$C$1 & "!K51") -> CLaw_perm | AO9: =INDIRECT(csv_selection!$B$1 & csv_selection!$C$1 & "!K52") -> CLaw_perm | AP9: =INDIRECT(csv_selection!$B$1 & csv_selection!$C$1 & "!K53") -> CLaw_perm | AQ9: =INDIRECT(csv_selection!$B$1 & csv_selection!$C$1 & "!K54") -> CLCC_perm | AR9: =INDIRECT(csv_selection!$B$1 & csv_selection!$C$1 & "!K55") -> CLPT_perm | AS9: =INDIRECT(csv_selection!$B$1 & csv_selection!$C$1 & "!K56") -> CLaw_perm | AT9: =INDIRECT(csv_selection!$B$1 & csv_selection!$C$1 & "!K58") -> Claw_perm | AU9: =INDIRECT(csv_selection!$B$1 & csv_selection!$C$1 & "!K59") -> CLaw_rduc | AV9: =INDIRECT(csv_selection!$B$1 & csv_selection!$C$1 & "!K61") -> CLaw_2033 | AW9: =INDIRECT(csv_selection!$B$1 & csv_selection!$C$1 & "!K63") -> CLaw_perm | AX9: =INDIRECT(csv_selection!$B$1 & csv_selection!$C$1 & "!K64") -> CLaw_perm | AY9: =INDIRECT(csv_selection!$B$1 & csv_selection!$C$1 & "!K65") -> CLaw_perm | AZ9: =INDIRECT(csv_selection!$B$1 & csv_selection!$C$1 & "!K66") -> CLaw_perm | BA9: =INDIRECT(csv_selection!$B$1 & csv_selection!$C$1 & "!K67") -> CLaw_perm | BB9: =INDIRECT(csv_selection!$B$1 & csv_selection!$C$1 & "!K69") -> 0.638 | BC9: =INDIRECT(csv_selection!$B$1 & csv_selection!$C$1 & "!K70") -> 0.0335 | BD9: =INDIRECT(csv_selection!$B$1 & csv_selection!$C$1 & "!K71") -> 0.3285 | BE9: =INDIRECT(csv_selection!$B$1 & csv_selection!$C$1 & "!K72") -> 0.3981 | BF9: =INDIRECT(csv_selection!$B$1 & csv_selection!$C$1 & "!K73") -> 0.1925 | BG9: =INDIRECT(csv_selection!$B$1 & csv_selection!$C$1 & "!K74") -> 0.4094 | BH9: =INDIRECT(csv_selection!$B$1 & csv_selection!$C$1 & "!K75") -> 1 | BI9: =INDIRECT(csv_selection!$B$1 & csv_selection!$C$1 & "!K76") -> 0 | BJ9: =INDIRECT(csv_selection!$B$1 & csv_selection!$C$1 & "!K77") -> 0 | BK9: =INDIRECT(csv_selection!$B$1 & csv_selection!$C$1 & "!K78") -> 0.6935 | BL9: =INDIRECT(csv_selection!$B$1 & csv_selection!$C$1 & "!K79") -> 0.1284 | BM9: =INDIRECT(csv_selection!$B$1 & csv_selection!$C$1 & "!K80") -> 0.1781 | BN9: =INDIRECT(csv_selection!$B$1 & csv_selection!$C$1 & "!K81") -> 1 | BO9: =INDIRECT(csv_selection!$B$1 & csv_selection!$C$1 & "!K82") -> 0 | BP9: =INDIRECT(csv_selection!$B$1 & csv_selection!$C$1 & "!K83") -> 0 | BQ9: =INDIRECT(csv_selection!$B$1 & csv_selection!$C$1 & "!K84") -> 0.8154 | BR9: =INDIRECT(csv_selection!$B$1 & csv_selection!$C$1 & "!K85") -> 0.0578 | BS9: =INDIRECT(csv_selection!$B$1 & csv_selection!$C$1 & "!K86") -> 0.1268
A10: =INDIRECT(csv_selection!$B$1 & csv_selection!$C$1 & "!L2") -> 2034 | B10: =INDIRECT(csv_selection!$B$1 & csv_selection!$C$1 & "!L5") -> 0.21 | C10: =INDIRECT(csv_selection!$B$1 & csv_selection!$C$1 & "!L6") -> 0.3139 | D10: =INDIRECT(csv_selection!$B$1 & csv_selection!$C$1 & "!L7") -> 0.0352 | E10: =INDIRECT(csv_selection!$B$1 & csv_selection!$C$1 & "!L8") -> 0.01 | F10: =INDIRECT(csv_selection!$B$1 & csv_selection!$C$1 & "!L9") -> 0 | G10: =INDIRECT(csv_selection!$B$1 & csv_selection!$C$1 & "!L11") -> 0.2022 | H10: =INDIRECT(csv_selection!$B$1 & csv_selection!$C$1 & "!L12") -> 0.332 | I10: =INDIRECT(csv_selection!$B$1 & csv_selection!$C$1 & "!L13") -> 0.2049 | J10: =INDIRECT(csv_selection!$B$1 & csv_selection!$C$1 & "!L14") -> 0 | K10: =INDIRECT(csv_selection!$B$1 & csv_selection!$C$1 & "!L15") -> 0.3056 | L10: =INDIRECT(csv_selection!$B$1 & csv_selection!$C$1 & "!L16") -> 0.3056 | M10: =INDIRECT(csv_selection!$B$1 & csv_selection!$C$1 & "!L17") -> 0.2364 | N10: =INDIRECT(csv_selection!$B$1 & csv_selection!$C$1 & "!L18") -> 0 | O10: =INDIRECT(csv_selection!$B$1 & csv_selection!$C$1 & "!L20") -> 0.1996 | P10: =INDIRECT(csv_selection!$B$1 & csv_selection!$C$1 & "!L21") -> 0.1823 | Q10: =INDIRECT(csv_selection!$B$1 & csv_selection!$C$1 & "!L23") -> 0.2948 | R10: =INDIRECT(csv_selection!$B$1 & csv_selection!$C$1 & "!L24") -> 0.7739 | S10: =INDIRECT(csv_selection!$B$1 & csv_selection!$C$1 & "!L25") -> 0.9736 | T10: =INDIRECT(csv_selection!$B$1 & csv_selection!$C$1 & "!L26") -> 0.9848 | U10: =INDIRECT(csv_selection!$B$1 & csv_selection!$C$1 & "!L27") -> 0.6137 | V10: =INDIRECT(csv_selection!$B$1 & csv_selection!$C$1 & "!L28") -> 0.04 | W10: =INDIRECT(csv_selection!$B$1 & csv_selection!$C$1 & "!L31") -> 1 | X10: =INDIRECT(csv_selection!$B$1 & csv_selection!$C$1 & "!L32") -> 1 | Y10: =INDIRECT(csv_selection!$B$1 & csv_selection!$C$1 & "!L33") -> 1 | Z10: =INDIRECT(csv_selection!$B$1 & csv_selection!$C$1 & "!L34") -> 1 | AA10: =INDIRECT(csv_selection!$B$1 & csv_selection!$C$1 & "!L35") -> 1 | AB10: =INDIRECT(csv_selection!$B$1 & csv_selection!$C$1 & "!L36") -> 1 | AC10: =INDIRECT(csv_selection!$B$1 & csv_selection!$C$1 & "!L37") -> 1 | AD10: =INDIRECT(csv_selection!$B$1 & csv_selection!$C$1 & "!L38") -> 1 | AE10: =INDIRECT(csv_selection!$B$1 & csv_selection!$C$1 & "!L40") -> 0 | AF10: =INDIRECT(csv_selection!$B$1 & csv_selection!$C$1 & "!L41") -> 0 | AG10: =INDIRECT(csv_selection!$B$1 & csv_selection!$C$1 & "!L42") -> 0 | AH10: =INDIRECT(csv_selection!$B$1 & csv_selection!$C$1 & "!L43") -> 0 | AI10: =INDIRECT(csv_selection!$B$1 & csv_selection!$C$1 & "!L44") -> 0 | AJ10: =INDIRECT(csv_selection!$B$1 & csv_selection!$C$1 & "!L45") -> 0 | AK10: =INDIRECT(csv_selection!$B$1 & csv_selection!$C$1 & "!L46") -> 0 | AL10: =INDIRECT(csv_selection!$B$1 & csv_selection!$C$1 & "!L47") -> 0 | AM10: =INDIRECT(csv_selection!$B$1 & csv_selection!$C$1 & "!L50") -> CLaw_perm | AN10: =INDIRECT(csv_selection!$B$1 & csv_selection!$C$1 & "!L51") -> CLaw_perm | AO10: =INDIRECT(csv_selection!$B$1 & csv_selection!$C$1 & "!L52") -> CLaw_perm | AP10: =INDIRECT(csv_selection!$B$1 & csv_selection!$C$1 & "!L53") -> CLaw_perm | AQ10: =INDIRECT(csv_selection!$B$1 & csv_selection!$C$1 & "!L54") -> CLCC_perm | AR10: =INDIRECT(csv_selection!$B$1 & csv_selection!$C$1 & "!L55") -> CLPT_perm | AS10: =INDIRECT(csv_selection!$B$1 & csv_selection!$C$1 & "!L56") -> CLaw_perm | AT10: =INDIRECT(csv_selection!$B$1 & csv_selection!$C$1 & "!L58") -> Claw_perm | AU10: =INDIRECT(csv_selection!$B$1 & csv_selection!$C$1 & "!L59") -> CLaw_rduc | AV10: =INDIRECT(csv_selection!$B$1 & csv_selection!$C$1 & "!L61") -> CLaw_perm | AW10: =INDIRECT(csv_selection!$B$1 & csv_selection!$C$1 & "!L63") -> CLaw_perm | AX10: =INDIRECT(csv_selection!$B$1 & csv_selection!$C$1 & "!L64") -> CLaw_perm | AY10: =INDIRECT(csv_selection!$B$1 & csv_selection!$C$1 & "!L65") -> CLaw_perm | AZ10: =INDIRECT(csv_selection!$B$1 & csv_selection!$C$1 & "!L66") -> CLaw_perm | BA10: =INDIRECT(csv_selection!$B$1 & csv_selection!$C$1 & "!L67") -> CLaw_perm | BB10: =INDIRECT(csv_selection!$B$1 & csv_selection!$C$1 & "!L69") -> 0.6394 | BC10: =INDIRECT(csv_selection!$B$1 & csv_selection!$C$1 & "!L70") -> 0.0335 | BD10: =INDIRECT(csv_selection!$B$1 & csv_selection!$C$1 & "!L71") -> 0.3271 | BE10: =INDIRECT(csv_selection!$B$1 & csv_selection!$C$1 & "!L72") -> 0.3991 | BF10: =INDIRECT(csv_selection!$B$1 & csv_selection!$C$1 & "!L73") -> 0.1925 | BG10: =INDIRECT(csv_selection!$B$1 & csv_selection!$C$1 & "!L74") -> 0.4084 | BH10: =INDIRECT(csv_selection!$B$1 & csv_selection!$C$1 & "!L75") -> 1 | BI10: =INDIRECT(csv_selection!$B$1 & csv_selection!$C$1 & "!L76") -> 0 | BJ10: =INDIRECT(csv_selection!$B$1 & csv_selection!$C$1 & "!L77") -> 0 | BK10: =INDIRECT(csv_selection!$B$1 & csv_selection!$C$1 & "!L78") -> 0.694 | BL10: =INDIRECT(csv_selection!$B$1 & csv_selection!$C$1 & "!L79") -> 0.1284 | BM10: =INDIRECT(csv_selection!$B$1 & csv_selection!$C$1 & "!L80") -> 0.1776 | BN10: =INDIRECT(csv_selection!$B$1 & csv_selection!$C$1 & "!L81") -> 1 | BO10: =INDIRECT(csv_selection!$B$1 & csv_selection!$C$1 & "!L82") -> 0 | BP10: =INDIRECT(csv_selection!$B$1 & csv_selection!$C$1 & "!L83") -> 0 | BQ10: =INDIRECT(csv_selection!$B$1 & csv_selection!$C$1 & "!L84") -> 0.8157 | BR10: =INDIRECT(csv_selection!$B$1 & csv_selection!$C$1 & "!L85") -> 0.0578 | BS10: =INDIRECT(csv_selection!$B$1 & csv_selection!$C$1 & "!L86") -> 0.1265
A11: =INDIRECT(csv_selection!$B$1 & csv_selection!$C$1 & "!M2") -> 2035 | B11: =INDIRECT(csv_selection!$B$1 & csv_selection!$C$1 & "!M5") -> 0.21 | C11: =INDIRECT(csv_selection!$B$1 & csv_selection!$C$1 & "!M6") -> 0.3139 | D11: =INDIRECT(csv_selection!$B$1 & csv_selection!$C$1 & "!M7") -> 0.0353 | E11: =INDIRECT(csv_selection!$B$1 & csv_selection!$C$1 & "!M8") -> 0.01 | F11: =INDIRECT(csv_selection!$B$1 & csv_selection!$C$1 & "!M9") -> 0 | G11: =INDIRECT(csv_selection!$B$1 & csv_selection!$C$1 & "!M11") -> 0.2019 | H11: =INDIRECT(csv_selection!$B$1 & csv_selection!$C$1 & "!M12") -> 0.3317 | I11: =INDIRECT(csv_selection!$B$1 & csv_selection!$C$1 & "!M13") -> 0.2042 | J11: =INDIRECT(csv_selection!$B$1 & csv_selection!$C$1 & "!M14") -> 0 | K11: =INDIRECT(csv_selection!$B$1 & csv_selection!$C$1 & "!M15") -> 0.3061 | L11: =INDIRECT(csv_selection!$B$1 & csv_selection!$C$1 & "!M16") -> 0.3061 | M11: =INDIRECT(csv_selection!$B$1 & csv_selection!$C$1 & "!M17") -> 0.2379 | N11: =INDIRECT(csv_selection!$B$1 & csv_selection!$C$1 & "!M18") -> 0 | O11: =INDIRECT(csv_selection!$B$1 & csv_selection!$C$1 & "!M20") -> 0.2006 | P11: =INDIRECT(csv_selection!$B$1 & csv_selection!$C$1 & "!M21") -> 0.1828 | Q11: =INDIRECT(csv_selection!$B$1 & csv_selection!$C$1 & "!M23") -> 0.2919 | R11: =INDIRECT(csv_selection!$B$1 & csv_selection!$C$1 & "!M24") -> 0.7732 | S11: =INDIRECT(csv_selection!$B$1 & csv_selection!$C$1 & "!M25") -> 0.9738 | T11: =INDIRECT(csv_selection!$B$1 & csv_selection!$C$1 & "!M26") -> 0.9849 | U11: =INDIRECT(csv_selection!$B$1 & csv_selection!$C$1 & "!M27") -> 0.6211 | V11: =INDIRECT(csv_selection!$B$1 & csv_selection!$C$1 & "!M28") -> 0.0383 | W11: =INDIRECT(csv_selection!$B$1 & csv_selection!$C$1 & "!M31") -> 1 | X11: =INDIRECT(csv_selection!$B$1 & csv_selection!$C$1 & "!M32") -> 1 | Y11: =INDIRECT(csv_selection!$B$1 & csv_selection!$C$1 & "!M33") -> 1 | Z11: =INDIRECT(csv_selection!$B$1 & csv_selection!$C$1 & "!M34") -> 1 | AA11: =INDIRECT(csv_selection!$B$1 & csv_selection!$C$1 & "!M35") -> 1 | AB11: =INDIRECT(csv_selection!$B$1 & csv_selection!$C$1 & "!M36") -> 1 | AC11: =INDIRECT(csv_selection!$B$1 & csv_selection!$C$1 & "!M37") -> 1 | AD11: =INDIRECT(csv_selection!$B$1 & csv_selection!$C$1 & "!M38") -> 1 | AE11: =INDIRECT(csv_selection!$B$1 & csv_selection!$C$1 & "!M40") -> 0 | AF11: =INDIRECT(csv_selection!$B$1 & csv_selection!$C$1 & "!M41") -> 0 | AG11: =INDIRECT(csv_selection!$B$1 & csv_selection!$C$1 & "!M42") -> 0 | AH11: =INDIRECT(csv_selection!$B$1 & csv_selection!$C$1 & "!M43") -> 0 | AI11: =INDIRECT(csv_selection!$B$1 & csv_selection!$C$1 & "!M44") -> 0 | AJ11: =INDIRECT(csv_selection!$B$1 & csv_selection!$C$1 & "!M45") -> 0 | AK11: =INDIRECT(csv_selection!$B$1 & csv_selection!$C$1 & "!M46") -> 0 | AL11: =INDIRECT(csv_selection!$B$1 & csv_selection!$C$1 & "!M47") -> 0 | AM11: =INDIRECT(csv_selection!$B$1 & csv_selection!$C$1 & "!M50") -> CLaw_perm | AN11: =INDIRECT(csv_selection!$B$1 & csv_selection!$C$1 & "!M51") -> CLaw_perm | AO11: =INDIRECT(csv_selection!$B$1 & csv_selection!$C$1 & "!M52") -> CLaw_perm | AP11: =INDIRECT(csv_selection!$B$1 & csv_selection!$C$1 & "!M53") -> CLaw_perm | AQ11: =INDIRECT(csv_selection!$B$1 & csv_selection!$C$1 & "!M54") -> CLCC_perm | AR11: =INDIRECT(csv_selection!$B$1 & csv_selection!$C$1 & "!M55") -> CLPT_perm | AS11: =INDIRECT(csv_selection!$B$1 & csv_selection!$C$1 & "!M56") -> CLaw_perm | AT11: =INDIRECT(csv_selection!$B$1 & csv_selection!$C$1 & "!M58") -> Claw_perm | AU11: =INDIRECT(csv_selection!$B$1 & csv_selection!$C$1 & "!M59") -> CLaw_rduc | AV11: =INDIRECT(csv_selection!$B$1 & csv_selection!$C$1 & "!M61") -> CLaw_perm | AW11: =INDIRECT(csv_selection!$B$1 & csv_selection!$C$1 & "!M63") -> CLaw_perm | AX11: =INDIRECT(csv_selection!$B$1 & csv_selection!$C$1 & "!M64") -> CLaw_perm | AY11: =INDIRECT(csv_selection!$B$1 & csv_selection!$C$1 & "!M65") -> CLaw_perm | AZ11: =INDIRECT(csv_selection!$B$1 & csv_selection!$C$1 & "!M66") -> CLaw_perm | BA11: =INDIRECT(csv_selection!$B$1 & csv_selection!$C$1 & "!M67") -> CLaw_perm | BB11: =INDIRECT(csv_selection!$B$1 & csv_selection!$C$1 & "!M69") -> 0.64 | BC11: =INDIRECT(csv_selection!$B$1 & csv_selection!$C$1 & "!M70") -> 0.0335 | BD11: =INDIRECT(csv_selection!$B$1 & csv_selection!$C$1 & "!M71") -> 0.3265 | BE11: =INDIRECT(csv_selection!$B$1 & csv_selection!$C$1 & "!M72") -> 0.3996 | BF11: =INDIRECT(csv_selection!$B$1 & csv_selection!$C$1 & "!M73") -> 0.1925 | BG11: =INDIRECT(csv_selection!$B$1 & csv_selection!$C$1 & "!M74") -> 0.4079 | BH11: =INDIRECT(csv_selection!$B$1 & csv_selection!$C$1 & "!M75") -> 1 | BI11: =INDIRECT(csv_selection!$B$1 & csv_selection!$C$1 & "!M76") -> 0 | BJ11: =INDIRECT(csv_selection!$B$1 & csv_selection!$C$1 & "!M77") -> 0 | BK11: =INDIRECT(csv_selection!$B$1 & csv_selection!$C$1 & "!M78") -> 0.6942 | BL11: =INDIRECT(csv_selection!$B$1 & csv_selection!$C$1 & "!M79") -> 0.1284 | BM11: =INDIRECT(csv_selection!$B$1 & csv_selection!$C$1 & "!M80") -> 0.1774 | BN11: =INDIRECT(csv_selection!$B$1 & csv_selection!$C$1 & "!M81") -> 1 | BO11: =INDIRECT(csv_selection!$B$1 & csv_selection!$C$1 & "!M82") -> 0 | BP11: =INDIRECT(csv_selection!$B$1 & csv_selection!$C$1 & "!M83") -> 0 | BQ11: =INDIRECT(csv_selection!$B$1 & csv_selection!$C$1 & "!M84") -> 0.8158 | BR11: =INDIRECT(csv_selection!$B$1 & csv_selection!$C$1 & "!M85") -> 0.0578 | BS11: =INDIRECT(csv_selection!$B$1 & csv_selection!$C$1 & "!M86") -> 0.1264
A12: =INDIRECT(csv_selection!$B$1 & csv_selection!$C$1 & "!N2") -> 2036 | B12: =INDIRECT(csv_selection!$B$1 & csv_selection!$C$1 & "!N5") -> 0.21 | C12: =INDIRECT(csv_selection!$B$1 & csv_selection!$C$1 & "!N6") -> 0.3164 | D12: =INDIRECT(csv_selection!$B$1 & csv_selection!$C$1 & "!N7") -> 0.0353 | E12: =INDIRECT(csv_selection!$B$1 & csv_selection!$C$1 & "!N8") -> 0.01 | F12: =INDIRECT(csv_selection!$B$1 & csv_selection!$C$1 & "!N9") -> 0 | G12: =INDIRECT(csv_selection!$B$1 & csv_selection!$C$1 & "!N11") -> 0.2063 | H12: =INDIRECT(csv_selection!$B$1 & csv_selection!$C$1 & "!N12") -> 0.3339 | I12: =INDIRECT(csv_selection!$B$1 & csv_selection!$C$1 & "!N13") -> 0.2052 | J12: =INDIRECT(csv_selection!$B$1 & csv_selection!$C$1 & "!N14") -> 0 | K12: =INDIRECT(csv_selection!$B$1 & csv_selection!$C$1 & "!N15") -> 0.3089 | L12: =INDIRECT(csv_selection!$B$1 & csv_selection!$C$1 & "!N16") -> 0.3089 | M12: =INDIRECT(csv_selection!$B$1 & csv_selection!$C$1 & "!N17") -> 0.238 | N12: =INDIRECT(csv_selection!$B$1 & csv_selection!$C$1 & "!N18") -> 0 | O12: =INDIRECT(csv_selection!$B$1 & csv_selection!$C$1 & "!N20") -> 0.2015 | P12: =INDIRECT(csv_selection!$B$1 & csv_selection!$C$1 & "!N21") -> 0.1836 | Q12: =INDIRECT(csv_selection!$B$1 & csv_selection!$C$1 & "!N23") -> 0.2896 | R12: =INDIRECT(csv_selection!$B$1 & csv_selection!$C$1 & "!N24") -> 0.773 | S12: =INDIRECT(csv_selection!$B$1 & csv_selection!$C$1 & "!N25") -> 0.9743 | T12: =INDIRECT(csv_selection!$B$1 & csv_selection!$C$1 & "!N26") -> 0.9852 | U12: =INDIRECT(csv_selection!$B$1 & csv_selection!$C$1 & "!N27") -> 0.6253 | V12: =INDIRECT(csv_selection!$B$1 & csv_selection!$C$1 & "!N28") -> 0.0365 | W12: =INDIRECT(csv_selection!$B$1 & csv_selection!$C$1 & "!N31") -> 1 | X12: =INDIRECT(csv_selection!$B$1 & csv_selection!$C$1 & "!N32") -> 1 | Y12: =INDIRECT(csv_selection!$B$1 & csv_selection!$C$1 & "!N33") -> 1 | Z12: =INDIRECT(csv_selection!$B$1 & csv_selection!$C$1 & "!N34") -> 1 | AA12: =INDIRECT(csv_selection!$B$1 & csv_selection!$C$1 & "!N35") -> 1 | AB12: =INDIRECT(csv_selection!$B$1 & csv_selection!$C$1 & "!N36") -> 1 | AC12: =INDIRECT(csv_selection!$B$1 & csv_selection!$C$1 & "!N37") -> 1 | AD12: =INDIRECT(csv_selection!$B$1 & csv_selection!$C$1 & "!N38") -> 1 | AE12: =INDIRECT(csv_selection!$B$1 & csv_selection!$C$1 & "!N40") -> 0 | AF12: =INDIRECT(csv_selection!$B$1 & csv_selection!$C$1 & "!N41") -> 0 | AG12: =INDIRECT(csv_selection!$B$1 & csv_selection!$C$1 & "!N42") -> 0 | AH12: =INDIRECT(csv_selection!$B$1 & csv_selection!$C$1 & "!N43") -> 0 | AI12: =INDIRECT(csv_selection!$B$1 & csv_selection!$C$1 & "!N44") -> 0 | AJ12: =INDIRECT(csv_selection!$B$1 & csv_selection!$C$1 & "!N45") -> 0 | AK12: =INDIRECT(csv_selection!$B$1 & csv_selection!$C$1 & "!N46") -> 0 | AL12: =INDIRECT(csv_selection!$B$1 & csv_selection!$C$1 & "!N47") -> 0 | AM12: =INDIRECT(csv_selection!$B$1 & csv_selection!$C$1 & "!N50") -> CLaw_perm | AN12: =INDIRECT(csv_selection!$B$1 & csv_selection!$C$1 & "!N51") -> CLaw_perm | AO12: =INDIRECT(csv_selection!$B$1 & csv_selection!$C$1 & "!N52") -> CLaw_perm | AP12: =INDIRECT(csv_selection!$B$1 & csv_selection!$C$1 & "!N53") -> CLaw_perm | AQ12: =INDIRECT(csv_selection!$B$1 & csv_selection!$C$1 & "!N54") -> CLCC_perm | AR12: =INDIRECT(csv_selection!$B$1 & csv_selection!$C$1 & "!N55") -> CLPT_perm | AS12: =INDIRECT(csv_selection!$B$1 & csv_selection!$C$1 & "!N56") -> CLaw_perm | AT12: =INDIRECT(csv_selection!$B$1 & csv_selection!$C$1 & "!N58") -> Claw_perm | AU12: =INDIRECT(csv_selection!$B$1 & csv_selection!$C$1 & "!N59") -> CLaw_rduc | AV12: =INDIRECT(csv_selection!$B$1 & csv_selection!$C$1 & "!N61") -> CLaw_perm | AW12: =INDIRECT(csv_selection!$B$1 & csv_selection!$C$1 & "!N63") -> CLaw_perm | AX12: =INDIRECT(csv_selection!$B$1 & csv_selection!$C$1 & "!N64") -> CLaw_perm | AY12: =INDIRECT(csv_selection!$B$1 & csv_selection!$C$1 & "!N65") -> CLaw_perm | AZ12: =INDIRECT(csv_selection!$B$1 & csv_selection!$C$1 & "!N66") -> CLaw_perm | BA12: =INDIRECT(csv_selection!$B$1 & csv_selection!$C$1 & "!N67") -> CLaw_perm | BB12: =INDIRECT(csv_selection!$B$1 & csv_selection!$C$1 & "!N69") -> 0.6406 | BC12: =INDIRECT(csv_selection!$B$1 & csv_selection!$C$1 & "!N70") -> 0.0335 | BD12: =INDIRECT(csv_selection!$B$1 & csv_selection!$C$1 & "!N71") -> 0.3259 | BE12: =INDIRECT(csv_selection!$B$1 & csv_selection!$C$1 & "!N72") -> 0.4 | BF12: =INDIRECT(csv_selection!$B$1 & csv_selection!$C$1 & "!N73") -> 0.1925 | BG12: =INDIRECT(csv_selection!$B$1 & csv_selection!$C$1 & "!N74") -> 0.4075 | BH12: =INDIRECT(csv_selection!$B$1 & csv_selection!$C$1 & "!N75") -> 1 | BI12: =INDIRECT(csv_selection!$B$1 & csv_selection!$C$1 & "!N76") -> 0 | BJ12: =INDIRECT(csv_selection!$B$1 & csv_selection!$C$1 & "!N77") -> 0 | BK12: =INDIRECT(csv_selection!$B$1 & csv_selection!$C$1 & "!N78") -> 0.6944 | BL12: =INDIRECT(csv_selection!$B$1 & csv_selection!$C$1 & "!N79") -> 0.1284 | BM12: =INDIRECT(csv_selection!$B$1 & csv_selection!$C$1 & "!N80") -> 0.1772 | BN12: =INDIRECT(csv_selection!$B$1 & csv_selection!$C$1 & "!N81") -> 1 | BO12: =INDIRECT(csv_selection!$B$1 & csv_selection!$C$1 & "!N82") -> 0 | BP12: =INDIRECT(csv_selection!$B$1 & csv_selection!$C$1 & "!N83") -> 0 | BQ12: =INDIRECT(csv_selection!$B$1 & csv_selection!$C$1 & "!N84") -> 0.8159 | BR12: =INDIRECT(csv_selection!$B$1 & csv_selection!$C$1 & "!N85") -> 0.0578 | BS12: =INDIRECT(csv_selection!$B$1 & csv_selection!$C$1 & "!N86") -> 0.1263

Sheet policy_parameters_uniformity
A1: =INDIRECT(csv_selection!$B$2 & csv_selection!$C$2 & "!C2") -> year | B1: =INDIRECT(csv_selection!$B$2 & csv_selection!$C$2 & "!C5") -> c_corp_tax_rate | C1: =INDIRECT(csv_selection!$B$2 & csv_selection!$C$2 & "!C6") -> pass_thru_tax_rate | D1: =INDIRECT(csv_selection!$B$2 & csv_selection!$C$2 & "!C7") -> seca_tax_rate | E1: =INDIRECT(csv_selection!$B$2 & csv_selection!$C$2 & "!C8") -> repurchases_tax_rate | F1: =INDIRECT(csv_selection!$B$2 & csv_selection!$C$2 & "!C9") -> ooh_tax_rate | G1: =INDIRECT(csv_selection!$B$2 & csv_selection!$C$2 & "!C11") -> dividend_inc_tax_rate | H1: =INDIRECT(csv_selection!$B$2 & csv_selection!$C$2 & "!C12") -> cap_gains_short_term_tax_rate | I1: =INDIRECT(csv_selection!$B$2 & csv_selection!$C$2 & "!C13") -> cap_gains_long_term_tax_rate | J1: =INDIRECT(csv_selection!$B$2 & csv_selection!$C$2 & "!C14") -> cap_gains_at_death_tax_rate | K1: =INDIRECT(csv_selection!$B$2 & csv_selection!$C$2 & "!C15") -> interest_inc_from_biz_tax_rate | L1: =INDIRECT(csv_selection!$B$2 & csv_selection!$C$2 & "!C16") -> interest_inc_from_ooh_tax_rate | M1: =INDIRECT(csv_selection!$B$2 & csv_selection!$C$2 & "!C17") -> ret_plan_deferred_tax_rate | N1: =INDIRECT(csv_selection!$B$2 & csv_selection!$C$2 & "!C18") -> ret_plan_nontaxable_tax_rate | O1: =INDIRECT(csv_selection!$B$2 & csv_selection!$C$2 & "!C20") -> mortg_interest_deduction_tax_rate | P1: =INDIRECT(csv_selection!$B$2 & csv_selection!$C$2 & "!C21") -> prop_tax_deduction_tax_rate | Q1: =INDIRECT(csv_selection!$B$2 & csv_selection!$C$2 & "!C23") -> pass_thru_inc_share_below_thresholds | R1: =INDIRECT(csv_selection!$B$2 & csv_selection!$C$2 & "!C24") -> pass_thru_eligibility_below_thresholds | S1: =INDIRECT(csv_selection!$B$2 & csv_selection!$C$2 & "!C25") -> c_corp_interest_deductible_share | T1: =INDIRECT(csv_selection!$B$2 & csv_selection!$C$2 & "!C26") -> pass_thru_interest_deductible_share | U1: =INDIRECT(csv_selection!$B$2 & csv_selection!$C$2 & "!C27") -> mortg_interest_deductible_share | V1: =INDIRECT(csv_selection!$B$2 & csv_selection!$C$2 & "!C28") -> prop_tax_deductible_share | W1: =INDIRECT(csv_selection!$B$2 & csv_selection!$C$2 & "!C31") -> c_corp_net_inc_timing_adjustment | X1: =INDIRECT(csv_selection!$B$2 & csv_selection!$C$2 & "!C32") -> pass_thru_net_inc_timing_adjustment | Y1: =INDIRECT(csv_selection!$B$2 & csv_selection!$C$2 & "!C33") -> seca_net_inc_timing_adjustment | Z1: =INDIRECT(csv_selection!$B$2 & csv_selection!$C$2 & "!C34") -> c_corp_deductions_timing_adjustment | AA1: =INDIRECT(csv_selection!$B$2 & csv_selection!$C$2 & "!C35") -> pass_thru_deductions_timing_adjustment | AB1: =INDIRECT(csv_selection!$B$2 & csv_selection!$C$2 & "!C36") -> seca_deductions_timing_adjustment | AC1: =INDIRECT(csv_selection!$B$2 & csv_selection!$C$2 & "!C37") -> c_corp_credits_timing_adjustment | AD1: =INDIRECT(csv_selection!$B$2 & csv_selection!$C$2 & "!C38") -> pass_thru_credits_timing_adjustment | AE1: =INDIRECT(csv_selection!$B$2 & csv_selection!$C$2 & "!C40") -> change_cap_gains_short_term_share | AF1: =INDIRECT(csv_selection!$B$2 & csv_selection!$C$2 & "!C41") -> change_cap_gains_at_death_share | AG1: =INDIRECT(csv_selection!$B$2 & csv_selection!$C$2 & "!C42") -> change_cap_gains_short_term_holding_period | AH1: =INDIRECT(csv_selection!$B$2 & csv_selection!$C$2 & "!C43") -> change_cap_gains_long_term_holding_period | AI1: =INDIRECT(csv_selection!$B$2 & csv_selection!$C$2 & "!C44") -> change_cap_gains_at_death_holding_period | AJ1: =INDIRECT(csv_selection!$B$2 & csv_selection!$C$2 & "!C45") -> change_ret_plan_deferred_holding_period | AK1: =INDIRECT(csv_selection!$B$2 & csv_selection!$C$2 & "!C46") -> change_ret_plan_nontaxable_holding_period | AL1: =INDIRECT(csv_selection!$B$2 & csv_selection!$C$2 & "!C47") -> change_inventories_holding_period | AM1: =INDIRECT(csv_selection!$B$2 & csv_selection!$C$2 & "!C50") -> recovery_periods | AN1: =INDIRECT(csv_selection!$B$2 & csv_selection!$C$2 & "!C51") -> acceleration_rates | AO1: =INDIRECT(csv_selection!$B$2 & csv_selection!$C$2 & "!C52") -> straight_line_flags | AP1: =INDIRECT(csv_selection!$B$2 & csv_selection!$C$2 & "!C53") -> inflation_adjustments | AQ1: =INDIRECT(csv_selection!$B$2 & csv_selection!$C$2 & "!C54") -> c_corp_sec_179_expens_shares | AR1: =INDIRECT(csv_selection!$B$2 & csv_selection!$C$2 & "!C55") -> pass_thru_sec_179_expens_shares | AS1: =INDIRECT(csv_selection!$B$2 & csv_selection!$C$2 & "!C56") -> other_expens_shares | AT1: =INDIRECT(csv_selection!$B$2 & csv_selection!$C$2 & "!C58") -> itc_rates | AU1: =INDIRECT(csv_selection!$B$2 & csv_selection!$C$2 & "!C59") -> itc_nondeprcbl_bases | AV1: =INDIRECT(csv_selection!$B$2 & csv_selection!$C$2 & "!C61") -> ptc_rates | AW1: =INDIRECT(csv_selection!$B$2 & csv_selection!$C$2 & "!C63") -> sec_199A_adjustments | AX1: =INDIRECT(csv_selection!$B$2 & csv_selection!$C$2 & "!C64") -> c_corp_industry_adjustments | AY1: =INDIRECT(csv_selection!$B$2 & csv_selection!$C$2 & "!C65") -> pass_thru_industry_adjustments | AZ1: =INDIRECT(csv_selection!$B$2 & csv_selection!$C$2 & "!C66") -> c_corp_asset_adjustments | BA1: =INDIRECT(csv_selection!$B$2 & csv_selection!$C$2 & "!C67") -> pass_thru_asset_adjustments | BB1: =INDIRECT(csv_selection!$B$2 & csv_selection!$C$2 & "!C69") -> c_corp_equity_account_category_share_taxable | BC1: =INDIRECT(csv_selection!$B$2 & csv_selection!$C$2 & "!C70") -> c_corp_equity_account_category_share_deferred | BD1: =INDIRECT(csv_selection!$B$2 & csv_selection!$C$2 & "!C71") -> c_corp_equity_account_category_share_nontaxable | BE1: =INDIRECT(csv_selection!$B$2 & csv_selection!$C$2 & "!C72") -> c_corp_debt_account_category_share_taxable | BF1: =INDIRECT(csv_selection!$B$2 & csv_selection!$C$2 & "!C73") -> c_corp_debt_account_category_share_deferred | BG1: =INDIRECT(csv_selection!$B$2 & csv_selection!$C$2 & "!C74") -> c_corp_debt_account_category_share_nontaxable | BH1: =INDIRECT(csv_selection!$B$2 & csv_selection!$C$2 & "!C75") -> pass_thru_equity_account_category_share_taxable | BI1: =INDIRECT(csv_selection!$B$2 & csv_selection!$C$2 & "!C76") -> pass_thru_equity_account_category_share_deferred | BJ1: =INDIRECT(csv_selection!$B$2 & csv_selection!$C$2 & "!C77") -> pass_thru_equity_account_category_share_nontaxable | BK1: =INDIRECT(csv_selection!$B$2 & csv_selection!$C$2 & "!C78") -> pass_thru_debt_account_category_share_taxable | BL1: =INDIRECT(csv_selection!$B$2 & csv_selection!$C$2 & "!C79") -> pass_thru_debt_account_category_share_deferred | BM1: =INDIRECT(csv_selection!$B$2 & csv_selection!$C$2 & "!C80") -> pass_thru_debt_account_category_share_nontaxable | BN1: =INDIRECT(csv_selection!$B$2 & csv_selection!$C$2 & "!C81") -> ooh_equity_account_category_share_taxable | BO1: =INDIRECT(csv_selection!$B$2 & csv_selection!$C$2 & "!C82") -> ooh_equity_account_category_share_deferred | BP1: =INDIRECT(csv_selection!$B$2 & csv_selection!$C$2 & "!C83") -> ooh_equity_account_category_share_nontaxable | BQ1: =INDIRECT(csv_selection!$B$2 & csv_selection!$C$2 & "!C84") -> ooh_debt_account_category_share_taxable | BR1: =INDIRECT(csv_selection!$B$2 & csv_selection!$C$2 & "!C85") -> ooh_debt_account_category_share_deferred | BS1: =INDIRECT(csv_selection!$B$2 & csv_selection!$C$2 & "!C86") -> ooh_debt_account_category_share_nontaxable
A2: =INDIRECT(csv_selection!$B$2 & csv_selection!$C$2 & "!D2") -> 2026 | B2: =INDIRECT(csv_selection!$B$2 & csv_selection!$C$2 & "!D5") -> 0.21 | C2: =INDIRECT(csv_selection!$B$2 & csv_selection!$C$2 & "!D6") -> 0.2776 | D2: =INDIRECT(csv_selection!$B$2 & csv_selection!$C$2 & "!D7") -> 0.0352 | E2: =INDIRECT(csv_selection!$B$2 & csv_selection!$C$2 & "!D8") -> 0.01 | F2: =INDIRECT(csv_selection!$B$2 & csv_selection!$C$2 & "!D9") -> 0 | G2: =INDIRECT(csv_selection!$B$2 & csv_selection!$C$2 & "!D11") -> 0.2092 | H2: =INDIRECT(csv_selection!$B$2 & csv_selection!$C$2 & "!D12") -> 0.2776 | I2: =INDIRECT(csv_selection!$B$2 & csv_selection!$C$2 & "!D13") -> 0.2092 | J2: =INDIRECT(csv_selection!$B$2 & csv_selection!$C$2 & "!D14") -> 0 | K2: =INDIRECT(csv_selection!$B$2 & csv_selection!$C$2 & "!D15") -> 0.2776 | L2: =INDIRECT(csv_selection!$B$2 & csv_selection!$C$2 & "!D16") -> 0.2776 | M2: =INDIRECT(csv_selection!$B$2 & csv_selection!$C$2 & "!D17") -> 0.2776 | N2: =INDIRECT(csv_selection!$B$2 & csv_selection!$C$2 & "!D18") -> 0 | O2: =INDIRECT(csv_selection!$B$2 & csv_selection!$C$2 & "!D20") -> 0.2776 | P2: =INDIRECT(csv_selection!$B$2 & csv_selection!$C$2 & "!D21") -> 0.2776 | Q2: =INDIRECT(csv_selection!$B$2 & csv_selection!$C$2 & "!D23") -> 0.3225 | R2: =INDIRECT(csv_selection!$B$2 & csv_selection!$C$2 & "!D24") -> 0.7734 | S2: =INDIRECT(csv_selection!$B$2 & csv_selection!$C$2 & "!D25") -> 0.9888 | T2: =INDIRECT(csv_selection!$B$2 & csv_selection!$C$2 & "!D26") -> 0.9888 | U2: =INDIRECT(csv_selection!$B$2 & csv_selection!$C$2 & "!D27") -> 0.5552 | V2: =INDIRECT(csv_selection!$B$2 & csv_selection!$C$2 & "!D28") -> 0.3457 | W2: =INDIRECT(csv_selection!$B$2 & csv_selection!$C$2 & "!D31") -> 1 | X2: =INDIRECT(csv_selection!$B$2 & csv_selection!$C$2 & "!D32") -> 1 | Y2: =INDIRECT(csv_selection!$B$2 & csv_selection!$C$2 & "!D33") -> 1 | Z2: =INDIRECT(csv_selection!$B$2 & csv_selection!$C$2 & "!D34") -> 1 | AA2: =INDIRECT(csv_selection!$B$2 & csv_selection!$C$2 & "!D35") -> 1 | AB2: =INDIRECT(csv_selection!$B$2 & csv_selection!$C$2 & "!D36") -> 1 | AC2: =INDIRECT(csv_selection!$B$2 & csv_selection!$C$2 & "!D37") -> 1 | AD2: =INDIRECT(csv_selection!$B$2 & csv_selection!$C$2 & "!D38") -> 1 | AE2: =INDIRECT(csv_selection!$B$2 & csv_selection!$C$2 & "!D40") -> 0 | AF2: =INDIRECT(csv_selection!$B$2 & csv_selection!$C$2 & "!D41") -> 0 | AG2: =INDIRECT(csv_selection!$B$2 & csv_selection!$C$2 & "!D42") -> 0 | AH2: =INDIRECT(csv_selection!$B$2 & csv_selection!$C$2 & "!D43") -> 0 | AI2: =INDIRECT(csv_selection!$B$2 & csv_selection!$C$2 & "!D44") -> 0 | AJ2: =INDIRECT(csv_selection!$B$2 & csv_selection!$C$2 & "!D45") -> 0 | AK2: =INDIRECT(csv_selection!$B$2 & csv_selection!$C$2 & "!D46") -> 0 | AL2: =INDIRECT(csv_selection!$B$2 & csv_selection!$C$2 & "!D47") -> 0 | AM2: =INDIRECT(csv_selection!$B$2 & csv_selection!$C$2 & "!D50") -> CLaw_perm | AN2: =INDIRECT(csv_selection!$B$2 & csv_selection!$C$2 & "!D51") -> CLaw_perm | AO2: =INDIRECT(csv_selection!$B$2 & csv_selection!$C$2 & "!D52") -> CLaw_perm | AP2: =INDIRECT(csv_selection!$B$2 & csv_selection!$C$2 & "!D53") -> CLaw_perm | AQ2: =INDIRECT(csv_selection!$B$2 & csv_selection!$C$2 & "!D54") -> CLaw_perm | AR2: =INDIRECT(csv_selection!$B$2 & csv_selection!$C$2 & "!D55") -> CLaw_perm | AS2: =INDIRECT(csv_selection!$B$2 & csv_selection!$C$2 & "!D56") -> CLaw_temp | AT2: =INDIRECT(csv_selection!$B$2 & csv_selection!$C$2 & "!D58") -> CLaw_2026 | AU2: =INDIRECT(csv_selection!$B$2 & csv_selection!$C$2 & "!D59") -> CLaw_rduc | AV2: =INDIRECT(csv_selection!$B$2 & csv_selection!$C$2 & "!D61") -> CLaw_2026 | AW2: =INDIRECT(csv_selection!$B$2 & csv_selection!$C$2 & "!D63") -> CLaw_perm | AX2: =INDIRECT(csv_selection!$B$2 & csv_selection!$C$2 & "!D64") -> CLaw_perm | AY2: =INDIRECT(csv_selection!$B$2 & csv_selection!$C$2 & "!D65") -> CLaw_perm | AZ2: =INDIRECT(csv_selection!$B$2 & csv_selection!$C$2 & "!D66") -> CLaw_perm | BA2: =INDIRECT(csv_selection!$B$2 & csv_selection!$C$2 & "!D67") -> CLaw_perm | BB2: =INDIRECT(csv_selection!$B$2 & csv_selection!$C$2 & "!D69") -> 0.5934 | BC2: =INDIRECT(csv_selection!$B$2 & csv_selection!$C$2 & "!D70") -> 0.0578 | BD2: =INDIRECT(csv_selection!$B$2 & csv_selection!$C$2 & "!D71") -> 0.3488 | BE2: =INDIRECT(csv_selection!$B$2 & csv_selection!$C$2 & "!D72") -> 0.5934 | BF2: =INDIRECT(csv_selection!$B$2 & csv_selection!$C$2 & "!D73") -> 0.0578 | BG2: =INDIRECT(csv_selection!$B$2 & csv_selection!$C$2 & "!D74") -> 0.3488 | BH2: =INDIRECT(csv_selection!$B$2 & csv_selection!$C$2 & "!D75") -> 1 | BI2: =INDIRECT(csv_selection!$B$2 & csv_selection!$C$2 & "!D76") -> 0 | BJ2: =INDIRECT(csv_selection!$B$2 & csv_selection!$C$2 & "!D77") -> 0 | BK2: =INDIRECT(csv_selection!$B$2 & csv_selection!$C$2 & "!D78") -> 0.5934 | BL2: =INDIRECT(csv_selection!$B$2 & csv_selection!$C$2 & "!D79") -> 0.0578 | BM2: =INDIRECT(csv_selection!$B$2 & csv_selection!$C$2 & "!D80") -> 0.3488 | BN2: =INDIRECT(csv_selection!$B$2 & csv_selection!$C$2 & "!D81") -> 1 | BO2: =INDIRECT(csv_selection!$B$2 & csv_selection!$C$2 & "!D82") -> 0 | BP2: =INDIRECT(csv_selection!$B$2 & csv_selection!$C$2 & "!D83") -> 0 | BQ2: =INDIRECT(csv_selection!$B$2 & csv_selection!$C$2 & "!D84") -> 0.5934 | BR2: =INDIRECT(csv_selection!$B$2 & csv_selection!$C$2 & "!D85") -> 0.0578 | BS2: =INDIRECT(csv_selection!$B$2 & csv_selection!$C$2 & "!D86") -> 0.3488
A3: =INDIRECT(csv_selection!$B$2 & csv_selection!$C$2 & "!E2") -> 2027 | B3: =INDIRECT(csv_selection!$B$2 & csv_selection!$C$2 & "!E5") -> 0.21 | C3: =INDIRECT(csv_selection!$B$2 & csv_selection!$C$2 & "!E6") -> 0.2769 | D3: =INDIRECT(csv_selection!$B$2 & csv_selection!$C$2 & "!E7") -> 0.0352 | E3: =INDIRECT(csv_selection!$B$2 & csv_selection!$C$2 & "!E8") -> 0.01 | F3: =INDIRECT(csv_selection!$B$2 & csv_selection!$C$2 & "!E9") -> 0 | G3: =INDIRECT(csv_selection!$B$2 & csv_selection!$C$2 & "!E11") -> 0.2076 | H3: =INDIRECT(csv_selection!$B$2 & csv_selection!$C$2 & "!E12") -> 0.2769 | I3: =INDIRECT(csv_selection!$B$2 & csv_selection!$C$2 & "!E13") -> 0.2076 | J3: =INDIRECT(csv_selection!$B$2 & csv_selection!$C$2 & "!E14") -> 0 | K3: =INDIRECT(csv_selection!$B$2 & csv_selection!$C$2 & "!E15") -> 0.2769 | L3: =INDIRECT(csv_selection!$B$2 & csv_selection!$C$2 & "!E16") -> 0.2769 | M3: =INDIRECT(csv_selection!$B$2 & csv_selection!$C$2 & "!E17") -> 0.2769 | N3: =INDIRECT(csv_selection!$B$2 & csv_selection!$C$2 & "!E18") -> 0 | O3: =INDIRECT(csv_selection!$B$2 & csv_selection!$C$2 & "!E20") -> 0.2769 | P3: =INDIRECT(csv_selection!$B$2 & csv_selection!$C$2 & "!E21") -> 0.2769 | Q3: =INDIRECT(csv_selection!$B$2 & csv_selection!$C$2 & "!E23") -> 0.318 | R3: =INDIRECT(csv_selection!$B$2 & csv_selection!$C$2 & "!E24") -> 0.7741 | S3: =INDIRECT(csv_selection!$B$2 & csv_selection!$C$2 & "!E25") -> 0.9822 | T3: =INDIRECT(csv_selection!$B$2 & csv_selection!$C$2 & "!E26") -> 0.9822 | U3: =INDIRECT(csv_selection!$B$2 & csv_selection!$C$2 & "!E27") -> 0.5876 | V3: =INDIRECT(csv_selection!$B$2 & csv_selection!$C$2 & "!E28") -> 0.356 | W3: =INDIRECT(csv_selection!$B$2 & csv_selection!$C$2 & "!E31") -> 1 | X3: =INDIRECT(csv_selection!$B$2 & csv_selection!$C$2 & "!E32") -> 1 | Y3: =INDIRECT(csv_selection!$B$2 & csv_selection!$C$2 & "!E33") -> 1 | Z3: =INDIRECT(csv_selection!$B$2 & csv_selection!$C$2 & "!E34") -> 1 | AA3: =INDIRECT(csv_selection!$B$2 & csv_selection!$C$2 & "!E35") -> 1 | AB3: =INDIRECT(csv_selection!$B$2 & csv_selection!$C$2 & "!E36") -> 1 | AC3: =INDIRECT(csv_selection!$B$2 & csv_selection!$C$2 & "!E37") -> 1 | AD3: =INDIRECT(csv_selection!$B$2 & csv_selection!$C$2 & "!E38") -> 1 | AE3: =INDIRECT(csv_selection!$B$2 & csv_selection!$C$2 & "!E40") -> 0 | AF3: =INDIRECT(csv_selection!$B$2 & csv_selection!$C$2 & "!E41") -> 0 | AG3: =INDIRECT(csv_selection!$B$2 & csv_selection!$C$2 & "!E42") -> 0 | AH3: =INDIRECT(csv_selection!$B$2 & csv_selection!$C$2 & "!E43") -> 0 | AI3: =INDIRECT(csv_selection!$B$2 & csv_selection!$C$2 & "!E44") -> 0 | AJ3: =INDIRECT(csv_selection!$B$2 & csv_selection!$C$2 & "!E45") -> 0 | AK3: =INDIRECT(csv_selection!$B$2 & csv_selection!$C$2 & "!E46") -> 0 | AL3: =INDIRECT(csv_selection!$B$2 & csv_selection!$C$2 & "!E47") -> 0 | AM3: =INDIRECT(csv_selection!$B$2 & csv_selection!$C$2 & "!E50") -> CLaw_perm | AN3: =INDIRECT(csv_selection!$B$2 & csv_selection!$C$2 & "!E51") -> CLaw_perm | AO3: =INDIRECT(csv_selection!$B$2 & csv_selection!$C$2 & "!E52") -> CLaw_perm | AP3: =INDIRECT(csv_selection!$B$2 & csv_selection!$C$2 & "!E53") -> CLaw_perm | AQ3: =INDIRECT(csv_selection!$B$2 & csv_selection!$C$2 & "!E54") -> CLaw_perm | AR3: =INDIRECT(csv_selection!$B$2 & csv_selection!$C$2 & "!E55") -> CLaw_perm | AS3: =INDIRECT(csv_selection!$B$2 & csv_selection!$C$2 & "!E56") -> CLaw_temp | AT3: =INDIRECT(csv_selection!$B$2 & csv_selection!$C$2 & "!E58") -> Claw_perm | AU3: =INDIRECT(csv_selection!$B$2 & csv_selection!$C$2 & "!E59") -> CLaw_rduc | AV3: =INDIRECT(csv_selection!$B$2 & csv_selection!$C$2 & "!E61") -> CLaw_2027 | AW3: =INDIRECT(csv_selection!$B$2 & csv_selection!$C$2 & "!E63") -> CLaw_perm | AX3: =INDIRECT(csv_selection!$B$2 & csv_selection!$C$2 & "!E64") -> CLaw_perm | AY3: =INDIRECT(csv_selection!$B$2 & csv_selection!$C$2 & "!E65") -> CLaw_perm | AZ3: =INDIRECT(csv_selection!$B$2 & csv_selection!$C$2 & "!E66") -> CLaw_perm | BA3: =INDIRECT(csv_selection!$B$2 & csv_selection!$C$2 & "!E67") -> CLaw_perm | BB3: =INDIRECT(csv_selection!$B$2 & csv_selection!$C$2 & "!E69") -> 0.5984 | BC3: =INDIRECT(csv_selection!$B$2 & csv_selection!$C$2 & "!E70") -> 0.0578 | BD3: =INDIRECT(csv_selection!$B$2 & csv_selection!$C$2 & "!E71") -> 0.3438 | BE3: =INDIRECT(csv_selection!$B$2 & csv_selection!$C$2 & "!E72") -> 0.5984 | BF3: =INDIRECT(csv_selection!$B$2 & csv_selection!$C$2 & "!E73") -> 0.0578 | BG3: =INDIRECT(csv_selection!$B$2 & csv_selection!$C$2 & "!E74") -> 0.3438 | BH3: =INDIRECT(csv_selection!$B$2 & csv_selection!$C$2 & "!E75") -> 1 | BI3: =INDIRECT(csv_selection!$B$2 & csv_selection!$C$2 & "!E76") -> 0 | BJ3: =INDIRECT(csv_selection!$B$2 & csv_selection!$C$2 & "!E77") -> 0 | BK3: =INDIRECT(csv_selection!$B$2 & csv_selection!$C$2 & "!E78") -> 0.5984 | BL3: =INDIRECT(csv_selection!$B$2 & csv_selection!$C$2 & "!E79") -> 0.0578 | BM3: =INDIRECT(csv_selection!$B$2 & csv_selection!$C$2 & "!E80") -> 0.3438 | BN3: =INDIRECT(csv_selection!$B$2 & csv_selection!$C$2 & "!E81") -> 1 | BO3: =INDIRECT(csv_selection!$B$2 & csv_selection!$C$2 & "!E82") -> 0 | BP3: =INDIRECT(csv_selection!$B$2 & csv_selection!$C$2 & "!E83") -> 0 | BQ3: =INDIRECT(csv_selection!$B$2 & csv_selection!$C$2 & "!E84") -> 0.5984 | BR3: =INDIRECT(csv_selection!$B$2 & csv_selection!$C$2 & "!E85") -> 0.0578 | BS3: =INDIRECT(csv_selection!$B$2 & csv_selection!$C$2 & "!E86") -> 0.3438
A4: =INDIRECT(csv_selection!$B$2 & csv_selection!$C$2 & "!F2") -> 2028 | B4: =INDIRECT(csv_selection!$B$2 & csv_selection!$C$2 & "!F5") -> 0.21 | C4: =INDIRECT(csv_selection!$B$2 & csv_selection!$C$2 & "!F6") -> 0.2759 | D4: =INDIRECT(csv_selection!$B$2 & csv_selection!$C$2 & "!F7") -> 0.0352 | E4: =INDIRECT(csv_selection!$B$2 & csv_selection!$C$2 & "!F8") -> 0.01 | F4: =INDIRECT(csv_selection!$B$2 & csv_selection!$C$2 & "!F9") -> 0 | G4: =INDIRECT(csv_selection!$B$2 & csv_selection!$C$2 & "!F11") -> 0.2059 | H4: =INDIRECT(csv_selection!$B$2 & csv_selection!$C$2 & "!F12") -> 0.2759 | I4: =INDIRECT(csv_selection!$B$2 & csv_selection!$C$2 & "!F13") -> 0.2059 | J4: =INDIRECT(csv_selection!$B$2 & csv_selection!$C$2 & "!F14") -> 0 | K4: =INDIRECT(csv_selection!$B$2 & csv_selection!$C$2 & "!F15") -> 0.2759 | L4: =INDIRECT(csv_selection!$B$2 & csv_selection!$C$2 & "!F16") -> 0.2759 | M4: =INDIRECT(csv_selection!$B$2 & csv_selection!$C$2 & "!F17") -> 0.2759 | N4: =INDIRECT(csv_selection!$B$2 & csv_selection!$C$2 & "!F18") -> 0 | O4: =INDIRECT(csv_selection!$B$2 & csv_selection!$C$2 & "!F20") -> 0.2759 | P4: =INDIRECT(csv_selection!$B$2 & csv_selection!$C$2 & "!F21") -> 0.2759 | Q4: =INDIRECT(csv_selection!$B$2 & csv_selection!$C$2 & "!F23") -> 0.3209 | R4: =INDIRECT(csv_selection!$B$2 & csv_selection!$C$2 & "!F24") -> 0.7749 | S4: =INDIRECT(csv_selection!$B$2 & csv_selection!$C$2 & "!F25") -> 0.9777 | T4: =INDIRECT(csv_selection!$B$2 & csv_selection!$C$2 & "!F26") -> 0.9777 | U4: =INDIRECT(csv_selection!$B$2 & csv_selection!$C$2 & "!F27") -> 0.6222 | V4: =INDIRECT(csv_selection!$B$2 & csv_selection!$C$2 & "!F28") -> 0.3709 | W4: =INDIRECT(csv_selection!$B$2 & csv_selection!$C$2 & "!F31") -> 1 | X4: =INDIRECT(csv_selection!$B$2 & csv_selection!$C$2 & "!F32") -> 1 | Y4: =INDIRECT(csv_selection!$B$2 & csv_selection!$C$2 & "!F33") -> 1 | Z4: =INDIRECT(csv_selection!$B$2 & csv_selection!$C$2 & "!F34") -> 1 | AA4: =INDIRECT(csv_selection!$B$2 & csv_selection!$C$2 & "!F35") -> 1 | AB4: =INDIRECT(csv_selection!$B$2 & csv_selection!$C$2 & "!F36") -> 1 | AC4: =INDIRECT(csv_selection!$B$2 & csv_selection!$C$2 & "!F37") -> 1 | AD4: =INDIRECT(csv_selection!$B$2 & csv_selection!$C$2 & "!F38") -> 1 | AE4: =INDIRECT(csv_selection!$B$2 & csv_selection!$C$2 & "!F40") -> 0 | AF4: =INDIRECT(csv_selection!$B$2 & csv_selection!$C$2 & "!F41") -> 0 | AG4: =INDIRECT(csv_selection!$B$2 & csv_selection!$C$2 & "!F42") -> 0 | AH4: =INDIRECT(csv_selection!$B$2 & csv_selection!$C$2 & "!F43") -> 0 | AI4: =INDIRECT(csv_selection!$B$2 & csv_selection!$C$2 & "!F44") -> 0 | AJ4: =INDIRECT(csv_selection!$B$2 & csv_selection!$C$2 & "!F45") -> 0 | AK4: =INDIRECT(csv_selection!$B$2 & csv_selection!$C$2 & "!F46") -> 0 | AL4: =INDIRECT(csv_selection!$B$2 & csv_selection!$C$2 & "!F47") -> 0 | AM4: =INDIRECT(csv_selection!$B$2 & csv_selection!$C$2 & "!F50") -> CLaw_perm | AN4: =INDIRECT(csv_selection!$B$2 & csv_selection!$C$2 & "!F51") -> CLaw_perm | AO4: =INDIRECT(csv_selection!$B$2 & csv_selection!$C$2 & "!F52") -> CLaw_perm | AP4: =INDIRECT(csv_selection!$B$2 & csv_selection!$C$2 & "!F53") -> CLaw_perm | AQ4: =INDIRECT(csv_selection!$B$2 & csv_selection!$C$2 & "!F54") -> CLaw_perm | AR4: =INDIRECT(csv_selection!$B$2 & csv_selection!$C$2 & "!F55") -> CLaw_perm | AS4: =INDIRECT(csv_selection!$B$2 & csv_selection!$C$2 & "!F56") -> CLaw_temp | AT4: =INDIRECT(csv_selection!$B$2 & csv_selection!$C$2 & "!F58") -> Claw_perm | AU4: =INDIRECT(csv_selection!$B$2 & csv_selection!$C$2 & "!F59") -> CLaw_rduc | AV4: =INDIRECT(csv_selection!$B$2 & csv_selection!$C$2 & "!F61") -> CLaw_2028 | AW4: =INDIRECT(csv_selection!$B$2 & csv_selection!$C$2 & "!F63") -> CLaw_perm | AX4: =INDIRECT(csv_selection!$B$2 & csv_selection!$C$2 & "!F64") -> CLaw_perm | AY4: =INDIRECT(csv_selection!$B$2 & csv_selection!$C$2 & "!F65") -> CLaw_perm | AZ4: =INDIRECT(csv_selection!$B$2 & csv_selection!$C$2 & "!F66") -> CLaw_perm | BA4: =INDIRECT(csv_selection!$B$2 & csv_selection!$C$2 & "!F67") -> CLaw_perm | BB4: =INDIRECT(csv_selection!$B$2 & csv_selection!$C$2 & "!F69") -> 0.5958 | BC4: =INDIRECT(csv_selection!$B$2 & csv_selection!$C$2 & "!F70") -> 0.0578 | BD4: =INDIRECT(csv_selection!$B$2 & csv_selection!$C$2 & "!F71") -> 0.3464 | BE4: =INDIRECT(csv_selection!$B$2 & csv_selection!$C$2 & "!F72") -> 0.5958 | BF4: =INDIRECT(csv_selection!$B$2 & csv_selection!$C$2 & "!F73") -> 0.0578 | BG4: =INDIRECT(csv_selection!$B$2 & csv_selection!$C$2 & "!F74") -> 0.3464 | BH4: =INDIRECT(csv_selection!$B$2 & csv_selection!$C$2 & "!F75") -> 1 | BI4: =INDIRECT(csv_selection!$B$2 & csv_selection!$C$2 & "!F76") -> 0 | BJ4: =INDIRECT(csv_selection!$B$2 & csv_selection!$C$2 & "!F77") -> 0 | BK4: =INDIRECT(csv_selection!$B$2 & csv_selection!$C$2 & "!F78") -> 0.5958 | BL4: =INDIRECT(csv_selection!$B$2 & csv_selection!$C$2 & "!F79") -> 0.0578 | BM4: =INDIRECT(csv_selection!$B$2 & csv_selection!$C$2 & "!F80") -> 0.3464 | BN4: =INDIRECT(csv_selection!$B$2 & csv_selection!$C$2 & "!F81") -> 1 | BO4: =INDIRECT(csv_selection!$B$2 & csv_selection!$C$2 & "!F82") -> 0 | BP4: =INDIRECT(csv_selection!$B$2 & csv_selection!$C$2 & "!F83") -> 0 | BQ4: =INDIRECT(csv_selection!$B$2 & csv_selection!$C$2 & "!F84") -> 0.5958 | BR4: =INDIRECT(csv_selection!$B$2 & csv_selection!$C$2 & "!F85") -> 0.0578 | BS4: =INDIRECT(csv_selection!$B$2 & csv_selection!$C$2 & "!F86") -> 0.3464
A5: =INDIRECT(csv_selection!$B$2 & csv_selection!$C$2 & "!G2") -> 2029 | B5: =INDIRECT(csv_selection!$B$2 & csv_selection!$C$2 & "!G5") -> 0.21 | C5: =INDIRECT(csv_selection!$B$2 & csv_selection!$C$2 & "!G6") -> 0.276 | D5: =INDIRECT(csv_selection!$B$2 & csv_selection!$C$2 & "!G7") -> 0.0352 | E5: =INDIRECT(csv_selection!$B$2 & csv_selection!$C$2 & "!G8") -> 0.01 | F5: =INDIRECT(csv_selection!$B$2 & csv_selection!$C$2 & "!G9") -> 0 | G5: =INDIRECT(csv_selection!$B$2 & csv_selection!$C$2 & "!G11") -> 0.2034 | H5: =INDIRECT(csv_selection!$B$2 & csv_selection!$C$2 & "!G12") -> 0.276 | I5: =INDIRECT(csv_selection!$B$2 & csv_selection!$C$2 & "!G13") -> 0.2034 | J5: =INDIRECT(csv_selection!$B$2 & csv_selection!$C$2 & "!G14") -> 0 | K5: =INDIRECT(csv_selection!$B$2 & csv_selection!$C$2 & "!G15") -> 0.276 | L5: =INDIRECT(csv_selection!$B$2 & csv_selection!$C$2 & "!G16") -> 0.276 | M5: =INDIRECT(csv_selection!$B$2 & csv_selection!$C$2 & "!G17") -> 0.276 | N5: =INDIRECT(csv_selection!$B$2 & csv_selection!$C$2 & "!G18") -> 0 | O5: =INDIRECT(csv_selection!$B$2 & csv_selection!$C$2 & "!G20") -> 0.276 | P5: =INDIRECT(csv_selection!$B$2 & csv_selection!$C$2 & "!G21") -> 0.276 | Q5: =INDIRECT(csv_selection!$B$2 & csv_selection!$C$2 & "!G23") -> 0.3133 | R5: =INDIRECT(csv_selection!$B$2 & csv_selection!$C$2 & "!G24") -> 0.775 | S5: =INDIRECT(csv_selection!$B$2 & csv_selection!$C$2 & "!G25") -> 0.9749 | T5: =INDIRECT(csv_selection!$B$2 & csv_selection!$C$2 & "!G26") -> 0.9749 | U5: =INDIRECT(csv_selection!$B$2 & csv_selection!$C$2 & "!G27") -> 0.6473 | V5: =INDIRECT(csv_selection!$B$2 & csv_selection!$C$2 & "!G28") -> 0.3781 | W5: =INDIRECT(csv_selection!$B$2 & csv_selection!$C$2 & "!G31") -> 1 | X5: =INDIRECT(csv_selection!$B$2 & csv_selection!$C$2 & "!G32") -> 1 | Y5: =INDIRECT(csv_selection!$B$2 & csv_selection!$C$2 & "!G33") -> 1 | Z5: =INDIRECT(csv_selection!$B$2 & csv_selection!$C$2 & "!G34") -> 1 | AA5: =INDIRECT(csv_selection!$B$2 & csv_selection!$C$2 & "!G35") -> 1 | AB5: =INDIRECT(csv_selection!$B$2 & csv_selection!$C$2 & "!G36") -> 1 | AC5: =INDIRECT(csv_selection!$B$2 & csv_selection!$C$2 & "!G37") -> 1 | AD5: =INDIRECT(csv_selection!$B$2 & csv_selection!$C$2 & "!G38") -> 1 | AE5: =INDIRECT(csv_selection!$B$2 & csv_selection!$C$2 & "!G40") -> 0 | AF5: =INDIRECT(csv_selection!$B$2 & csv_selection!$C$2 & "!G41") -> 0 | AG5: =INDIRECT(csv_selection!$B$2 & csv_selection!$C$2 & "!G42") -> 0 | AH5: =INDIRECT(csv_selection!$B$2 & csv_selection!$C$2 & "!G43") -> 0 | AI5: =INDIRECT(csv_selection!$B$2 & csv_selection!$C$2 & "!G44") -> 0 | AJ5: =INDIRECT(csv_selection!$B$2 & csv_selection!$C$2 & "!G45") -> 0 | AK5: =INDIRECT(csv_selection!$B$2 & csv_selection!$C$2 & "!G46") -> 0 | AL5: =INDIRECT(csv_selection!$B$2 & csv_selection!$C$2 & "!G47") -> 0 | AM5: =INDIRECT(csv_selection!$B$2 & csv_selection!$C$2 & "!G50") -> CLaw_perm | AN5: =INDIRECT(csv_selection!$B$2 & csv_selection!$C$2 & "!G51") -> CLaw_perm | AO5: =INDIRECT(csv_selection!$B$2 & csv_selection!$C$2 & "!G52") -> CLaw_perm | AP5: =INDIRECT(csv_selection!$B$2 & csv_selection!$C$2 & "!G53") -> CLaw_perm | AQ5: =INDIRECT(csv_selection!$B$2 & csv_selection!$C$2 & "!G54") -> CLaw_perm | AR5: =INDIRECT(csv_selection!$B$2 & csv_selection!$C$2 & "!G55") -> CLaw_perm | AS5: =INDIRECT(csv_selection!$B$2 & csv_selection!$C$2 & "!G56") -> CLaw_perm | AT5: =INDIRECT(csv_selection!$B$2 & csv_selection!$C$2 & "!G58") -> Claw_perm | AU5: =INDIRECT(csv_selection!$B$2 & csv_selection!$C$2 & "!G59") -> CLaw_rduc | AV5: =INDIRECT(csv_selection!$B$2 & csv_selection!$C$2 & "!G61") -> CLaw_2029 | AW5: =INDIRECT(csv_selection!$B$2 & csv_selection!$C$2 & "!G63") -> CLaw_perm | AX5: =INDIRECT(csv_selection!$B$2 & csv_selection!$C$2 & "!G64") -> CLaw_perm | AY5: =INDIRECT(csv_selection!$B$2 & csv_selection!$C$2 & "!G65") -> CLaw_perm | AZ5: =INDIRECT(csv_selection!$B$2 & csv_selection!$C$2 & "!G66") -> CLaw_perm | BA5: =INDIRECT(csv_selection!$B$2 & csv_selection!$C$2 & "!G67") -> CLaw_perm | BB5: =INDIRECT(csv_selection!$B$2 & csv_selection!$C$2 & "!G69") -> 0.6003 | BC5: =INDIRECT(csv_selection!$B$2 & csv_selection!$C$2 & "!G70") -> 0.0578 | BD5: =INDIRECT(csv_selection!$B$2 & csv_selection!$C$2 & "!G71") -> 0.3419 | BE5: =INDIRECT(csv_selection!$B$2 & csv_selection!$C$2 & "!G72") -> 0.6003 | BF5: =INDIRECT(csv_selection!$B$2 & csv_selection!$C$2 & "!G73") -> 0.0578 | BG5: =INDIRECT(csv_selection!$B$2 & csv_selection!$C$2 & "!G74") -> 0.3419 | BH5: =INDIRECT(csv_selection!$B$2 & csv_selection!$C$2 & "!G75") -> 1 | BI5: =INDIRECT(csv_selection!$B$2 & csv_selection!$C$2 & "!G76") -> 0 | BJ5: =INDIRECT(csv_selection!$B$2 & csv_selection!$C$2 & "!G77") -> 0 | BK5: =INDIRECT(csv_selection!$B$2 & csv_selection!$C$2 & "!G78") -> 0.6003 | BL5: =INDIRECT(csv_selection!$B$2 & csv_selection!$C$2 & "!G79") -> 0.0578 | BM5: =INDIRECT(csv_selection!$B$2 & csv_selection!$C$2 & "!G80") -> 0.3419 | BN5: =INDIRECT(csv_selection!$B$2 & csv_selection!$C$2 & "!G81") -> 1 | BO5: =INDIRECT(csv_selection!$B$2 & csv_selection!$C$2 & "!G82") -> 0 | BP5: =INDIRECT(csv_selection!$B$2 & csv_selection!$C$2 & "!G83") -> 0 | BQ5: =INDIRECT(csv_selection!$B$2 & csv_selection!$C$2 & "!G84") -> 0.6003 | BR5: =INDIRECT(csv_selection!$B$2 & csv_selection!$C$2 & "!G85") -> 0.0578 | BS5: =INDIRECT(csv_selection!$B$2 & csv_selection!$C$2 & "!G86") -> 0.3419
A6: =INDIRECT(csv_selection!$B$2 & csv_selection!$C$2 & "!H2") -> 2030 | B6: =INDIRECT(csv_selection!$B$2 & csv_selection!$C$2 & "!H5") -> 0.21 | C6: =INDIRECT(csv_selection!$B$2 & csv_selection!$C$2 & "!H6") -> 0.2766 | D6: =INDIRECT(csv_selection!$B$2 & csv_selection!$C$2 & "!H7") -> 0.0352 | E6: =INDIRECT(csv_selection!$B$2 & csv_selection!$C$2 & "!H8") -> 0.01 | F6: =INDIRECT(csv_selection!$B$2 & csv_selection!$C$2 & "!H9") -> 0 | G6: =INDIRECT(csv_selection!$B$2 & csv_selection!$C$2 & "!H11") -> 0.2031 | H6: =INDIRECT(csv_selection!$B$2 & csv_selection!$C$2 & "!H12") -> 0.2766 | I6: =INDIRECT(csv_selection!$B$2 & csv_selection!$C$2 & "!H13") -> 0.2031 | J6: =INDIRECT(csv_selection!$B$2 & csv_selection!$C$2 & "!H14") -> 0 | K6: =INDIRECT(csv_selection!$B$2 & csv_selection!$C$2 & "!H15") -> 0.2766 | L6: =INDIRECT(csv_selection!$B$2 & csv_selection!$C$2 & "!H16") -> 0.2766 | M6: =INDIRECT(csv_selection!$B$2 & csv_selection!$C$2 & "!H17") -> 0.2766 | N6: =INDIRECT(csv_selection!$B$2 & csv_selection!$C$2 & "!H18") -> 0 | O6: =INDIRECT(csv_selection!$B$2 & csv_selection!$C$2 & "!H20") -> 0.2766 | P6: =INDIRECT(csv_selection!$B$2 & csv_selection!$C$2 & "!H21") -> 0.2766 | Q6: =INDIRECT(csv_selection!$B$2 & csv_selection!$C$2 & "!H23") -> 0.305 | R6: =INDIRECT(csv_selection!$B$2 & csv_selection!$C$2 & "!H24") -> 0.7743 | S6: =INDIRECT(csv_selection!$B$2 & csv_selection!$C$2 & "!H25") -> 0.9734 | T6: =INDIRECT(csv_selection!$B$2 & csv_selection!$C$2 & "!H26") -> 0.9734 | U6: =INDIRECT(csv_selection!$B$2 & csv_selection!$C$2 & "!H27") -> 0.5526 | V6: =INDIRECT(csv_selection!$B$2 & csv_selection!$C$2 & "!H28") -> 0.0435 | W6: =INDIRECT(csv_selection!$B$2 & csv_selection!$C$2 & "!H31") -> 1 | X6: =INDIRECT(csv_selection!$B$2 & csv_selection!$C$2 & "!H32") -> 1 | Y6: =INDIRECT(csv_selection!$B$2 & csv_selection!$C$2 & "!H33") -> 1 | Z6: =INDIRECT(csv_selection!$B$2 & csv_selection!$C$2 & "!H34") -> 1 | AA6: =INDIRECT(csv_selection!$B$2 & csv_selection!$C$2 & "!H35") -> 1 | AB6: =INDIRECT(csv_selection!$B$2 & csv_selection!$C$2 & "!H36") -> 1 | AC6: =INDIRECT(csv_selection!$B$2 & csv_selection!$C$2 & "!H37") -> 1 | AD6: =INDIRECT(csv_selection!$B$2 & csv_selection!$C$2 & "!H38") -> 1 | AE6: =INDIRECT(csv_selection!$B$2 & csv_selection!$C$2 & "!H40") -> 0 | AF6: =INDIRECT(csv_selection!$B$2 & csv_selection!$C$2 & "!H41") -> 0 | AG6: =INDIRECT(csv_selection!$B$2 & csv_selection!$C$2 & "!H42") -> 0 | AH6: =INDIRECT(csv_selection!$B$2 & csv_selection!$C$2 & "!H43") -> 0 | AI6: =INDIRECT(csv_selection!$B$2 & csv_selection!$C$2 & "!H44") -> 0 | AJ6: =INDIRECT(csv_selection!$B$2 & csv_selection!$C$2 & "!H45") -> 0 | AK6: =INDIRECT(csv_selection!$B$2 & csv_selection!$C$2 & "!H46") -> 0 | AL6: =INDIRECT(csv_selection!$B$2 & csv_selection!$C$2 & "!H47") -> 0 | AM6: =INDIRECT(csv_selection!$B$2 & csv_selection!$C$2 & "!H50") -> CLaw_perm | AN6: =INDIRECT(csv_selection!$B$2 & csv_selection!$C$2 & "!H51") -> CLaw_perm | AO6: =INDIRECT(csv_selection!$B$2 & csv_selection!$C$2 & "!H52") -> CLaw_perm | AP6: =INDIRECT(csv_selection!$B$2 & csv_selection!$C$2 & "!H53") -> CLaw_perm | AQ6: =INDIRECT(csv_selection!$B$2 & csv_selection!$C$2 & "!H54") -> CLaw_perm | AR6: =INDIRECT(csv_selection!$B$2 & csv_selection!$C$2 & "!H55") -> CLaw_perm | AS6: =INDIRECT(csv_selection!$B$2 & csv_selection!$C$2 & "!H56") -> CLaw_perm | AT6: =INDIRECT(csv_selection!$B$2 & csv_selection!$C$2 & "!H58") -> Claw_perm | AU6: =INDIRECT(csv_selection!$B$2 & csv_selection!$C$2 & "!H59") -> CLaw_rduc | AV6: =INDIRECT(csv_selection!$B$2 & csv_selection!$C$2 & "!H61") -> CLaw_2030 | AW6: =INDIRECT(csv_selection!$B$2 & csv_selection!$C$2 & "!H63") -> CLaw_perm | AX6: =INDIRECT(csv_selection!$B$2 & csv_selection!$C$2 & "!H64") -> CLaw_perm | AY6: =INDIRECT(csv_selection!$B$2 & csv_selection!$C$2 & "!H65") -> CLaw_perm | AZ6: =INDIRECT(csv_selection!$B$2 & csv_selection!$C$2 & "!H66") -> CLaw_perm | BA6: =INDIRECT(csv_selection!$B$2 & csv_selection!$C$2 & "!H67") -> CLaw_perm | BB6: =INDIRECT(csv_selection!$B$2 & csv_selection!$C$2 & "!H69") -> 0.6008 | BC6: =INDIRECT(csv_selection!$B$2 & csv_selection!$C$2 & "!H70") -> 0.0578 | BD6: =INDIRECT(csv_selection!$B$2 & csv_selection!$C$2 & "!H71") -> 0.3414 | BE6: =INDIRECT(csv_selection!$B$2 & csv_selection!$C$2 & "!H72") -> 0.6008 | BF6: =INDIRECT(csv_selection!$B$2 & csv_selection!$C$2 & "!H73") -> 0.0578 | BG6: =INDIRECT(csv_selection!$B$2 & csv_selection!$C$2 & "!H74") -> 0.3414 | BH6: =INDIRECT(csv_selection!$B$2 & csv_selection!$C$2 & "!H75") -> 1 | BI6: =INDIRECT(csv_selection!$B$2 & csv_selection!$C$2 & "!H76") -> 0 | BJ6: =INDIRECT(csv_selection!$B$2 & csv_selection!$C$2 & "!H77") -> 0 | BK6: =INDIRECT(csv_selection!$B$2 & csv_selection!$C$2 & "!H78") -> 0.6008 | BL6: =INDIRECT(csv_selection!$B$2 & csv_selection!$C$2 & "!H79") -> 0.0578 | BM6: =INDIRECT(csv_selection!$B$2 & csv_selection!$C$2 & "!H80") -> 0.3414 | BN6: =INDIRECT(csv_selection!$B$2 & csv_selection!$C$2 & "!H81") -> 1 | BO6: =INDIRECT(csv_selection!$B$2 & csv_selection!$C$2 & "!H82") -> 0 | BP6: =INDIRECT(csv_selection!$B$2 & csv_selection!$C$2 & "!H83") -> 0 | BQ6: =INDIRECT(csv_selection!$B$2 & csv_selection!$C$2 & "!H84") -> 0.6008 | BR6: =INDIRECT(csv_selection!$B$2 & csv_selection!$C$2 & "!H85") -> 0.0578 | BS6: =INDIRECT(csv_selection!$B$2 & csv_selection!$C$2 & "!H86") -> 0.3414
A7: =INDIRECT(csv_selection!$B$2 & csv_selection!$C$2 & "!I2") -> 2031 | B7: =INDIRECT(csv_selection!$B$2 & csv_selection!$C$2 & "!I5") -> 0.21 | C7: =INDIRECT(csv_selection!$B$2 & csv_selection!$C$2 & "!I6") -> 0.276 | D7: =INDIRECT(csv_selection!$B$2 & csv_selection!$C$2 & "!I7") -> 0.0352 | E7: =INDIRECT(csv_selection!$B$2 & csv_selection!$C$2 & "!I8") -> 0.01 | F7: =INDIRECT(csv_selection!$B$2 & csv_selection!$C$2 & "!I9") -> 0 | G7: =INDIRECT(csv_selection!$B$2 & csv_selection!$C$2 & "!I11") -> 0.203 | H7: =INDIRECT(csv_selection!$B$2 & csv_selection!$C$2 & "!I12") -> 0.276 | I7: =INDIRECT(csv_selection!$B$2 & csv_selection!$C$2 & "!I13") -> 0.203 | J7: =INDIRECT(csv_selection!$B$2 & csv_selection!$C$2 & "!I14") -> 0 | K7: =INDIRECT(csv_selection!$B$2 & csv_selection!$C$2 & "!I15") -> 0.276 | L7: =INDIRECT(csv_selection!$B$2 & csv_selection!$C$2 & "!I16") -> 0.276 | M7: =INDIRECT(csv_selection!$B$2 & csv_selection!$C$2 & "!I17") -> 0.276 | N7: =INDIRECT(csv_selection!$B$2 & csv_selection!$C$2 & "!I18") -> 0 | O7: =INDIRECT(csv_selection!$B$2 & csv_selection!$C$2 & "!I20") -> 0.276 | P7: =INDIRECT(csv_selection!$B$2 & csv_selection!$C$2 & "!I21") -> 0.276 | Q7: =INDIRECT(csv_selection!$B$2 & csv_selection!$C$2 & "!I23") -> 0.3035 | R7: =INDIRECT(csv_selection!$B$2 & csv_selection!$C$2 & "!I24") -> 0.7744 | S7: =INDIRECT(csv_selection!$B$2 & csv_selection!$C$2 & "!I25") -> 0.9734 | T7: =INDIRECT(csv_selection!$B$2 & csv_selection!$C$2 & "!I26") -> 0.9734 | U7: =INDIRECT(csv_selection!$B$2 & csv_selection!$C$2 & "!I27") -> 0.5723 | V7: =INDIRECT(csv_selection!$B$2 & csv_selection!$C$2 & "!I28") -> 0.0436 | W7: =INDIRECT(csv_selection!$B$2 & csv_selection!$C$2 & "!I31") -> 1 | X7: =INDIRECT(csv_selection!$B$2 & csv_selection!$C$2 & "!I32") -> 1 | Y7: =INDIRECT(csv_selection!$B$2 & csv_selection!$C$2 & "!I33") -> 1 | Z7: =INDIRECT(csv_selection!$B$2 & csv_selection!$C$2 & "!I34") -> 1 | AA7: =INDIRECT(csv_selection!$B$2 & csv_selection!$C$2 & "!I35") -> 1 | AB7: =INDIRECT(csv_selection!$B$2 & csv_selection!$C$2 & "!I36") -> 1 | AC7: =INDIRECT(csv_selection!$B$2 & csv_selection!$C$2 & "!I37") -> 1 | AD7: =INDIRECT(csv_selection!$B$2 & csv_selection!$C$2 & "!I38") -> 1 | AE7: =INDIRECT(csv_selection!$B$2 & csv_selection!$C$2 & "!I40") -> 0 | AF7: =INDIRECT(csv_selection!$B$2 & csv_selection!$C$2 & "!I41") -> 0 | AG7: =INDIRECT(csv_selection!$B$2 & csv_selection!$C$2 & "!I42") -> 0 | AH7: =INDIRECT(csv_selection!$B$2 & csv_selection!$C$2 & "!I43") -> 0 | AI7: =INDIRECT(csv_selection!$B$2 & csv_selection!$C$2 & "!I44") -> 0 | AJ7: =INDIRECT(csv_selection!$B$2 & csv_selection!$C$2 & "!I45") -> 0 | AK7: =INDIRECT(csv_selection!$B$2 & csv_selection!$C$2 & "!I46") -> 0 | AL7: =INDIRECT(csv_selection!$B$2 & csv_selection!$C$2 & "!I47") -> 0 | AM7: =INDIRECT(csv_selection!$B$2 & csv_selection!$C$2 & "!I50") -> CLaw_perm | AN7: =INDIRECT(csv_selection!$B$2 & csv_selection!$C$2 & "!I51") -> CLaw_perm | AO7: =INDIRECT(csv_selection!$B$2 & csv_selection!$C$2 & "!I52") -> CLaw_perm | AP7: =INDIRECT(csv_selection!$B$2 & csv_selection!$C$2 & "!I53") -> CLaw_perm | AQ7: =INDIRECT(csv_selection!$B$2 & csv_selection!$C$2 & "!I54") -> CLaw_perm | AR7: =INDIRECT(csv_selection!$B$2 & csv_selection!$C$2 & "!I55") -> CLaw_perm | AS7: =INDIRECT(csv_selection!$B$2 & csv_selection!$C$2 & "!I56") -> CLaw_perm | AT7: =INDIRECT(csv_selection!$B$2 & csv_selection!$C$2 & "!I58") -> Claw_perm | AU7: =INDIRECT(csv_selection!$B$2 & csv_selection!$C$2 & "!I59") -> CLaw_rduc | AV7: =INDIRECT(csv_selection!$B$2 & csv_selection!$C$2 & "!I61") -> CLaw_2031 | AW7: =INDIRECT(csv_selection!$B$2 & csv_selection!$C$2 & "!I63") -> CLaw_perm | AX7: =INDIRECT(csv_selection!$B$2 & csv_selection!$C$2 & "!I64") -> CLaw_perm | AY7: =INDIRECT(csv_selection!$B$2 & csv_selection!$C$2 & "!I65") -> CLaw_perm | AZ7: =INDIRECT(csv_selection!$B$2 & csv_selection!$C$2 & "!I66") -> CLaw_perm | BA7: =INDIRECT(csv_selection!$B$2 & csv_selection!$C$2 & "!I67") -> CLaw_perm | BB7: =INDIRECT(csv_selection!$B$2 & csv_selection!$C$2 & "!I69") -> 0.6036 | BC7: =INDIRECT(csv_selection!$B$2 & csv_selection!$C$2 & "!I70") -> 0.0578 | BD7: =INDIRECT(csv_selection!$B$2 & csv_selection!$C$2 & "!I71") -> 0.3386 | BE7: =INDIRECT(csv_selection!$B$2 & csv_selection!$C$2 & "!I72") -> 0.6036 | BF7: =INDIRECT(csv_selection!$B$2 & csv_selection!$C$2 & "!I73") -> 0.0578 | BG7: =INDIRECT(csv_selection!$B$2 & csv_selection!$C$2 & "!I74") -> 0.3386 | BH7: =INDIRECT(csv_selection!$B$2 & csv_selection!$C$2 & "!I75") -> 1 | BI7: =INDIRECT(csv_selection!$B$2 & csv_selection!$C$2 & "!I76") -> 0 | BJ7: =INDIRECT(csv_selection!$B$2 & csv_selection!$C$2 & "!I77") -> 0 | BK7: =INDIRECT(csv_selection!$B$2 & csv_selection!$C$2 & "!I78") -> 0.6036 | BL7: =INDIRECT(csv_selection!$B$2 & csv_selection!$C$2 & "!I79") -> 0.0578 | BM7: =INDIRECT(csv_selection!$B$2 & csv_selection!$C$2 & "!I80") -> 0.3386 | BN7: =INDIRECT(csv_selection!$B$2 & csv_selection!$C$2 & "!I81") -> 1 | BO7: =INDIRECT(csv_selection!$B$2 & csv_selection!$C$2 & "!I82") -> 0 | BP7: =INDIRECT(csv_selection!$B$2 & csv_selection!$C$2 & "!I83") -> 0 | BQ7: =INDIRECT(csv_selection!$B$2 & csv_selection!$C$2 & "!I84") -> 0.6036 | BR7: =INDIRECT(csv_selection!$B$2 & csv_selection!$C$2 & "!I85") -> 0.0578 | BS7: =INDIRECT(csv_selection!$B$2 & csv_selection!$C$2 & "!I86") -> 0.3386
A8: =INDIRECT(csv_selection!$B$2 & csv_selection!$C$2 & "!J2") -> 2032 | B8: =INDIRECT(csv_selection!$B$2 & csv_selection!$C$2 & "!J5") -> 0.21 | C8: =INDIRECT(csv_selection!$B$2 & csv_selection!$C$2 & "!J6") -> 0.275 | D8: =INDIRECT(csv_selection!$B$2 & csv_selection!$C$2 & "!J7") -> 0.0352 | E8: =INDIRECT(csv_selection!$B$2 & csv_selection!$C$2 & "!J8") -> 0.01 | F8: =INDIRECT(csv_selection!$B$2 & csv_selection!$C$2 & "!J9") -> 0 | G8: =INDIRECT(csv_selection!$B$2 & csv_selection!$C$2 & "!J11") -> 0.2037 | H8: =INDIRECT(csv_selection!$B$2 & csv_selection!$C$2 & "!J12") -> 0.275 | I8: =INDIRECT(csv_selection!$B$2 & csv_selection!$C$2 & "!J13") -> 0.2037 | J8: =INDIRECT(csv_selection!$B$2 & csv_selection!$C$2 & "!J14") -> 0 | K8: =INDIRECT(csv_selection!$B$2 & csv_selection!$C$2 & "!J15") -> 0.275 | L8: =INDIRECT(csv_selection!$B$2 & csv_selection!$C$2 & "!J16") -> 0.275 | M8: =INDIRECT(csv_selection!$B$2 & csv_selection!$C$2 & "!J17") -> 0.275 | N8: =INDIRECT(csv_selection!$B$2 & csv_selection!$C$2 & "!J18") -> 0 | O8: =INDIRECT(csv_selection!$B$2 & csv_selection!$C$2 & "!J20") -> 0.275 | P8: =INDIRECT(csv_selection!$B$2 & csv_selection!$C$2 & "!J21") -> 0.275 | Q8: =INDIRECT(csv_selection!$B$2 & csv_selection!$C$2 & "!J23") -> 0.3006 | R8: =INDIRECT(csv_selection!$B$2 & csv_selection!$C$2 & "!J24") -> 0.774 | S8: =INDIRECT(csv_selection!$B$2 & csv_selection!$C$2 & "!J25") -> 0.9737 | T8: =INDIRECT(csv_selection!$B$2 & csv_selection!$C$2 & "!J26") -> 0.9737 | U8: =INDIRECT(csv_selection!$B$2 & csv_selection!$C$2 & "!J27") -> 0.589 | V8: =INDIRECT(csv_selection!$B$2 & csv_selection!$C$2 & "!J28") -> 0.0424 | W8: =INDIRECT(csv_selection!$B$2 & csv_selection!$C$2 & "!J31") -> 1 | X8: =INDIRECT(csv_selection!$B$2 & csv_selection!$C$2 & "!J32") -> 1 | Y8: =INDIRECT(csv_selection!$B$2 & csv_selection!$C$2 & "!J33") -> 1 | Z8: =INDIRECT(csv_selection!$B$2 & csv_selection!$C$2 & "!J34") -> 1 | AA8: =INDIRECT(csv_selection!$B$2 & csv_selection!$C$2 & "!J35") -> 1 | AB8: =INDIRECT(csv_selection!$B$2 & csv_selection!$C$2 & "!J36") -> 1 | AC8: =INDIRECT(csv_selection!$B$2 & csv_selection!$C$2 & "!J37") -> 1 | AD8: =INDIRECT(csv_selection!$B$2 & csv_selection!$C$2 & "!J38") -> 1 | AE8: =INDIRECT(csv_selection!$B$2 & csv_selection!$C$2 & "!J40") -> 0 | AF8: =INDIRECT(csv_selection!$B$2 & csv_selection!$C$2 & "!J41") -> 0 | AG8: =INDIRECT(csv_selection!$B$2 & csv_selection!$C$2 & "!J42") -> 0 | AH8: =INDIRECT(csv_selection!$B$2 & csv_selection!$C$2 & "!J43") -> 0 | AI8: =INDIRECT(csv_selection!$B$2 & csv_selection!$C$2 & "!J44") -> 0 | AJ8: =INDIRECT(csv_selection!$B$2 & csv_selection!$C$2 & "!J45") -> 0 | AK8: =INDIRECT(csv_selection!$B$2 & csv_selection!$C$2 & "!J46") -> 0 | AL8: =INDIRECT(csv_selection!$B$2 & csv_selection!$C$2 & "!J47") -> 0 | AM8: =INDIRECT(csv_selection!$B$2 & csv_selection!$C$2 & "!J50") -> CLaw_perm | AN8: =INDIRECT(csv_selection!$B$2 & csv_selection!$C$2 & "!J51") -> CLaw_perm | AO8: =INDIRECT(csv_selection!$B$2 & csv_selection!$C$2 & "!J52") -> CLaw_perm | AP8: =INDIRECT(csv_selection!$B$2 & csv_selection!$C$2 & "!J53") -> CLaw_perm | AQ8: =INDIRECT(csv_selection!$B$2 & csv_selection!$C$2 & "!J54") -> CLaw_perm | AR8: =INDIRECT(csv_selection!$B$2 & csv_selection!$C$2 & "!J55") -> CLaw_perm | AS8: =INDIRECT(csv_selection!$B$2 & csv_selection!$C$2 & "!J56") -> CLaw_perm | AT8: =INDIRECT(csv_selection!$B$2 & csv_selection!$C$2 & "!J58") -> Claw_perm | AU8: =INDIRECT(csv_selection!$B$2 & csv_selection!$C$2 & "!J59") -> CLaw_rduc | AV8: =INDIRECT(csv_selection!$B$2 & csv_selection!$C$2 & "!J61") -> CLaw_2032 | AW8: =INDIRECT(csv_selection!$B$2 & csv_selection!$C$2 & "!J63") -> CLaw_perm | AX8: =INDIRECT(csv_selection!$B$2 & csv_selection!$C$2 & "!J64") -> CLaw_perm | AY8: =INDIRECT(csv_selection!$B$2 & csv_selection!$C$2 & "!J65") -> CLaw_perm | AZ8: =INDIRECT(csv_selection!$B$2 & csv_selection!$C$2 & "!J66") -> CLaw_perm | BA8: =INDIRECT(csv_selection!$B$2 & csv_selection!$C$2 & "!J67") -> CLaw_perm | BB8: =INDIRECT(csv_selection!$B$2 & csv_selection!$C$2 & "!J69") -> 0.604 | BC8: =INDIRECT(csv_selection!$B$2 & csv_selection!$C$2 & "!J70") -> 0.0578 | BD8: =INDIRECT(csv_selection!$B$2 & csv_selection!$C$2 & "!J71") -> 0.3382 | BE8: =INDIRECT(csv_selection!$B$2 & csv_selection!$C$2 & "!J72") -> 0.604 | BF8: =INDIRECT(csv_selection!$B$2 & csv_selection!$C$2 & "!J73") -> 0.0578 | BG8: =INDIRECT(csv_selection!$B$2 & csv_selection!$C$2 & "!J74") -> 0.3382 | BH8: =INDIRECT(csv_selection!$B$2 & csv_selection!$C$2 & "!J75") -> 1 | BI8: =INDIRECT(csv_selection!$B$2 & csv_selection!$C$2 & "!J76") -> 0 | BJ8: =INDIRECT(csv_selection!$B$2 & csv_selection!$C$2 & "!J77") -> 0 | BK8: =INDIRECT(csv_selection!$B$2 & csv_selection!$C$2 & "!J78") -> 0.604 | BL8: =INDIRECT(csv_selection!$B$2 & csv_selection!$C$2 & "!J79") -> 0.0578 | BM8: =INDIRECT(csv_selection!$B$2 & csv_selection!$C$2 & "!J80") -> 0.3382 | BN8: =INDIRECT(csv_selection!$B$2 & csv_selection!$C$2 & "!J81") -> 1 | BO8: =INDIRECT(csv_selection!$B$2 & csv_selection!$C$2 & "!J82") -> 0 | BP8: =INDIRECT(csv_selection!$B$2 & csv_selection!$C$2 & "!J83") -> 0 | BQ8: =INDIRECT(csv_selection!$B$2 & csv_selection!$C$2 & "!J84") -> 0.604 | BR8: =INDIRECT(csv_selection!$B$2 & csv_selection!$C$2 & "!J85") -> 0.0578 | BS8: =INDIRECT(csv_selection!$B$2 & csv_selection!$C$2 & "!J86") -> 0.3382
A9: =INDIRECT(csv_selection!$B$2 & csv_selection!$C$2 & "!K2") -> 2033 | B9: =INDIRECT(csv_selection!$B$2 & csv_selection!$C$2 & "!K5") -> 0.21 | C9: =INDIRECT(csv_selection!$B$2 & csv_selection!$C$2 & "!K6") -> 0.2761 | D9: =INDIRECT(csv_selection!$B$2 & csv_selection!$C$2 & "!K7") -> 0.0352 | E9: =INDIRECT(csv_selection!$B$2 & csv_selection!$C$2 & "!K8") -> 0.01 | F9: =INDIRECT(csv_selection!$B$2 & csv_selection!$C$2 & "!K9") -> 0 | G9: =INDIRECT(csv_selection!$B$2 & csv_selection!$C$2 & "!K11") -> 0.2037 | H9: =INDIRECT(csv_selection!$B$2 & csv_selection!$C$2 & "!K12") -> 0.2761 | I9: =INDIRECT(csv_selection!$B$2 & csv_selection!$C$2 & "!K13") -> 0.2037 | J9: =INDIRECT(csv_selection!$B$2 & csv_selection!$C$2 & "!K14") -> 0 | K9: =INDIRECT(csv_selection!$B$2 & csv_selection!$C$2 & "!K15") -> 0.2761 | L9: =INDIRECT(csv_selection!$B$2 & csv_selection!$C$2 & "!K16") -> 0.2761 | M9: =INDIRECT(csv_selection!$B$2 & csv_selection!$C$2 & "!K17") -> 0.2761 | N9: =INDIRECT(csv_selection!$B$2 & csv_selection!$C$2 & "!K18") -> 0 | O9: =INDIRECT(csv_selection!$B$2 & csv_selection!$C$2 & "!K20") -> 0.2761 | P9: =INDIRECT(csv_selection!$B$2 & csv_selection!$C$2 & "!K21") -> 0.2761 | Q9: =INDIRECT(csv_selection!$B$2 & csv_selection!$C$2 & "!K23") -> 0.2979 | R9: =INDIRECT(csv_selection!$B$2 & csv_selection!$C$2 & "!K24") -> 0.7738 | S9: =INDIRECT(csv_selection!$B$2 & csv_selection!$C$2 & "!K25") -> 0.9743 | T9: =INDIRECT(csv_selection!$B$2 & csv_selection!$C$2 & "!K26") -> 0.9743 | U9: =INDIRECT(csv_selection!$B$2 & csv_selection!$C$2 & "!K27") -> 0.6036 | V9: =INDIRECT(csv_selection!$B$2 & csv_selection!$C$2 & "!K28") -> 0.0413 | W9: =INDIRECT(csv_selection!$B$2 & csv_selection!$C$2 & "!K31") -> 1 | X9: =INDIRECT(csv_selection!$B$2 & csv_selection!$C$2 & "!K32") -> 1 | Y9: =INDIRECT(csv_selection!$B$2 & csv_selection!$C$2 & "!K33") -> 1 | Z9: =INDIRECT(csv_selection!$B$2 & csv_selection!$C$2 & "!K34") -> 1 | AA9: =INDIRECT(csv_selection!$B$2 & csv_selection!$C$2 & "!K35") -> 1 | AB9: =INDIRECT(csv_selection!$B$2 & csv_selection!$C$2 & "!K36") -> 1 | AC9: =INDIRECT(csv_selection!$B$2 & csv_selection!$C$2 & "!K37") -> 1 | AD9: =INDIRECT(csv_selection!$B$2 & csv_selection!$C$2 & "!K38") -> 1 | AE9: =INDIRECT(csv_selection!$B$2 & csv_selection!$C$2 & "!K40") -> 0 | AF9: =INDIRECT(csv_selection!$B$2 & csv_selection!$C$2 & "!K41") -> 0 | AG9: =INDIRECT(csv_selection!$B$2 & csv_selection!$C$2 & "!K42") -> 0 | AH9: =INDIRECT(csv_selection!$B$2 & csv_selection!$C$2 & "!K43") -> 0 | AI9: =INDIRECT(csv_selection!$B$2 & csv_selection!$C$2 & "!K44") -> 0 | AJ9: =INDIRECT(csv_selection!$B$2 & csv_selection!$C$2 & "!K45") -> 0 | AK9: =INDIRECT(csv_selection!$B$2 & csv_selection!$C$2 & "!K46") -> 0 | AL9: =INDIRECT(csv_selection!$B$2 & csv_selection!$C$2 & "!K47") -> 0 | AM9: =INDIRECT(csv_selection!$B$2 & csv_selection!$C$2 & "!K50") -> CLaw_perm | AN9: =INDIRECT(csv_selection!$B$2 & csv_selection!$C$2 & "!K51") -> CLaw_perm | AO9: =INDIRECT(csv_selection!$B$2 & csv_selection!$C$2 & "!K52") -> CLaw_perm | AP9: =INDIRECT(csv_selection!$B$2 & csv_selection!$C$2 & "!K53") -> CLaw_perm | AQ9: =INDIRECT(csv_selection!$B$2 & csv_selection!$C$2 & "!K54") -> CLaw_perm | AR9: =INDIRECT(csv_selection!$B$2 & csv_selection!$C$2 & "!K55") -> CLaw_perm | AS9: =INDIRECT(csv_selection!$B$2 & csv_selection!$C$2 & "!K56") -> CLaw_perm | AT9: =INDIRECT(csv_selection!$B$2 & csv_selection!$C$2 & "!K58") -> Claw_perm | AU9: =INDIRECT(csv_selection!$B$2 & csv_selection!$C$2 & "!K59") -> CLaw_rduc | AV9: =INDIRECT(csv_selection!$B$2 & csv_selection!$C$2 & "!K61") -> CLaw_2033 | AW9: =INDIRECT(csv_selection!$B$2 & csv_selection!$C$2 & "!K63") -> CLaw_perm | AX9: =INDIRECT(csv_selection!$B$2 & csv_selection!$C$2 & "!K64") -> CLaw_perm | AY9: =INDIRECT(csv_selection!$B$2 & csv_selection!$C$2 & "!K65") -> CLaw_perm | AZ9: =INDIRECT(csv_selection!$B$2 & csv_selection!$C$2 & "!K66") -> CLaw_perm | BA9: =INDIRECT(csv_selection!$B$2 & csv_selection!$C$2 & "!K67") -> CLaw_perm | BB9: =INDIRECT(csv_selection!$B$2 & csv_selection!$C$2 & "!K69") -> 0.6054 | BC9: =INDIRECT(csv_selection!$B$2 & csv_selection!$C$2 & "!K70") -> 0.0578 | BD9: =INDIRECT(csv_selection!$B$2 & csv_selection!$C$2 & "!K71") -> 0.3368 | BE9: =INDIRECT(csv_selection!$B$2 & csv_selection!$C$2 & "!K72") -> 0.6054 | BF9: =INDIRECT(csv_selection!$B$2 & csv_selection!$C$2 & "!K73") -> 0.0578 | BG9: =INDIRECT(csv_selection!$B$2 & csv_selection!$C$2 & "!K74") -> 0.3368 | BH9: =INDIRECT(csv_selection!$B$2 & csv_selection!$C$2 & "!K75") -> 1 | BI9: =INDIRECT(csv_selection!$B$2 & csv_selection!$C$2 & "!K76") -> 0 | BJ9: =INDIRECT(csv_selection!$B$2 & csv_selection!$C$2 & "!K77") -> 0 | BK9: =INDIRECT(csv_selection!$B$2 & csv_selection!$C$2 & "!K78") -> 0.6054 | BL9: =INDIRECT(csv_selection!$B$2 & csv_selection!$C$2 & "!K79") -> 0.0578 | BM9: =INDIRECT(csv_selection!$B$2 & csv_selection!$C$2 & "!K80") -> 0.3368 | BN9: =INDIRECT(csv_selection!$B$2 & csv_selection!$C$2 & "!K81") -> 1 | BO9: =INDIRECT(csv_selection!$B$2 & csv_selection!$C$2 & "!K82") -> 0 | BP9: =INDIRECT(csv_selection!$B$2 & csv_selection!$C$2 & "!K83") -> 0 | BQ9: =INDIRECT(csv_selection!$B$2 & csv_selection!$C$2 & "!K84") -> 0.6054 | BR9: =INDIRECT(csv_selection!$B$2 & csv_selection!$C$2 & "!K85") -> 0.0578 | BS9: =INDIRECT(csv_selection!$B$2 & csv_selection!$C$2 & "!K86") -> 0.3368
A10: =INDIRECT(csv_selection!$B$2 & csv_selection!$C$2 & "!L2") -> 2034 | B10: =INDIRECT(csv_selection!$B$2 & csv_selection!$C$2 & "!L5") -> 0.21 | C10: =INDIRECT(csv_selection!$B$2 & csv_selection!$C$2 & "!L6") -> 0.2764 | D10: =INDIRECT(csv_selection!$B$2 & csv_selection!$C$2 & "!L7") -> 0.0352 | E10: =INDIRECT(csv_selection!$B$2 & csv_selection!$C$2 & "!L8") -> 0.01 | F10: =INDIRECT(csv_selection!$B$2 & csv_selection!$C$2 & "!L9") -> 0 | G10: =INDIRECT(csv_selection!$B$2 & csv_selection!$C$2 & "!L11") -> 0.2044 | H10: =INDIRECT(csv_selection!$B$2 & csv_selection!$C$2 & "!L12") -> 0.2764 | I10: =INDIRECT(csv_selection!$B$2 & csv_selection!$C$2 & "!L13") -> 0.2044 | J10: =INDIRECT(csv_selection!$B$2 & csv_selection!$C$2 & "!L14") -> 0 | K10: =INDIRECT(csv_selection!$B$2 & csv_selection!$C$2 & "!L15") -> 0.2764 | L10: =INDIRECT(csv_selection!$B$2 & csv_selection!$C$2 & "!L16") -> 0.2764 | M10: =INDIRECT(csv_selection!$B$2 & csv_selection!$C$2 & "!L17") -> 0.2764 | N10: =INDIRECT(csv_selection!$B$2 & csv_selection!$C$2 & "!L18") -> 0 | O10: =INDIRECT(csv_selection!$B$2 & csv_selection!$C$2 & "!L20") -> 0.2764 | P10: =INDIRECT(csv_selection!$B$2 & csv_selection!$C$2 & "!L21") -> 0.2764 | Q10: =INDIRECT(csv_selection!$B$2 & csv_selection!$C$2 & "!L23") -> 0.2948 | R10: =INDIRECT(csv_selection!$B$2 & csv_selection!$C$2 & "!L24") -> 0.7739 | S10: =INDIRECT(csv_selection!$B$2 & csv_selection!$C$2 & "!L25") -> 0.9746 | T10: =INDIRECT(csv_selection!$B$2 & csv_selection!$C$2 & "!L26") -> 0.9746 | U10: =INDIRECT(csv_selection!$B$2 & csv_selection!$C$2 & "!L27") -> 0.6137 | V10: =INDIRECT(csv_selection!$B$2 & csv_selection!$C$2 & "!L28") -> 0.04 | W10: =INDIRECT(csv_selection!$B$2 & csv_selection!$C$2 & "!L31") -> 1 | X10: =INDIRECT(csv_selection!$B$2 & csv_selection!$C$2 & "!L32") -> 1 | Y10: =INDIRECT(csv_selection!$B$2 & csv_selection!$C$2 & "!L33") -> 1 | Z10: =INDIRECT(csv_selection!$B$2 & csv_selection!$C$2 & "!L34") -> 1 | AA10: =INDIRECT(csv_selection!$B$2 & csv_selection!$C$2 & "!L35") -> 1 | AB10: =INDIRECT(csv_selection!$B$2 & csv_selection!$C$2 & "!L36") -> 1 | AC10: =INDIRECT(csv_selection!$B$2 & csv_selection!$C$2 & "!L37") -> 1 | AD10: =INDIRECT(csv_selection!$B$2 & csv_selection!$C$2 & "!L38") -> 1 | AE10: =INDIRECT(csv_selection!$B$2 & csv_selection!$C$2 & "!L40") -> 0 | AF10: =INDIRECT(csv_selection!$B$2 & csv_selection!$C$2 & "!L41") -> 0 | AG10: =INDIRECT(csv_selection!$B$2 & csv_selection!$C$2 & "!L42") -> 0 | AH10: =INDIRECT(csv_selection!$B$2 & csv_selection!$C$2 & "!L43") -> 0 | AI10: =INDIRECT(csv_selection!$B$2 & csv_selection!$C$2 & "!L44") -> 0 | AJ10: =INDIRECT(csv_selection!$B$2 & csv_selection!$C$2 & "!L45") -> 0 | AK10: =INDIRECT(csv_selection!$B$2 & csv_selection!$C$2 & "!L46") -> 0 | AL10: =INDIRECT(csv_selection!$B$2 & csv_selection!$C$2 & "!L47") -> 0 | AM10: =INDIRECT(csv_selection!$B$2 & csv_selection!$C$2 & "!L50") -> CLaw_perm | AN10: =INDIRECT(csv_selection!$B$2 & csv_selection!$C$2 & "!L51") -> CLaw_perm | AO10: =INDIRECT(csv_selection!$B$2 & csv_selection!$C$2 & "!L52") -> CLaw_perm | AP10: =INDIRECT(csv_selection!$B$2 & csv_selection!$C$2 & "!L53") -> CLaw_perm | AQ10: =INDIRECT(csv_selection!$B$2 & csv_selection!$C$2 & "!L54") -> CLaw_perm | AR10: =INDIRECT(csv_selection!$B$2 & csv_selection!$C$2 & "!L55") -> CLaw_perm | AS10: =INDIRECT(csv_selection!$B$2 & csv_selection!$C$2 & "!L56") -> CLaw_perm | AT10: =INDIRECT(csv_selection!$B$2 & csv_selection!$C$2 & "!L58") -> Claw_perm | AU10: =INDIRECT(csv_selection!$B$2 & csv_selection!$C$2 & "!L59") -> CLaw_rduc | AV10: =INDIRECT(csv_selection!$B$2 & csv_selection!$C$2 & "!L61") -> CLaw_perm | AW10: =INDIRECT(csv_selection!$B$2 & csv_selection!$C$2 & "!L63") -> CLaw_perm | AX10: =INDIRECT(csv_selection!$B$2 & csv_selection!$C$2 & "!L64") -> CLaw_perm | AY10: =INDIRECT(csv_selection!$B$2 & csv_selection!$C$2 & "!L65") -> CLaw_perm | AZ10: =INDIRECT(csv_selection!$B$2 & csv_selection!$C$2 & "!L66") -> CLaw_perm | BA10: =INDIRECT(csv_selection!$B$2 & csv_selection!$C$2 & "!L67") -> CLaw_perm | BB10: =INDIRECT(csv_selection!$B$2 & csv_selection!$C$2 & "!L69") -> 0.6065 | BC10: =INDIRECT(csv_selection!$B$2 & csv_selection!$C$2 & "!L70") -> 0.0578 | BD10: =INDIRECT(csv_selection!$B$2 & csv_selection!$C$2 & "!L71") -> 0.3357 | BE10: =INDIRECT(csv_selection!$B$2 & csv_selection!$C$2 & "!L72") -> 0.6065 | BF10: =INDIRECT(csv_selection!$B$2 & csv_selection!$C$2 & "!L73") -> 0.0578 | BG10: =INDIRECT(csv_selection!$B$2 & csv_selection!$C$2 & "!L74") -> 0.3357 | BH10: =INDIRECT(csv_selection!$B$2 & csv_selection!$C$2 & "!L75") -> 1 | BI10: =INDIRECT(csv_selection!$B$2 & csv_selection!$C$2 & "!L76") -> 0 | BJ10: =INDIRECT(csv_selection!$B$2 & csv_selection!$C$2 & "!L77") -> 0 | BK10: =INDIRECT(csv_selection!$B$2 & csv_selection!$C$2 & "!L78") -> 0.6065 | BL10: =INDIRECT(csv_selection!$B$2 & csv_selection!$C$2 & "!L79") -> 0.0578 | BM10: =INDIRECT(csv_selection!$B$2 & csv_selection!$C$2 & "!L80") -> 0.3357 | BN10: =INDIRECT(csv_selection!$B$2 & csv_selection!$C$2 & "!L81") -> 1 | BO10: =INDIRECT(csv_selection!$B$2 & csv_selection!$C$2 & "!L82") -> 0 | BP10: =INDIRECT(csv_selection!$B$2 & csv_selection!$C$2 & "!L83") -> 0 | BQ10: =INDIRECT(csv_selection!$B$2 & csv_selection!$C$2 & "!L84") -> 0.6065 | BR10: =INDIRECT(csv_selection!$B$2 & csv_selection!$C$2 & "!L85") -> 0.0578 | BS10: =INDIRECT(csv_selection!$B$2 & csv_selection!$C$2 & "!L86") -> 0.3357
A11: =INDIRECT(csv_selection!$B$2 & csv_selection!$C$2 & "!M2") -> 2035 | B11: =INDIRECT(csv_selection!$B$2 & csv_selection!$C$2 & "!M5") -> 0.21 | C11: =INDIRECT(csv_selection!$B$2 & csv_selection!$C$2 & "!M6") -> 0.2767 | D11: =INDIRECT(csv_selection!$B$2 & csv_selection!$C$2 & "!M7") -> 0.0353 | E11: =INDIRECT(csv_selection!$B$2 & csv_selection!$C$2 & "!M8") -> 0.01 | F11: =INDIRECT(csv_selection!$B$2 & csv_selection!$C$2 & "!M9") -> 0 | G11: =INDIRECT(csv_selection!$B$2 & csv_selection!$C$2 & "!M11") -> 0.2037 | H11: =INDIRECT(csv_selection!$B$2 & csv_selection!$C$2 & "!M12") -> 0.2767 | I11: =INDIRECT(csv_selection!$B$2 & csv_selection!$C$2 & "!M13") -> 0.2037 | J11: =INDIRECT(csv_selection!$B$2 & csv_selection!$C$2 & "!M14") -> 0 | K11: =INDIRECT(csv_selection!$B$2 & csv_selection!$C$2 & "!M15") -> 0.2767 | L11: =INDIRECT(csv_selection!$B$2 & csv_selection!$C$2 & "!M16") -> 0.2767 | M11: =INDIRECT(csv_selection!$B$2 & csv_selection!$C$2 & "!M17") -> 0.2767 | N11: =INDIRECT(csv_selection!$B$2 & csv_selection!$C$2 & "!M18") -> 0 | O11: =INDIRECT(csv_selection!$B$2 & csv_selection!$C$2 & "!M20") -> 0.2767 | P11: =INDIRECT(csv_selection!$B$2 & csv_selection!$C$2 & "!M21") -> 0.2767 | Q11: =INDIRECT(csv_selection!$B$2 & csv_selection!$C$2 & "!M23") -> 0.2919 | R11: =INDIRECT(csv_selection!$B$2 & csv_selection!$C$2 & "!M24") -> 0.7732 | S11: =INDIRECT(csv_selection!$B$2 & csv_selection!$C$2 & "!M25") -> 0.9748 | T11: =INDIRECT(csv_selection!$B$2 & csv_selection!$C$2 & "!M26") -> 0.9748 | U11: =INDIRECT(csv_selection!$B$2 & csv_selection!$C$2 & "!M27") -> 0.6211 | V11: =INDIRECT(csv_selection!$B$2 & csv_selection!$C$2 & "!M28") -> 0.0383 | W11: =INDIRECT(csv_selection!$B$2 & csv_selection!$C$2 & "!M31") -> 1 | X11: =INDIRECT(csv_selection!$B$2 & csv_selection!$C$2 & "!M32") -> 1 | Y11: =INDIRECT(csv_selection!$B$2 & csv_selection!$C$2 & "!M33") -> 1 | Z11: =INDIRECT(csv_selection!$B$2 & csv_selection!$C$2 & "!M34") -> 1 | AA11: =INDIRECT(csv_selection!$B$2 & csv_selection!$C$2 & "!M35") -> 1 | AB11: =INDIRECT(csv_selection!$B$2 & csv_selection!$C$2 & "!M36") -> 1 | AC11: =INDIRECT(csv_selection!$B$2 & csv_selection!$C$2 & "!M37") -> 1 | AD11: =INDIRECT(csv_selection!$B$2 & csv_selection!$C$2 & "!M38") -> 1 | AE11: =INDIRECT(csv_selection!$B$2 & csv_selection!$C$2 & "!M40") -> 0 | AF11: =INDIRECT(csv_selection!$B$2 & csv_selection!$C$2 & "!M41") -> 0 | AG11: =INDIRECT(csv_selection!$B$2 & csv_selection!$C$2 & "!M42") -> 0 | AH11: =INDIRECT(csv_selection!$B$2 & csv_selection!$C$2 & "!M43") -> 0 | AI11: =INDIRECT(csv_selection!$B$2 & csv_selection!$C$2 & "!M44") -> 0 | AJ11: =INDIRECT(csv_selection!$B$2 & csv_selection!$C$2 & "!M45") -> 0 | AK11: =INDIRECT(csv_selection!$B$2 & csv_selection!$C$2 & "!M46") -> 0 | AL11: =INDIRECT(csv_selection!$B$2 & csv_selection!$C$2 & "!M47") -> 0 | AM11: =INDIRECT(csv_selection!$B$2 & csv_selection!$C$2 & "!M50") -> CLaw_perm | AN11: =INDIRECT(csv_selection!$B$2 & csv_selection!$C$2 & "!M51") -> CLaw_perm | AO11: =INDIRECT(csv_selection!$B$2 & csv_selection!$C$2 & "!M52") -> CLaw_perm | AP11: =INDIRECT(csv_selection!$B$2 & csv_selection!$C$2 & "!M53") -> CLaw_perm | AQ11: =INDIRECT(csv_selection!$B$2 & csv_selection!$C$2 & "!M54") -> CLaw_perm | AR11: =INDIRECT(csv_selection!$B$2 & csv_selection!$C$2 & "!M55") -> CLaw_perm | AS11: =INDIRECT(csv_selection!$B$2 & csv_selection!$C$2 & "!M56") -> CLaw_perm | AT11: =INDIRECT(csv_selection!$B$2 & csv_selection!$C$2 & "!M58") -> Claw_perm | AU11: =INDIRECT(csv_selection!$B$2 & csv_selection!$C$2 & "!M59") -> CLaw_rduc | AV11: =INDIRECT(csv_selection!$B$2 & csv_selection!$C$2 & "!M61") -> CLaw_perm | AW11: =INDIRECT(csv_selection!$B$2 & csv_selection!$C$2 & "!M63") -> CLaw_perm | AX11: =INDIRECT(csv_selection!$B$2 & csv_selection!$C$2 & "!M64") -> CLaw_perm | AY11: =INDIRECT(csv_selection!$B$2 & csv_selection!$C$2 & "!M65") -> CLaw_perm | AZ11: =INDIRECT(csv_selection!$B$2 & csv_selection!$C$2 & "!M66") -> CLaw_perm | BA11: =INDIRECT(csv_selection!$B$2 & csv_selection!$C$2 & "!M67") -> CLaw_perm | BB11: =INDIRECT(csv_selection!$B$2 & csv_selection!$C$2 & "!M69") -> 0.6071 | BC11: =INDIRECT(csv_selection!$B$2 & csv_selection!$C$2 & "!M70") -> 0.0578 | BD11: =INDIRECT(csv_selection!$B$2 & csv_selection!$C$2 & "!M71") -> 0.3351 | BE11: =INDIRECT(csv_selection!$B$2 & csv_selection!$C$2 & "!M72") -> 0.6071 | BF11: =INDIRECT(csv_selection!$B$2 & csv_selection!$C$2 & "!M73") -> 0.0578 | BG11: =INDIRECT(csv_selection!$B$2 & csv_selection!$C$2 & "!M74") -> 0.3351 | BH11: =INDIRECT(csv_selection!$B$2 & csv_selection!$C$2 & "!M75") -> 1 | BI11: =INDIRECT(csv_selection!$B$2 & csv_selection!$C$2 & "!M76") -> 0 | BJ11: =INDIRECT(csv_selection!$B$2 & csv_selection!$C$2 & "!M77") -> 0 | BK11: =INDIRECT(csv_selection!$B$2 & csv_selection!$C$2 & "!M78") -> 0.6071 | BL11: =INDIRECT(csv_selection!$B$2 & csv_selection!$C$2 & "!M79") -> 0.0578 | BM11: =INDIRECT(csv_selection!$B$2 & csv_selection!$C$2 & "!M80") -> 0.3351 | BN11: =INDIRECT(csv_selection!$B$2 & csv_selection!$C$2 & "!M81") -> 1 | BO11: =INDIRECT(csv_selection!$B$2 & csv_selection!$C$2 & "!M82") -> 0 | BP11: =INDIRECT(csv_selection!$B$2 & csv_selection!$C$2 & "!M83") -> 0 | BQ11: =INDIRECT(csv_selection!$B$2 & csv_selection!$C$2 & "!M84") -> 0.6071 | BR11: =INDIRECT(csv_selection!$B$2 & csv_selection!$C$2 & "!M85") -> 0.0578 | BS11: =INDIRECT(csv_selection!$B$2 & csv_selection!$C$2 & "!M86") -> 0.3351
A12: =INDIRECT(csv_selection!$B$2 & csv_selection!$C$2 & "!N2") -> 2036 | B12: =INDIRECT(csv_selection!$B$2 & csv_selection!$C$2 & "!N5") -> 0.21 | C12: =INDIRECT(csv_selection!$B$2 & csv_selection!$C$2 & "!N6") -> 0.2787 | D12: =INDIRECT(csv_selection!$B$2 & csv_selection!$C$2 & "!N7") -> 0.0353 | E12: =INDIRECT(csv_selection!$B$2 & csv_selection!$C$2 & "!N8") -> 0.01 | F12: =INDIRECT(csv_selection!$B$2 & csv_selection!$C$2 & "!N9") -> 0 | G12: =INDIRECT(csv_selection!$B$2 & csv_selection!$C$2 & "!N11") -> 0.2054 | H12: =INDIRECT(csv_selection!$B$2 & csv_selection!$C$2 & "!N12") -> 0.2787 | I12: =INDIRECT(csv_selection!$B$2 & csv_selection!$C$2 & "!N13") -> 0.2054 | J12: =INDIRECT(csv_selection!$B$2 & csv_selection!$C$2 & "!N14") -> 0 | K12: =INDIRECT(csv_selection!$B$2 & csv_selection!$C$2 & "!N15") -> 0.2787 | L12: =INDIRECT(csv_selection!$B$2 & csv_selection!$C$2 & "!N16") -> 0.2787 | M12: =INDIRECT(csv_selection!$B$2 & csv_selection!$C$2 & "!N17") -> 0.2787 | N12: =INDIRECT(csv_selection!$B$2 & csv_selection!$C$2 & "!N18") -> 0 | O12: =INDIRECT(csv_selection!$B$2 & csv_selection!$C$2 & "!N20") -> 0.2787 | P12: =INDIRECT(csv_selection!$B$2 & csv_selection!$C$2 & "!N21") -> 0.2787 | Q12: =INDIRECT(csv_selection!$B$2 & csv_selection!$C$2 & "!N23") -> 0.2896 | R12: =INDIRECT(csv_selection!$B$2 & csv_selection!$C$2 & "!N24") -> 0.773 | S12: =INDIRECT(csv_selection!$B$2 & csv_selection!$C$2 & "!N25") -> 0.9753 | T12: =INDIRECT(csv_selection!$B$2 & csv_selection!$C$2 & "!N26") -> 0.9753 | U12: =INDIRECT(csv_selection!$B$2 & csv_selection!$C$2 & "!N27") -> 0.6253 | V12: =INDIRECT(csv_selection!$B$2 & csv_selection!$C$2 & "!N28") -> 0.0365 | W12: =INDIRECT(csv_selection!$B$2 & csv_selection!$C$2 & "!N31") -> 1 | X12: =INDIRECT(csv_selection!$B$2 & csv_selection!$C$2 & "!N32") -> 1 | Y12: =INDIRECT(csv_selection!$B$2 & csv_selection!$C$2 & "!N33") -> 1 | Z12: =INDIRECT(csv_selection!$B$2 & csv_selection!$C$2 & "!N34") -> 1 | AA12: =INDIRECT(csv_selection!$B$2 & csv_selection!$C$2 & "!N35") -> 1 | AB12: =INDIRECT(csv_selection!$B$2 & csv_selection!$C$2 & "!N36") -> 1 | AC12: =INDIRECT(csv_selection!$B$2 & csv_selection!$C$2 & "!N37") -> 1 | AD12: =INDIRECT(csv_selection!$B$2 & csv_selection!$C$2 & "!N38") -> 1 | AE12: =INDIRECT(csv_selection!$B$2 & csv_selection!$C$2 & "!N40") -> 0 | AF12: =INDIRECT(csv_selection!$B$2 & csv_selection!$C$2 & "!N41") -> 0 | AG12: =INDIRECT(csv_selection!$B$2 & csv_selection!$C$2 & "!N42") -> 0 | AH12: =INDIRECT(csv_selection!$B$2 & csv_selection!$C$2 & "!N43") -> 0 | AI12: =INDIRECT(csv_selection!$B$2 & csv_selection!$C$2 & "!N44") -> 0 | AJ12: =INDIRECT(csv_selection!$B$2 & csv_selection!$C$2 & "!N45") -> 0 | AK12: =INDIRECT(csv_selection!$B$2 & csv_selection!$C$2 & "!N46") -> 0 | AL12: =INDIRECT(csv_selection!$B$2 & csv_selection!$C$2 & "!N47") -> 0 | AM12: =INDIRECT(csv_selection!$B$2 & csv_selection!$C$2 & "!N50") -> CLaw_perm | AN12: =INDIRECT(csv_selection!$B$2 & csv_selection!$C$2 & "!N51") -> CLaw_perm | AO12: =INDIRECT(csv_selection!$B$2 & csv_selection!$C$2 & "!N52") -> CLaw_perm | AP12: =INDIRECT(csv_selection!$B$2 & csv_selection!$C$2 & "!N53") -> CLaw_perm | AQ12: =INDIRECT(csv_selection!$B$2 & csv_selection!$C$2 & "!N54") -> CLaw_perm | AR12: =INDIRECT(csv_selection!$B$2 & csv_selection!$C$2 & "!N55") -> CLaw_perm | AS12: =INDIRECT(csv_selection!$B$2 & csv_selection!$C$2 & "!N56") -> CLaw_perm | AT12: =INDIRECT(csv_selection!$B$2 & csv_selection!$C$2 & "!N58") -> Claw_perm | AU12: =INDIRECT(csv_selection!$B$2 & csv_selection!$C$2 & "!N59") -> CLaw_rduc | AV12: =INDIRECT(csv_selection!$B$2 & csv_selection!$C$2 & "!N61") -> CLaw_perm | AW12: =INDIRECT(csv_selection!$B$2 & csv_selection!$C$2 & "!N63") -> CLaw_perm | AX12: =INDIRECT(csv_selection!$B$2 & csv_selection!$C$2 & "!N64") -> CLaw_perm | AY12: =INDIRECT(csv_selection!$B$2 & csv_selection!$C$2 & "!N65") -> CLaw_perm | AZ12: =INDIRECT(csv_selection!$B$2 & csv_selection!$C$2 & "!N66") -> CLaw_perm | BA12: =INDIRECT(csv_selection!$B$2 & csv_selection!$C$2 & "!N67") -> CLaw_perm | BB12: =INDIRECT(csv_selection!$B$2 & csv_selection!$C$2 & "!N69") -> 0.6076 | BC12: =INDIRECT(csv_selection!$B$2 & csv_selection!$C$2 & "!N70") -> 0.0578 | BD12: =INDIRECT(csv_selection!$B$2 & csv_selection!$C$2 & "!N71") -> 0.3346 | BE12: =INDIRECT(csv_selection!$B$2 & csv_selection!$C$2 & "!N72") -> 0.6076 | BF12: =INDIRECT(csv_selection!$B$2 & csv_selection!$C$2 & "!N73") -> 0.0578 | BG12: =INDIRECT(csv_selection!$B$2 & csv_selection!$C$2 & "!N74") -> 0.3346 | BH12: =INDIRECT(csv_selection!$B$2 & csv_selection!$C$2 & "!N75") -> 1 | BI12: =INDIRECT(csv_selection!$B$2 & csv_selection!$C$2 & "!N76") -> 0 | BJ12: =INDIRECT(csv_selection!$B$2 & csv_selection!$C$2 & "!N77") -> 0 | BK12: =INDIRECT(csv_selection!$B$2 & csv_selection!$C$2 & "!N78") -> 0.6076 | BL12: =INDIRECT(csv_selection!$B$2 & csv_selection!$C$2 & "!N79") -> 0.0578 | BM12: =INDIRECT(csv_selection!$B$2 & csv_selection!$C$2 & "!N80") -> 0.3346 | BN12: =INDIRECT(csv_selection!$B$2 & csv_selection!$C$2 & "!N81") -> 1 | BO12: =INDIRECT(csv_selection!$B$2 & csv_selection!$C$2 & "!N82") -> 0 | BP12: =INDIRECT(csv_selection!$B$2 & csv_selection!$C$2 & "!N83") -> 0 | BQ12: =INDIRECT(csv_selection!$B$2 & csv_selection!$C$2 & "!N84") -> 0.6076 | BR12: =INDIRECT(csv_selection!$B$2 & csv_selection!$C$2 & "!N85") -> 0.0578 | BS12: =INDIRECT(csv_selection!$B$2 & csv_selection!$C$2 & "!N86") -> 0.3346

Sheet Readme_Part_2
A1: Part 2: Parameters defining depreciation rules, investment tax credit rules, and marginal tax rate adjustments
B3: A. Introduction
C4: Parameters in Part 2 define the rules for recovering investment costs and adjusting marginal tax rates. Typically, they do not vary by year. When they do, separate sheets are provided to accommodate each unique year. The sheets are organized into four groups, each of which has unique characteristics which are explained, along with the list of sheets provided, in their own Readme files, as follows:
C6: ▪ | D6: Part 2.1--Cost recovery deduction parameters
D7: ▫ | E7: Part 2.1.1--Multiyear depreciation
D8: ▫ | E8: Part 2.1.2--Expensing
C9: ▪ | D9: Part 2.2--Investment tax credit parameters
C10: ▪ | D10: Part 2.3--Production tax credit parameters
C11: ▪ | D11: Part 2.4--Marginal tax rate adjustment parameters
C13: Nevertheless, there are several conventions that are common to all four groups. For example, there are certain conventions for naming worksheets.
C14: ▪ | D14: To read about the Part 2 conventions for naming worksheets, click here
C16: To avoid having to enter parameter values into each cell separately, Most cells reference either a row default or a column default. Color coding is used to identify which default is being referenced.
C17: ▪ | D17: To read about the color-coding, click here
C19: As in Part 1, some parameter values should differ depending on the analytical perspective.
C20: ▪ | D20: For guidance on how to make parameter values consistent with the uniformity perspective, click here.
C22: Finally, the same procedure for creating .csv files applies to all sheets in Part 2.
C23: ▪ | D23: For guidance on how to create alternative .csv files for Part 2 parameters, click here.
B25: B. Part 2 worksheet naming conventions
C27: All sheets in Part 2 that contain parameter values follow a simple naming convention—a descriptive name that the model recognizes and which should not be changed (these are listed in the group-specific Readme files), followed by an underscore and a 9 character suffix. In the sheets being supplied, that suffix consists of the following:
C29: ▪ | D29: Four characters representing the law or proposal being simulated. The sheets being supplied all represent current law, which CBO abbreviates as CLaw to accommodate this format. When current law differs by organizational form, CBO uses CLCC and CLPT as abbreviations for “current law, C corporations” and “current law, pass-throughs” respectively.
C30: ▪ | D30: An underscore.
C31: ▪ | D31: Four more characters representing the time period covered by the parameter values. If the parameter values apply in a single year, CBO uses the four-digit year in this spot. If the parameters values apply in multiple years, CBO uses perm (for “permanent”) if the multi-year period extends indefinitely into the future, temp (for “temporary”) if the parameter values apply in 2026 but expire at some point, and the four-digit year of when parameter values changed if the multi-year period expires at some point and is replaced by another multi-year period which also expires at some point. For itc_nondeprcbl_bases, the file is labelled rduc (consistent with a reduced R&E Credit and full cost recovery deductions).
C33: That suffix format is not mandatory. When you create a new sheet, you can use whatever nine characters you want. If you use more than nine characters, however, you risk having Excel truncate the suffix. When you create new sheets with new parameter values in Part 2, you tell Part 1 when to use them by entering the suffixes of those sheets into the appropriate cells (in rows 49-67) of a policy_parameters.suffix sheet. Remember that you have to do that twice--once for the comprehensive perspective and once for the uniformity perspective.
B35: C. Guide to color-coding in Part 2 worksheets
C37: All sheets in Parts 2.1, 2.2 and 2.3 have color-coded cells to facilitate the crosswalk between Publication 946 and the matrix cells. The codes are as follows:
G39: Cell value is user-supplied. It becomes the default value for the asset type (column)
G40: Cell value is formula-driven. It references the default asset type (column) value.
G42: Cell value is user-supplied. It becomes the default value for the industry (row)
G43: Cell value is formula-driven. It references the default industry (row) value.
G45: Cell value is user-supplied. It overrides both the asset type and industry defaults.
C47: Sheets in Part 2.4 are also color-coded. However, the matrices in that section are unidimensional and use only column defaults (and the associated colors), regardless of whether the dimension is asset type or industry.
B49: D. How to estimate parameter values that are consistent with the uniformity perspective
C51: The uniformity perspective is intended to illuminate differences in tax treatment among different industries, asset types, legal forms of organization, and sources of financing. Under the comprehensive perspective, however, some parameter values differ for other reasons. Among Part 2 parameters, the sheets supplied for Section 179 expensing (sec_179_expens_shares_) fall into that category.
C53: The limitations on the use of Section 179 are a function of the amount of investment. Based on their relatively smaller average investment amounts, more investment by pass-through entities than by C corporations qualifies for Section 179 expensing. Similarly, average investment size, and thus eligibility for Section 179, also vary by industry. Thus, under the comprehensive perspective, the expensible share under Section 179 should vary by industry and organizational form. (The table below shows the range within which the industry values fall for each organizational form.) Those differences, however, do not reflect explicitly different treatment of industries and organizational forms under the tax code—they reflect other characteristics of the industries and organizational forms. Thus, under the uniformity perspective, a single expensible share should apply to all industries and organizational forms. CBO calculated an average share using each organizational form’s share of total investment as the weights. The ineligibility of certain asset types for Section 179 expensing should be retained under the uniformity perspective because it reflects explicit distinctions made in the tax law.
G55: Legal form of organization | I55: 2026 values under the comprehensive perspective | K55: 2026 value under the uniformity perspective
G56: C Corporations-eligible types | I56: 0.0034 - 0.6173 | K56: 0.0844
G57: Pass-throughs-eligible types | I57: 0.0248 - 0.6657 | K57: 0.0844
G58: Ineligible asset types | I58: 0 | K58: 0
B60: E. How to create alternative csv files for Part 2 parameters
B62: 1. | C62: Copy an existing sheet and give it the suffix you want it to have.
B63: 2. | C63: Decide if you want to change any of the references to default values or change a formula-driven cell to a user-supplied cell. If so, select one of the three cells below and copy it into the cells you want to change. (This should happen only if there is a major rewrite of Publication 946.)
C65: Select this cell if you want to change to using an asset-type (column) default)>>>>>>> | M65: =M$2 -> 0
C66: Select this cell if you want to change to using an industry (row) default)>>>>>>>>>>>> | M66: =$B66 -> 0
C67: Select this cell if you want to change to a user-supplied value>>>>>>>>>>>>>>>>>>>>
B69: 3. | C69: Enter the desired parameter values into the user-supplied (green and dark-blue) cells.
B70: 4. | C70: Repeat Steps 1-3 for as many Part 2 sheets as you want to change.
B71: 5. | C71: For every year you want to use the new matrices, enter the suffixes chosen in Step 1 into the corresponding cells of lines 49-67 of two policy_parameters.suffix sheets--one containing values consistent with the comprehensive perspective and one containing value consistent with the uniformity perspective.
B72: 6. | C72: Save the workbook as an Excel file.
B73: 7. | C73: Save the new sheets to .csv files using the following steps for each:
C74: a. | D74: Click on 'Save As', then navigate to one of the following subfolders:
D75: i. | E75: For Part 2.1.x, \captax\captax\data\inputs\policy_parameters\depreciation_adjustments
D76: ii. | E76: For Part 2.2, \captax\captax\data\inputs\policy_parameters\investment_tax_credit_adjustments
D77: iii. | E77: For Part 2.3, \captax\captax\data\inputs\policy_parameters\production_tax_credit_adjustments
D78: iv. | E78: For Part 2.4, \captax\captax\data\inputs\policy_parameters\tax_rate_adjustments
C79: b. | D79: In the 'Save as type' box, select 'CSV (comma delimited)'.
C80: c. | D80: From the list of files in the folder, select a file with the same generic name (ignoring the 9-digit suffix), but do not click 'Save'.
C81: d. | D81: Replace the suffix of the file in the 'File name' box with a new suffix. It you are using Part 1 to create csv files for policy parameters, you must use the 9 character suffix assigned in Step 1. If you are not using Part 1 to create csv files, then you can use any suffix you want in this step.
C82: e. | D82: Click 'Save'.
B83: 8. | C83: Close the workbook without saving the changes in Step 7.

Sheet Readme_Part_2.1.1
A1: Part 2.1.1: Multiyear depreciation parameter sheets provided
C3: Multiyear depreciation rules are determined by four parameter matrices. The dimensions of the matrices are asset types (horizontal) and detailed industry (vertical). The industry dimension is more detailed than the industries that appear in the output because the additional detail is needed to more fully capture the tax law. Although the tax law allows some discretion in selecting a depreciation method, CBO assigned the most advantageous method available to each cell.
C5: The names of the four matrices and the suffixes of the sheets being supplied are as follows:
B7: · recovery_periods_
C8: The values in this matrix correspond, to the extent possible, to those found in the GDS(MACRS) column of Tables B-1 and B-2 of IRS Publication 946.
D9: CLaw_perm | E9: is the only suffix supplied.
B11: · acceleration_rates_
C12: The values in this matrix are statutorily linked to those in recovery_periods_ as explained in Table 4-1 of Publication 946. Use 2.0 for 200% declining balance, 1.5 for 150% declining balance, and 1.0 for 100% declining balance (not used under current law, but available for simulating economic depreciation) or straight-line depreciation.
D13: CLaw_perm | E13: is the only suffix supplied.
B15: · straight_line_flag_
C16: The values in this matrix can take on one of three values: 1 to switch to straight line depreciation when it is more advantageous than continuing with declining balance depreciation, -1 to conform tax depreciation to economic depreciation, and 0 otherwise.
D17: CLaw_perm, | E17: which contains values of 1 except in the inventories column, is the only suffix supplied.
B19: · inflation_adjustments_
C20: The values in this matrix range between 0.0 and 1.0, signalling the extent to which the undepreciated basis should be indexed for inflation. Use 1.0 for economic depreciation.
D21: CLaw_perm | E21: is the only suffix supplied. That sheet contains values of 0.0 except for inventories (0.5 to account for the use of the last-in-first-out accounting method) and entertainment, artistic, and literary originals (1.0 to simulate the income forecast method of depreciation).
B23: Following these sheets is a sheet labelled IRS asset class mapping. That sheet contains no parameter values. Instead, it serves as documentation for how CBO translated Publication 946 (and, where applicable, Internal Revenue Code sections not covered by Publication 946) into parameters that are used in the model. In general, Table B-1 is the source of the asset-type (column) defaults and Table B-2 is the source of the industry (row) defaults.
B24: · IRS asset class mapping

Sheet recovery_periods_CLaw_perm
A1: Recovery period | B1: Default value for industry | C1: Computers and peripheral equipment | D1: Communication equipment | E1: Nonelectronic medical instruments | F1: Electronic medical instruments | G1: Nonmedical instruments | H1: Photocopy and related equipment | I1: Office and accounting equipment | J1: Nuclear fuel | K1: Other fabricated metal products | L1: Steam engines | M1: Internal combustion engines | N1: Metalworking machinery | O1: Special industrial machinery, n.e.c. | P1: General industrial equipment | Q1: Electric transmission, distribution and industrial apparatus | R1: Light trucks (including utility vehicles) | S1: Other trucks, buses, and truck trailers | T1: Autos | U1: Aircraft | V1: Ships and boats | W1: Railroad equipment | X1: Household furniture | Y1: Other furniture and fixtures | Z1: Other agricultural machinery | AA1: Farm tractors | AB1: Other construction machinery | AC1: Construction tractors | AD1: Mining and oilfield machinery | AE1: Service industry machinery | AF1: Household appliances | AG1: Other electrical equipment, n.e.c | AH1: Other nonresidential equipment | AI1: Office and medical buildings | AJ1: Hospitals and special care facilities | AK1: Warehouses | AL1: Mobile structures | AM1: Other commercial buildings | AN1: Manufacturing buildings | AO1: Regulated electric power structures | AP1: Unregulated electric power structures | AQ1: Regulated wind and solar power structures | AR1: Unregulated wind and solar power structures | AS1: Gas power structures | AT1: Petroleum pipelines | AU1: Communication structures | AV1: Depreciable petroleum and natural gas structures | AW1: Depreciable mining structures | AX1: Religious buildings | AY1: Educational and vocational buildings | AZ1: Lodging buildings | BA1: Amusement and recreation buildings | BB1: Track replacement | BC1: Other railroad structures | BD1: Other transportation structures | BE1: Farm buildings | BF1: Water supply and sewer and waste disposal facilities | BG1: Public safety, highways, conservation, and development | BH1: Oil and gas exploration (geological and geophysical)--integrated | BI1: Oil and gas exploration (geological and geophysical)--independent | BJ1: Oil and gas development (intangible drilling costs)--integrated | BK1: Oil and gas development (intangible drilling costs)--independent | BL1: Other mineral exploration--C corps | BM1: Other mineral exploration--pass-throughs | BN1: Other mineral development--C corps | BO1: Other mineral development--pass-throughs | BP1: Prepackaged software | BQ1: Custom software | BR1: Credit-eligible own account software | BS1: Other own-account software | BT1: Credit-eligible research and development | BU1: Other research and development | BV1: Theatrical movies | BW1: Long-lived television programs | BX1: Books | BY1: Music | BZ1: Other entertainment originals | CA1: Reserved for non-BEA intangibles | CB1: Reserved for non-BEA intangibles | CC1: Residential equipment | CD1: Residential buildings | CE1: Inventories | CF1: Land | CG1: Reserved for non-BEA natural resources | CH1: Reserved for non-BEA natural resources | CI1: Reserved for non-BEA natural resources
A2: Default value for type of asset | C2: 5 | D2: 7 | H2: 5 | I2: 5 | J2: 5 | L2: 15 | Q2: 15 | R2: 5 | S2: 5 | T2: 5 | U2: 5 | V2: 10 | W2: 7 | Y2: 7 | AI2: 39 | AJ2: 39 | AK2: 39 | AL2: 7 | AM2: 39 | AN2: 39 | AO2: 20 | AP2: 20 | AQ2: 5 | AR2: 5 | AS2: 20 | AT2: 15 | AU2: 15 | AV2: 7 | AW2: 7 | AX2: 39 | AY2: 39 | AZ2: 39 | BA2: 39 | BB2: 7 | BC2: 20 | BD2: 39 | BE2: 20 | BF2: 25 | BG2: 15 | BH2: 7 | BI2: 2 | BJ2: 5 | BK2: 1 | BL2: 10 | BM2: 10 | BN2: 5 | BO2: 1 | BP2: 3 | BQ2: 3 | BR2: 1 | BS2: 1 | BT2: 1 | BU2: 1 | BV2: 10 | BW2: 10 | BX2: 10 | BY2: 10 | BZ2: 10 | CC2: 5 | CD2: 27.5 | CE2: 0 | CF2: 100000
A3: Farms | B3: 5 | C3: =C$2 -> 5 | D3: =D$2 -> 7 | E3: =$B3 -> 5 | F3: =$B3 -> 5 | G3: =$B3 -> 5 | H3: =H$2 -> 5 | I3: =I$2 -> 5 | J3: =J$2 -> 5 | K3: =$B3 -> 5 | L3: =L$2 -> 15 | M3: =$B3 -> 5 | N3: =$B3 -> 5 | O3: =$B3 -> 5 | P3: =$B3 -> 5 | Q3: =Q$2 -> 15 | R3: =R$2 -> 5 | S3: =S$2 -> 5 | T3: =T$2 -> 5 | U3: =U$2 -> 5 | V3: =V$2 -> 10 | W3: =W$2 -> 7 | X3: =$B3 -> 5 | Y3: =Y$2 -> 7 | Z3: =$B3 -> 5 | AA3: =$B3 -> 5 | AB3: =$B3 -> 5 | AC3: =$B3 -> 5 | AD3: =$B3 -> 5 | AE3: =$B3 -> 5 | AF3: =$B3 -> 5 | AG3: =$B3 -> 5 | AH3: =$B3 -> 5 | AI3: =AI$2 -> 39 | AJ3: =AJ$2 -> 39 | AK3: =AK$2 -> 39 | AL3: =AL$2 -> 7 | AM3: =AM$2 -> 39 | AN3: =AN$2 -> 39 | AO3: =AO$2 -> 20 | AP3: =AP$2 -> 20 | ... CI3: =CI$2 -> 0
A4: Forestry,_Fishing,_and_Related_Activites | B4: 7 | C4: =C$2 -> 5 | D4: =D$2 -> 7 | E4: =$B4 -> 7 | F4: =$B4 -> 7 | G4: =$B4 -> 7 | H4: =H$2 -> 5 | I4: =I$2 -> 5 | J4: =J$2 -> 5 | K4: =$B4 -> 7 | L4: =L$2 -> 15 | M4: =$B4 -> 7 | N4: =$B4 -> 7 | O4: =$B4 -> 7 | P4: =$B4 -> 7 | Q4: =Q$2 -> 15 | R4: =R$2 -> 5 | S4: =S$2 -> 5 | T4: =T$2 -> 5 | U4: =U$2 -> 5 | V4: =V$2 -> 10 | W4: =W$2 -> 7 | X4: =$B4 -> 7 | Y4: =Y$2 -> 7 | Z4: =$B4 -> 7 | AA4: =$B4 -> 7 | AB4: =$B4 -> 7 | AC4: =$B4 -> 7 | AD4: =$B4 -> 7 | AE4: =$B4 -> 7 | AF4: =$B4 -> 7 | AG4: =$B4 -> 7 | AH4: =$B4 -> 7 | AI4: =AI$2 -> 39 | AJ4: =AJ$2 -> 39 | AK4: =AK$2 -> 39 | AL4: =AL$2 -> 7 | AM4: =AM$2 -> 39 | AN4: =AN$2 -> 39 | AO4: =AO$2 -> 20 | AP4: =AP$2 -> 20 | ... CI4: =CI$2 -> 0
A5: Oil_and_Gas_Extraction | B5: 7 | C5: =C$2 -> 5 | D5: =D$2 -> 7 | E5: =$B5 -> 7 | F5: =$B5 -> 7 | G5: =$B5 -> 7 | H5: =H$2 -> 5 | I5: =I$2 -> 5 | J5: =J$2 -> 5 | K5: =$B5 -> 7 | L5: =L$2 -> 15 | M5: =$B5 -> 7 | N5: =$B5 -> 7 | O5: =$B5 -> 7 | P5: =$B5 -> 7 | Q5: =Q$2 -> 15 | R5: =R$2 -> 5 | S5: =S$2 -> 5 | T5: =T$2 -> 5 | U5: =U$2 -> 5 | V5: =V$2 -> 10 | W5: =W$2 -> 7 | X5: =$B5 -> 7 | Y5: =Y$2 -> 7 | Z5: =$B5 -> 7 | AA5: =$B5 -> 7 | AB5: =$B5 -> 7 | AC5: =$B5 -> 7 | AD5: =$B5 -> 7 | AE5: =$B5 -> 7 | AF5: =$B5 -> 7 | AG5: =$B5 -> 7 | AH5: =$B5 -> 7 | AI5: =AI$2 -> 39 | AJ5: =AJ$2 -> 39 | AK5: =AK$2 -> 39 | AL5: =AL$2 -> 7 | AM5: =AM$2 -> 39 | AN5: =AN$2 -> 39 | AO5: =AO$2 -> 20 | AP5: =AP$2 -> 20 | ... AS5: =AS$2 -> 20 | AT5: =$B5 -> 7 | AU5: =AU$2 -> 15 | AV5: =AV$2 -> 7 | AW5: =AW$2 -> 7 | AX5: =AX$2 -> 39 | AY5: =AY$2 -> 39 | AZ5: =AZ$2 -> 39 | BA5: =BA$2 -> 39 | BB5: =BB$2 -> 7 | ... CI5: =CI$2 -> 0
A6: Mining_(Except_Oil_and_Gas) | B6: 7 | C6: =C$2 -> 5 | D6: =D$2 -> 7 | E6: =$B6 -> 7 | F6: =$B6 -> 7 | G6: =$B6 -> 7 | H6: =H$2 -> 5 | I6: =I$2 -> 5 | J6: =J$2 -> 5 | K6: =$B6 -> 7 | L6: =L$2 -> 15 | M6: =$B6 -> 7 | N6: =$B6 -> 7 | O6: =$B6 -> 7 | P6: =$B6 -> 7 | Q6: =Q$2 -> 15 | R6: =R$2 -> 5 | S6: =S$2 -> 5 | T6: =T$2 -> 5 | U6: =U$2 -> 5 | V6: =V$2 -> 10 | W6: =W$2 -> 7 | X6: =$B6 -> 7 | Y6: =Y$2 -> 7 | Z6: =$B6 -> 7 | AA6: =$B6 -> 7 | AB6: =$B6 -> 7 | AC6: =$B6 -> 7 | AD6: =$B6 -> 7 | AE6: =$B6 -> 7 | AF6: =$B6 -> 7 | AG6: =$B6 -> 7 | AH6: =$B6 -> 7 | AI6: =AI$2 -> 39 | AJ6: =AJ$2 -> 39 | AK6: =AK$2 -> 39 | AL6: =AL$2 -> 7 | AM6: =AM$2 -> 39 | AN6: =AN$2 -> 39 | AO6: =AO$2 -> 20 | AP6: =AP$2 -> 20 | ... CI6: =CI$2 -> 0
A7: Support_Activities_For_Mining | B7: 5 | C7: =C$2 -> 5 | D7: =D$2 -> 7 | E7: =$B7 -> 5 | F7: =$B7 -> 5 | G7: =$B7 -> 5 | H7: =H$2 -> 5 | I7: =I$2 -> 5 | J7: =J$2 -> 5 | K7: =$B7 -> 5 | L7: =L$2 -> 15 | M7: =$B7 -> 5 | N7: =$B7 -> 5 | O7: =$B7 -> 5 | P7: =$B7 -> 5 | Q7: =Q$2 -> 15 | R7: =R$2 -> 5 | S7: =S$2 -> 5 | T7: =T$2 -> 5 | U7: =U$2 -> 5 | V7: =$B7 -> 5 | W7: =W$2 -> 7 | X7: =$B7 -> 5 | Y7: =Y$2 -> 7 | Z7: =$B7 -> 5 | AA7: =$B7 -> 5 | AB7: =$B7 -> 5 | AC7: =$B7 -> 5 | AD7: =$B7 -> 5 | AE7: =$B7 -> 5 | AF7: =$B7 -> 5 | AG7: =$B7 -> 5 | AH7: =$B7 -> 5 | AI7: =AI$2 -> 39 | AJ7: =AJ$2 -> 39 | AK7: =AK$2 -> 39 | AL7: =AL$2 -> 7 | AM7: =AM$2 -> 39 | AN7: =AN$2 -> 39 | AO7: =$B7 -> 5 | AP7: =$B7 -> 5 | AQ7: =AQ$2 -> 5 | AR7: =AR$2 -> 5 | AS7: =$B7 -> 5 | AT7: =$B7 -> 5 | AU7: =AU$2 -> 15 | AV7: =$B7 -> 5 | AW7: =$B7 -> 5 | AX7: =AX$2 -> 39 | AY7: =AY$2 -> 39 | AZ7: =AZ$2 -> 39 | BA7: =BA$2 -> 39 | BB7: =BB$2 -> 7 | BC7: =BC$2 -> 20 | BD7: =BD$2 -> 39 | BE7: =BE$2 -> 20 | ... CI7: =CI$2 -> 0
A8: Hydroelectric_Power_Generation | B8: 20 | C8: =C$2 -> 5 | D8: =D$2 -> 7 | E8: =$B8 -> 20 | F8: =$B8 -> 20 | G8: =$B8 -> 20 | H8: =H$2 -> 5 | I8: =I$2 -> 5 | J8: =J$2 -> 5 | K8: =$B8 -> 20 | L8: =L$2 -> 15 | M8: =$B8 -> 20 | N8: =$B8 -> 20 | O8: =$B8 -> 20 | P8: =$B8 -> 20 | Q8: =Q$2 -> 15 | R8: =R$2 -> 5 | S8: =S$2 -> 5 | T8: =T$2 -> 5 | U8: =U$2 -> 5 | V8: =V$2 -> 10 | W8: =W$2 -> 7 | X8: =$B8 -> 20 | Y8: =Y$2 -> 7 | Z8: =$B8 -> 20 | AA8: =$B8 -> 20 | AB8: =$B8 -> 20 | AC8: =$B8 -> 20 | AD8: =$B8 -> 20 | AE8: =$B8 -> 20 | AF8: =$B8 -> 20 | AG8: =$B8 -> 20 | AH8: =$B8 -> 20 | AI8: =AI$2 -> 39 | AJ8: =AJ$2 -> 39 | AK8: =AK$2 -> 39 | AL8: =AL$2 -> 7 | AM8: =AM$2 -> 39 | AN8: =AN$2 -> 39 | AO8: =$B8 -> 20 | AP8: =$B8 -> 20 | AQ8: =AQ$2 -> 5 | AR8: =AR$2 -> 5 | AS8: =AS$2 -> 20 | AT8: =AT$2 -> 15 | AU8: =AU$2 -> 15 | AV8: =AV$2 -> 7 | AW8: =AW$2 -> 7 | AX8: =AX$2 -> 39 | ... BF8: =BF$2 -> 25 | BG8: =$B8 -> 20 | BH8: =BH$2 -> 7 | BI8: =BI$2 -> 2 | BJ8: =BJ$2 -> 5 | BK8: =BK$2 -> 1 | BL8: =BL$2 -> 10 | BM8: =BM$2 -> 10 | BN8: =BN$2 -> 5 | BO8: =BO$2 -> 1 | ... CI8: =CI$2 -> 0
A9: Nuclear_Electric_Power_Generation | B9: 15 | C9: =C$2 -> 5 | D9: =D$2 -> 7 | E9: =$B9 -> 15 | F9: =$B9 -> 15 | G9: =$B9 -> 15 | H9: =H$2 -> 5 | I9: =I$2 -> 5 | J9: =J$2 -> 5 | K9: =$B9 -> 15 | L9: =L$2 -> 15 | M9: =$B9 -> 15 | N9: =$B9 -> 15 | O9: =$B9 -> 15 | P9: =$B9 -> 15 | Q9: =Q$2 -> 15 | R9: =R$2 -> 5 | S9: =S$2 -> 5 | T9: =T$2 -> 5 | U9: =U$2 -> 5 | V9: =V$2 -> 10 | W9: =W$2 -> 7 | X9: =$B9 -> 15 | Y9: =Y$2 -> 7 | Z9: =$B9 -> 15 | AA9: =$B9 -> 15 | AB9: =$B9 -> 15 | AC9: =$B9 -> 15 | AD9: =$B9 -> 15 | AE9: =$B9 -> 15 | AF9: =$B9 -> 15 | AG9: =$B9 -> 15 | AH9: =$B9 -> 15 | AI9: =AI$2 -> 39 | AJ9: =AJ$2 -> 39 | AK9: =AK$2 -> 39 | AL9: =AL$2 -> 7 | AM9: =AM$2 -> 39 | AN9: =AN$2 -> 39 | AO9: =$B9 -> 15 | AP9: =$B9 -> 15 | AQ9: =AQ$2 -> 5 | AR9: =AR$2 -> 5 | AS9: =AS$2 -> 20 | AT9: =AT$2 -> 15 | AU9: =AU$2 -> 15 | AV9: =AV$2 -> 7 | AW9: =AW$2 -> 7 | AX9: =AX$2 -> 39 | ... BF9: =BF$2 -> 25 | BG9: =$B9 -> 15 | BH9: =BH$2 -> 7 | BI9: =BI$2 -> 2 | BJ9: =BJ$2 -> 5 | BK9: =BK$2 -> 1 | BL9: =BL$2 -> 10 | BM9: =BM$2 -> 10 | BN9: =BN$2 -> 5 | BO9: =BO$2 -> 1 | ... CI9: =CI$2 -> 0
A10: Fossil_Fuel_Electric_Power_Generation,_Steam_and_Combined_Cycle | B10: 20 | C10: =C$2 -> 5 | D10: =D$2 -> 7 | E10: =$B10 -> 20 | F10: =$B10 -> 20 | G10: =$B10 -> 20 | H10: =H$2 -> 5 | I10: =I$2 -> 5 | J10: =J$2 -> 5 | K10: =$B10 -> 20 | L10: =L$2 -> 15 | M10: =$B10 -> 20 | N10: =$B10 -> 20 | O10: =$B10 -> 20 | P10: =$B10 -> 20 | Q10: =Q$2 -> 15 | R10: =R$2 -> 5 | S10: =S$2 -> 5 | T10: =T$2 -> 5 | U10: =U$2 -> 5 | V10: =V$2 -> 10 | W10: =W$2 -> 7 | X10: =$B10 -> 20 | Y10: =Y$2 -> 7 | Z10: =$B10 -> 20 | AA10: =$B10 -> 20 | AB10: =$B10 -> 20 | AC10: =$B10 -> 20 | AD10: =$B10 -> 20 | AE10: =$B10 -> 20 | AF10: =$B10 -> 20 | AG10: =$B10 -> 20 | AH10: =$B10 -> 20 | AI10: =AI$2 -> 39 | AJ10: =AJ$2 -> 39 | AK10: =AK$2 -> 39 | AL10: =AL$2 -> 7 | AM10: =AM$2 -> 39 | AN10: =AN$2 -> 39 | AO10: =$B10 -> 20 | AP10: =$B10 -> 20 | AQ10: =AQ$2 -> 5 | AR10: =AR$2 -> 5 | AS10: =AS$2 -> 20 | AT10: =AT$2 -> 15 | AU10: =AU$2 -> 15 | AV10: =AV$2 -> 7 | AW10: =AW$2 -> 7 | AX10: =AX$2 -> 39 | ... BF10: =BF$2 -> 25 | BG10: =$B10 -> 20 | BH10: =BH$2 -> 7 | BI10: =BI$2 -> 2 | BJ10: =BJ$2 -> 5 | BK10: =BK$2 -> 1 | BL10: =BL$2 -> 10 | BM10: =BM$2 -> 10 | BN10: =BN$2 -> 5 | BO10: =BO$2 -> 1 | ... CI10: =CI$2 -> 0
A11: Fossil_Fuel_Electric_Power_Generation,_Combustion | B11: 15 | C11: =C$2 -> 5 | D11: =D$2 -> 7 | E11: =$B11 -> 15 | F11: =$B11 -> 15 | G11: =$B11 -> 15 | H11: =H$2 -> 5 | I11: =I$2 -> 5 | J11: =J$2 -> 5 | K11: =$B11 -> 15 | L11: =L$2 -> 15 | M11: =$B11 -> 15 | N11: =$B11 -> 15 | O11: =$B11 -> 15 | P11: =$B11 -> 15 | Q11: =Q$2 -> 15 | R11: =R$2 -> 5 | S11: =S$2 -> 5 | T11: =T$2 -> 5 | U11: =U$2 -> 5 | V11: =V$2 -> 10 | W11: =W$2 -> 7 | X11: =$B11 -> 15 | Y11: =Y$2 -> 7 | Z11: =$B11 -> 15 | AA11: =$B11 -> 15 | AB11: =$B11 -> 15 | AC11: =$B11 -> 15 | AD11: =$B11 -> 15 | AE11: =$B11 -> 15 | AF11: =$B11 -> 15 | AG11: =$B11 -> 15 | AH11: =$B11 -> 15 | AI11: =AI$2 -> 39 | AJ11: =AJ$2 -> 39 | AK11: =AK$2 -> 39 | AL11: =AL$2 -> 7 | AM11: =AM$2 -> 39 | AN11: =AN$2 -> 39 | AO11: =$B11 -> 15 | AP11: =$B11 -> 15 | AQ11: =AQ$2 -> 5 | AR11: =AR$2 -> 5 | AS11: =AS$2 -> 20 | AT11: =AT$2 -> 15 | AU11: =AU$2 -> 15 | AV11: =AV$2 -> 7 | AW11: =AW$2 -> 7 | AX11: =AX$2 -> 39 | ... BF11: =BF$2 -> 25 | BG11: =$B11 -> 15 | BH11: =BH$2 -> 7 | BI11: =BI$2 -> 2 | BJ11: =BJ$2 -> 5 | BK11: =BK$2 -> 1 | BL11: =BL$2 -> 10 | BM11: =BM$2 -> 10 | BN11: =BN$2 -> 5 | BO11: =BO$2 -> 1 | ... CI11: =CI$2 -> 0
A12: Other_Electric_Power_Generation | B12: 7 | C12: =C$2 -> 5 | D12: =D$2 -> 7 | E12: =$B12 -> 7 | F12: =$B12 -> 7 | G12: =$B12 -> 7 | H12: =H$2 -> 5 | I12: =I$2 -> 5 | J12: =J$2 -> 5 | K12: =$B12 -> 7 | L12: =L$2 -> 15 | M12: =$B12 -> 7 | N12: =$B12 -> 7 | O12: =$B12 -> 7 | P12: =$B12 -> 7 | Q12: =Q$2 -> 15 | R12: =R$2 -> 5 | S12: =S$2 -> 5 | T12: =T$2 -> 5 | U12: =U$2 -> 5 | V12: =V$2 -> 10 | W12: =W$2 -> 7 | X12: =$B12 -> 7 | Y12: =Y$2 -> 7 | Z12: =$B12 -> 7 | AA12: =$B12 -> 7 | AB12: =$B12 -> 7 | AC12: =$B12 -> 7 | AD12: =$B12 -> 7 | AE12: =$B12 -> 7 | AF12: =$B12 -> 7 | AG12: =$B12 -> 7 | AH12: =$B12 -> 7 | AI12: =AI$2 -> 39 | AJ12: =AJ$2 -> 39 | AK12: =AK$2 -> 39 | AL12: =AL$2 -> 7 | AM12: =AM$2 -> 39 | AN12: =AN$2 -> 39 | AO12: =AO$2 -> 20 | AP12: =AP$2 -> 20 | ... CI12: =CI$2 -> 0
A13: Electric_Power_Transmission_and_Distribution | B13: 20 | C13: =C$2 -> 5 | D13: =D$2 -> 7 | E13: =$B13 -> 20 | F13: =$B13 -> 20 | G13: =$B13 -> 20 | H13: =H$2 -> 5 | I13: =I$2 -> 5 | J13: =J$2 -> 5 | K13: =$B13 -> 20 | L13: =L$2 -> 15 | M13: =$B13 -> 20 | N13: =$B13 -> 20 | O13: =$B13 -> 20 | P13: =$B13 -> 20 | Q13: =$B13 -> 20 | R13: =R$2 -> 5 | S13: =S$2 -> 5 | T13: =T$2 -> 5 | U13: =U$2 -> 5 | V13: =V$2 -> 10 | W13: =W$2 -> 7 | X13: =$B13 -> 20 | Y13: =Y$2 -> 7 | Z13: =$B13 -> 20 | AA13: =$B13 -> 20 | AB13: =$B13 -> 20 | AC13: =$B13 -> 20 | AD13: =$B13 -> 20 | AE13: =$B13 -> 20 | AF13: =$B13 -> 20 | AG13: =$B13 -> 20 | AH13: =$B13 -> 20 | AI13: =AI$2 -> 39 | AJ13: =AJ$2 -> 39 | AK13: =AK$2 -> 39 | AL13: =AL$2 -> 7 | AM13: =AM$2 -> 39 | AN13: =AN$2 -> 39 | AO13: =AO$2 -> 20 | AP13: =AP$2 -> 20 | ... BF13: =BF$2 -> 25 | BG13: =$B13 -> 20 | BH13: =BH$2 -> 7 | BI13: =BI$2 -> 2 | BJ13: =BJ$2 -> 5 | BK13: =BK$2 -> 1 | BL13: =BL$2 -> 10 | BM13: =BM$2 -> 10 | BN13: =BN$2 -> 5 | BO13: =BO$2 -> 1 | ... CI13: =CI$2 -> 0
